Workbook

Sheet Valuation
A1: Alphabet | valuation framework
A2: USD millions. Operating DCF versus adjusted market EV; aggregate equity bridge retained. No per-share inputs or outputs.
A3: Selected scenario | B3: =Assumptions!B3 -> Base
A4: Valuation date | B4: =Assumptions!B4 -> 46320
A6: Market inputs / enterprise bridge | B6: Input | C6: Basis
A7: Market capitalisation | B7: ='Discount rate'!B7 -> 3916000 | C7: Common equity market value at the agreed valuation date; source directly, without diluted-share multiplication.
A8: Unpaid legal settlement claim proxy | B8: ='Financial assets'!B37 -> 12156 | C8: June legal accrual less known July payment; provisional carrying-value proxy, separate from recurring FCFF.
A9: US Treasury risk-free rate | B9: ='Sources and basis'!B89 -> 0.05 | C9: 23 October 2026 US Treasury 10-year par yield; source in Sources and basis.
A10: Operating-business levered beta | B10: ='Discount rate'!B16 -> 1.0758505 | C10: Bottom-up / cash-adjusted beta research
A11: Implied equity risk premium | B11: ='Discount rate'!B9 -> 0.042 | C11: Latest monthly ERP available at 25 October: 1 October 2026.
A12: Pre-tax cost of debt | B12: ='Discount rate'!B30 -> 0.054 | C12: Valuation-date borrowing yield
A13: Debt market value, ex finance leases | B13: ='Discount rate'!B22 -> 101586 | C13: Current and long-term financing claims
A14: Preferred market claim | B14: ='Discount rate'!B36 -> 17804.325 | C14: Mandatory conversion terms; avoid adding shares and claim together
A15: Preferred required return | B15: ='Discount rate'!B37 -> 0.09518572 | C15: Dividend and conversion economics
A16: Finance lease claim proxy | B16: ='Sources and basis'!B55 -> 2590 | C16: Lease PP&E is included; book value used as the market-value proxy (disclosed approximation)
A17: Non-controlling interest value | B17: =IF(ISNUMBER('Discount rate'!B50),'Discount rate'!B50,"") -> 7100 | C17: Book value, deducted in full; Waymo share not disclosed (may overstate claims by up to 7,100)
A18: Credited excess cash | B18: =IF(ISNUMBER('Financial assets'!B33),'Financial assets'!B33,"") -> 26051.53 | C18: Required operating cash excluded
A19: Credited marketable investments | B19: =IF(COUNT('Financial assets'!H7:H10)=4,SUM('Financial assets'!H7:H10),"") -> 170751.74 | C19: Liquidity restrictions and valuation uncertainty assessed
A20: Credited non-marketable investments | B20: =IF(COUNT('Financial assets'!H11:H12)=2,SUM('Financial assets'!H11:H12),"") -> 110463.2 | C20: Valuation uncertainty and taxes assessed
A21: Terminal growth | B21: =Assumptions!B197 -> 0.03 | C21: ="Base 3.0% (Bear 2.0%, Bull 3.5%); below WACC and the "&TEXT('Discount rate'!B8,"0.00%")&" Treasury yield" -> Base 3.0% (Bear 2.0%, Bull 3.5%); below WACC and the 5.00% Treasury yield
A22: Terminal return on capital | B22: =Transition!B25 -> 0.12 | C22: Base ceiling 12%, Bull 16%, Bear current WACC; also capped at each scenario's starting return. Terminal reinvestment = growth / return.
A23: Baseline reviewed for valuation | B23: FALSE | C23: Group sign-off remains pending. Estimated June-to-October cash bridge, tax bases and book-value NCI are disclosed approximations.
A24: Mid-year discounting (1 = on, 0 = year-end) | B24: 1 | C24: Cash flows assumed mid-period; H2 2026 stub at its midpoint; terminal value shifted once through Transition!G19.
A26: Cost of equity | B26: =IF(COUNT(B9:B11)=3,B9+B10*B11,"") -> 0.09518572
A27: Market value of common equity | B27: =IF(ISNUMBER(B7),B7,"") -> 3916000
A28: Total financing value | B28: =IF(AND(ISNUMBER(B27),COUNT(B13:B14)=2,ISNUMBER(B16)),SUM(B27,B13:B14,B16),"") -> 4037980.3
A29: WACC | B29: =IF(AND(COUNT(B12:B16)=5,ISNUMBER(B26),ISNUMBER(B28),B28>0),B27/B28*B26+(B13+B16)/B28*B12*(1-Assumptions!B5)+B14/B28*B15,"") -> 0.093830607 | C29: Indicative estimate; see Discount rate for dated evidence and approximation choices.
A30: Valuation readiness | B30: =IF(COUNT(B7:B22)<16,"Market / bridge inputs pending",IF(NOT(B23),"Baseline review pending",IF(OR(B29<=B21,B22<=B21),"Review terminal assumptions","Ready"))) -> Baseline review pending
A33: Discounted cash flow | B33: H2 2026 | C33: 2027 | D33: 2028 | E33: 2029 | F33: 2030 | G33: 2031
A34: Cash-flow date | B34: =DATE(2026,12,31) -> 46387 | C34: =DATE(2027,12,31) -> 46752 | D34: =DATE(2028,12,31) -> 47118 | E34: =DATE(2029,12,31) -> 47483 | F34: =DATE(2030,12,31) -> 47848 | G34: =DATE(2031,12,31) -> 48213
A35: Years from valuation date | B35: =YEARFRAC($B$4,B34,3)*IF($B$24=1,0.5,1) -> 0.091780822 | C35: =YEARFRAC($B$4,C34,3)-IF($B$24=1,0.5,0) -> 0.68356164 | D35: =YEARFRAC($B$4,D34,3)-IF($B$24=1,0.5,0) -> 1.6863014 | E35: =YEARFRAC($B$4,E34,3)-IF($B$24=1,0.5,0) -> 2.6863014 | F35: =YEARFRAC($B$4,F34,3)-IF($B$24=1,0.5,0) -> 3.6863014 | G35: =YEARFRAC($B$4,G34,3)-IF($B$24=1,0.5,0) -> 4.6863014
A36: Remaining-period fraction | B36: =(B34-$B$4)/(B34-DATE(2026,6,30)) -> 0.36413043 | C36: =1 -> 1 | D36: =1 -> 1 | E36: =1 -> 1 | F36: =1 -> 1 | G36: =1 -> 1
A37: Model FCFF | B37: ='Capital and FCFF'!B38 -> -28017.165 | C37: ='Capital and FCFF'!C38 -> 713.39555 | D37: ='Capital and FCFF'!D38 -> 45919.555 | E37: ='Capital and FCFF'!E38 -> 72623.186 | F37: ='Capital and FCFF'!F38 -> 109739.81 | G37: ='Capital and FCFF'!G38 -> 145130.84
A38: Cash flow after valuation date | B38: =B37*B36 -> -10201.902 | C38: =C37*C36 -> 713.39555 | D38: =D37*D36 -> 45919.555 | E38: =E37*E36 -> 72623.186 | F38: =F37*F36 -> 109739.81 | G38: =G37*G36 -> 145130.84
A39: Present value | B39: =IF(AND(ISNUMBER($B$29),$B$29>0),B38/(1+$B$29)^B35,"") -> -10118.271 | C39: =IF(AND(ISNUMBER($B$29),$B$29>0),C38/(1+$B$29)^C35,"") -> 670.97389 | D39: =IF(AND(ISNUMBER($B$29),$B$29>0),D38/(1+$B$29)^D35,"") -> 39474.452 | E39: =IF(AND(ISNUMBER($B$29),$B$29>0),E38/(1+$B$29)^E35,"") -> 57074.704 | F39: =IF(AND(ISNUMBER($B$29),$B$29>0),F38/(1+$B$29)^F35,"") -> 78846.514 | G39: =IF(AND(ISNUMBER($B$29),$B$29>0),G38/(1+$B$29)^G35,"") -> 95329.638
A42: Terminal NOPAT | B42: =Transition!H13 -> 286781.19
A43: Terminal reinvestment rate | B43: =Transition!H14 -> 0.25
A44: Terminal FCFF | B44: =Transition!H16 -> 215085.89
A45: Terminal value | B45: =IF(AND(ISNUMBER(B29),B29>B21,B22>B21),B44/(B29-B21),"") -> 3369635.7
A46: Present value of terminal value | B46: =IF(ISNUMBER(B45),B45/(1+B29)^Transition!G19,"") -> 1412821.8
A48: Indicative operating enterprise value | B48: =IF(AND(COUNT(B39:G39)=6,COUNT(Transition!C20:G20)=5,ISNUMBER(B46)),SUM(B39:G39)+SUM(Transition!C20:G20)+B46,"") -> 2167268.3
A49: Non-operating assets credited | B49: =IF(COUNT(B18:B20)=3,SUM(B18:B20),"") -> 307266.47
A50: Financing, minority and settlement claims | B50: =IF(COUNT(B8,B13:B14,B16:B17)=5,SUM(B8,B13:B14,B16:B17),"") -> 141236.33
A51: Common equity value | B51: =IF(AND(B30="Ready",COUNT(B48:B50)=3),B48+B49-B50,"")
A52: Market-implied operating EV | B52: =IF(AND(ISNUMBER(B27),ISNUMBER(B49),ISNUMBER(B50)),B27+B50-B49,"") -> 3749969.9
A53: Operating EV valuation gap (%) | B53: =IF(AND(B30="Ready",ISNUMBER(B48),ISNUMBER(B52),B52>0),B48/B52-1,"")
A54: Operating EV surplus / (shortfall) | B54: =IF(AND(B30="Ready",COUNT(B48,B52)=2),B48-B52,"")
A56: June financial reference balances | B56: USD million | C56: Not automatically credited at book value
A57: Cash / marketable securities | B57: ='Balance sheet'!I10 -> 242474
A58: Non-marketable investments | B58: ='Balance sheet'!I17 -> 131461
A59: Debt carrying value, ex leases | B59: ='Balance sheet'!I35+'Sources and basis'!E37 -> 100164
A60: Preferred book capital | B60: ='Balance sheet'!I44 -> 18023
A61: Non-controlling interest book value | B61: ='Sources and basis'!B54 -> 7100
A63: The October bridge estimates elapsed operating cash flow and dividends, includes disclosed financing and marks quoted investments. Tax bases, debt values and NCI retain proxies. Final outputs await group sign-off.
A64: Explicit FCFF through 2031 is followed by the Transition schedule for 2032–2036. Terminal value starts in 2037; no per-share target is calculated.
A65: Operating-EV and common-equity gaps use their respective market-value denominators. Simulation inputs and Relative valuation contain the completed Monte Carlo and SOTP cross-checks.
A68: Investment bridge design | B68: Amount | C68: Treatment
A69: Taxable gain on each holding | C69: Use supported tax basis and tax jurisdiction; do not tax the entire holding automatically.
A70: Deferred tax already accounted for | C70: Match each tax adjustment to the equity bridge so the same tax is not deducted twice.
A71: Liquidity / valuation adjustment | C71: Apply only with a stated basis, after separating tax from marketability risk.
A74: Waymo funding reference | B74: USD million | C74: Not added to the consolidated DCF
A75: February 2026 post-money equity value | B75: ='Sources and basis'!B90 -> 126000 | C75: External transaction reference; financing rights and information cutoff matter.
A76: Funding raised | B76: ='Sources and basis'!B91 -> 16000 | C76: Cash raised is not the valuation.
A77: Alphabet attributable ownership | B77: 60-90% | C77: Not disclosed (majority investor); range used as a sensitivity in Relative valuation rows 39-40.
A78: Attributable equity reference | B78: 75,600-113,400 | C78: Post-money x ownership range; a funding price is not intrinsic value.
A79: SOTP treatment | B79: Done | C79: Relative valuation tab: Waymo at attributable value, all Waymo cash removed from the bridge, NCI kept in claims.
A82: Outstanding valuation work | B82: Status
A83: Market inputs / ERP vintage | B83: Done | C83: 25 October 2026 information cutoff; 23 October closes and Treasury yield; 1 October implied ERP. Source dates and balance-sheet proxies are identified in Discount rate.
A84: Investment tax bases / marketability | B84: Done (proxies) | C84: Tax-basis proxies and haircuts in Financial assets; zero-basis stress shown there.
A85: Cloud capacity / revenue linkage | B85: Done | C85: Capacity coverage in Cloud demand rows 17-19; requirement in Assumptions row 234.
A86: Cash taxes / replacement calibration | B86: Done (normalised rate) | C86: 18% normalised tax fading to 21%; renewal floors in Capital and FCFF (none binding).
A87: Monte Carlo distribution / SOTP | B87: Done | C87: Simulation inputs and Relative valuation tabs; Python replica matches Base, Bull and Bear.
A94: Discount-rate sensitivity | operating EV
A95: WACC change | B95: WACC | C95: Operating EV
A96: -0.02 | B96: =$B$29+A96 -> 0.073830607 | C96: =IF(B96>$B$21,SUMPRODUCT($B$38:$G$38,1/(1+B96)^$B$35:$G$35)+SUMPRODUCT(Transition!$C$16:$G$16,1/(1+B96)^Transition!$C$19:$G$19)+$B$44/(B96-$B$21)/(1+B96)^Transition!$G$19,"") -> 3308195.7
A97: -0.01 | B97: =$B$29+A97 -> 0.083830607 | C97: =IF(B97>$B$21,SUMPRODUCT($B$38:$G$38,1/(1+B97)^$B$35:$G$35)+SUMPRODUCT(Transition!$C$16:$G$16,1/(1+B97)^Transition!$C$19:$G$19)+$B$44/(B97-$B$21)/(1+B97)^Transition!$G$19,"") -> 2630591.7
A98: 0 | B98: =$B$29+A98 -> 0.093830607 | C98: =IF(B98>$B$21,SUMPRODUCT($B$38:$G$38,1/(1+B98)^$B$35:$G$35)+SUMPRODUCT(Transition!$C$16:$G$16,1/(1+B98)^Transition!$C$19:$G$19)+$B$44/(B98-$B$21)/(1+B98)^Transition!$G$19,"") -> 2167268.3
A99: 0.01 | B99: =$B$29+A99 -> 0.10383061 | C99: =IF(B99>$B$21,SUMPRODUCT($B$38:$G$38,1/(1+B99)^$B$35:$G$35)+SUMPRODUCT(Transition!$C$16:$G$16,1/(1+B99)^Transition!$C$19:$G$19)+$B$44/(B99-$B$21)/(1+B99)^Transition!$G$19,"") -> 1831079.8
A100: 0.02 | B100: =$B$29+A100 -> 0.11383061 | C100: =IF(B100>$B$21,SUMPRODUCT($B$38:$G$38,1/(1+B100)^$B$35:$G$35)+SUMPRODUCT(Transition!$C$16:$G$16,1/(1+B100)^Transition!$C$19:$G$19)+$B$44/(B100-$B$21)/(1+B100)^Transition!$G$19,"") -> 1576465.3
A103: Forecast cash flows and terminal operating assumptions are held fixed. This is discount-rate sensitivity, not Monte Carlo or a final investment recommendation.

Sheet Assumptions
A1: Alphabet | model assumptions
A2: PROVISIONAL BASELINE — editable scenarios; not a completed valuation or investment recommendation.
A3: Selected scenario | B3: Base
A4: Valuation date | B4: =DATE(2026,10,25) -> 46320
A5: Historical NOPAT tax benchmark | B5: 0.21
A6: Driver / scenario | B6: H2 2026 | C6: 2027 | D6: 2028 | E6: 2029 | F6: 2030 | G6: 2031 | H6: Rationale / evidence
A7: Search growth — active | B7: =INDEX(B8:B10,MATCH($B$3,$A8:$A10,0)) -> 0.17902223 | C7: =INDEX(C8:C10,MATCH($B$3,$A8:$A10,0)) -> 0.15 | D7: =INDEX(D8:D10,MATCH($B$3,$A8:$A10,0)) -> 0.13 | E7: =INDEX(E8:E10,MATCH($B$3,$A8:$A10,0)) -> 0.11 | F7: =INDEX(F8:F10,MATCH($B$3,$A8:$A10,0)) -> 0.09 | G7: =INDEX(G8:G10,MATCH($B$3,$A8:$A10,0)) -> 0.08 | H7: H2 base holds H1 YoY growth; later fade is provisional.
A8: Base | B8: ='Historical base'!E8/'Historical base'!D8-1 -> 0.17902223 | C8: 0.15 | D8: 0.13 | E8: 0.11 | F8: 0.09 | G8: 0.08
A9: Bull | B9: 0.22 | C9: 0.2 | D9: 0.18 | E9: 0.16 | F9: 0.14 | G9: 0.12
A10: Bear | B10: 0.1 | C10: 0.1 | D10: 0.08 | E10: 0.06 | F10: 0.04 | G10: 0.03
A12: YouTube advertising growth — active | B12: =INDEX(B13:B15,MATCH($B$3,$A13:$A15,0)) -> 0.11830369 | C12: =INDEX(C13:C15,MATCH($B$3,$A13:$A15,0)) -> 0.12 | D12: =INDEX(D13:D15,MATCH($B$3,$A13:$A15,0)) -> 0.11 | E12: =INDEX(E13:E15,MATCH($B$3,$A13:$A15,0)) -> 0.1 | F12: =INDEX(F13:F15,MATCH($B$3,$A13:$A15,0)) -> 0.09 | G12: =INDEX(G13:G15,MATCH($B$3,$A13:$A15,0)) -> 0.08 | H12: Advertising only; subscriptions remain within Services other revenue.
A13: Base | B13: ='Historical base'!E9/'Historical base'!D9-1 -> 0.11830369 | C13: 0.12 | D13: 0.11 | E13: 0.1 | F13: 0.09 | G13: 0.08
A14: Bull | B14: 0.16 | C14: 0.16 | D14: 0.15 | E14: 0.14 | F14: 0.13 | G14: 0.12
A15: Bear | B15: 0.07 | C15: 0.07 | D15: 0.06 | E15: 0.05 | F15: 0.04 | G15: 0.03
A17: Network growth — active | B17: =INDEX(B18:B20,MATCH($B$3,$A18:$A20,0)) -> -0.022997947 | C17: =INDEX(C18:C20,MATCH($B$3,$A18:$A20,0)) -> -0.03 | D17: =INDEX(D18:D20,MATCH($B$3,$A18:$A20,0)) -> -0.03 | E17: =INDEX(E18:E20,MATCH($B$3,$A18:$A20,0)) -> -0.02 | F17: =INDEX(F18:F20,MATCH($B$3,$A18:$A20,0)) -> -0.02 | G17: =INDEX(G18:G20,MATCH($B$3,$A18:$A20,0)) -> -0.02 | H17: Reflects recent contraction; scenarios are analyst inputs.
A18: Base | B18: ='Historical base'!E10/'Historical base'!D10-1 -> -0.022997947 | C18: -0.03 | D18: -0.03 | E18: -0.02 | F18: -0.02 | G18: -0.02
A19: Bull | B19: 0 | C19: 0 | D19: 0.01 | E19: 0.02 | F19: 0.02 | G19: 0.02
A20: Bear | B20: -0.08 | C20: -0.08 | D20: -0.07 | E20: -0.06 | F20: -0.05 | G20: -0.05
A22: Subscriptions / devices growth — active | B22: =INDEX(B23:B25,MATCH($B$3,$A23:$A25,0)) -> 0.17204152 | C22: =INDEX(C23:C25,MATCH($B$3,$A23:$A25,0)) -> 0.15 | D22: =INDEX(D23:D25,MATCH($B$3,$A23:$A25,0)) -> 0.13 | E22: =INDEX(E23:E25,MATCH($B$3,$A23:$A25,0)) -> 0.12 | F22: =INDEX(F23:F25,MATCH($B$3,$A23:$A25,0)) -> 0.1 | G22: =INDEX(G23:G25,MATCH($B$3,$A23:$A25,0)) -> 0.09 | H22: Includes subscriptions, platforms and devices.
A23: Base | B23: ='Historical base'!E11/'Historical base'!D11-1 -> 0.17204152 | C23: 0.15 | D23: 0.13 | E23: 0.12 | F23: 0.1 | G23: 0.09
A24: Bull | B24: 0.2 | C24: 0.2 | D24: 0.18 | E24: 0.16 | F24: 0.14 | G24: 0.13
A25: Bear | B25: 0.08 | C25: 0.08 | D25: 0.07 | E25: 0.06 | F25: 0.05 | G25: 0.04
A27: Cloud demand growth before backlog / delivery | B27: =INDEX(B28:B30,MATCH($B$3,$A28:$A30,0)) -> 0.73064441 | C27: =INDEX(C28:C30,MATCH($B$3,$A28:$A30,0)) -> 0.35 | D27: =INDEX(D28:D30,MATCH($B$3,$A28:$A30,0)) -> 0.25 | E27: =INDEX(E28:E30,MATCH($B$3,$A28:$A30,0)) -> 0.2 | F27: =INDEX(F28:F30,MATCH($B$3,$A28:$A30,0)) -> 0.16 | G27: =INDEX(G28:G30,MATCH($B$3,$A28:$A30,0)) -> 0.12 | H27: Reference demand taper; Cloud demand reconciles opening backlog, new business and delivery. Actual revenue growth is an output.
A28: Base | B28: ='Historical base'!E13/'Historical base'!D13-1 -> 0.73064441 | C28: 0.35 | D28: 0.25 | E28: 0.2 | F28: 0.16 | G28: 0.12
A29: Bull | B29: 0.85 | C29: 0.45 | D29: 0.35 | E29: 0.28 | F29: 0.23 | G29: 0.18
A30: Bear | B30: 0.45 | C30: 0.2 | D30: 0.15 | E30: 0.1 | F30: 0.08 | G30: 0.06
A32: Other Bets revenue growth — active | B32: =INDEX(B33:B35,MATCH($B$3,$A33:$A35,0)) -> 0.1 | C32: =INDEX(C33:C35,MATCH($B$3,$A33:$A35,0)) -> 0.1 | D32: =INDEX(D33:D35,MATCH($B$3,$A33:$A35,0)) -> 0.1 | E32: =INDEX(E33:E35,MATCH($B$3,$A33:$A35,0)) -> 0.1 | F32: =INDEX(F33:F35,MATCH($B$3,$A33:$A35,0)) -> 0.1 | G32: =INDEX(G33:G35,MATCH($B$3,$A33:$A35,0)) -> 0.1 | H32: Consolidated Other Bets, not a standalone Waymo valuation.
A33: Base | B33: 0.1 | C33: 0.1 | D33: 0.1 | E33: 0.1 | F33: 0.1 | G33: 0.1
A34: Bull | B34: 0.25 | C34: 0.25 | D34: 0.25 | E34: 0.2 | F34: 0.2 | G34: 0.2
A35: Bear | B35: 0 | C35: 0 | D35: 0 | E35: 0 | F35: 0 | G35: 0
A37: Services reference EBIT margin — active | B37: =INDEX(B38:B40,MATCH($B$3,$A38:$A40,0)) -> 0.4350869 | C37: =INDEX(C38:C40,MATCH($B$3,$A38:$A40,0)) -> 0.43 | D37: =INDEX(D38:D40,MATCH($B$3,$A38:$A40,0)) -> 0.43 | E37: =INDEX(E38:E40,MATCH($B$3,$A38:$A40,0)) -> 0.425 | F37: =INDEX(F38:F40,MATCH($B$3,$A38:$A40,0)) -> 0.42 | G37: =INDEX(G38:G40,MATCH($B$3,$A38:$A40,0)) -> 0.42 | H37: Common reference margin across cases; explicit TAC and AI-cost changes drive case differences.
A38: Base | B38: ='Historical base'!E26 -> 0.4350869 | C38: 0.43 | D38: 0.43 | E38: 0.425 | F38: 0.42 | G38: 0.42
A39: Bull | B39: =B38 -> 0.4350869 | C39: =C38 -> 0.43 | D39: =D38 -> 0.43 | E39: =E38 -> 0.425 | F39: =F38 -> 0.42 | G39: =G38 -> 0.42
A40: Bear | B40: =B38 -> 0.4350869 | C40: =C38 -> 0.43 | D40: =D38 -> 0.43 | E40: =E38 -> 0.425 | F40: =F38 -> 0.42 | G40: =G38 -> 0.42
A42: Cloud reference EBIT margin — active | B42: =INDEX(B43:B45,MATCH($B$3,$A43:$A45,0)) -> 0.34404858 | C42: =INDEX(C43:C45,MATCH($B$3,$A43:$A45,0)) -> 0.35 | D42: =INDEX(D43:D45,MATCH($B$3,$A43:$A45,0)) -> 0.36 | E42: =INDEX(E43:E45,MATCH($B$3,$A43:$A45,0)) -> 0.37 | F42: =INDEX(F43:F45,MATCH($B$3,$A43:$A45,0)) -> 0.38 | G42: =INDEX(G43:G45,MATCH($B$3,$A43:$A45,0)) -> 0.38 | H42: Reference margin; explicit capital schedule determines consolidated D&A.
A43: Base | B43: ='Historical base'!E27 -> 0.34404858 | C43: 0.35 | D43: 0.36 | E43: 0.37 | F43: 0.38 | G43: 0.38
A44: Bull | B44: 0.36 | C44: 0.38 | D44: 0.4 | E44: 0.41 | F44: 0.42 | G44: 0.42
A45: Bear | B45: 0.3 | C45: 0.29 | D45: 0.28 | E45: 0.28 | F45: 0.28 | G45: 0.28
A47: Other Bets cost growth — active | B47: =INDEX(B48:B50,MATCH($B$3,$A48:$A50,0)) -> 0.15 | C47: =INDEX(C48:C50,MATCH($B$3,$A48:$A50,0)) -> 0.15 | D47: =INDEX(D48:D50,MATCH($B$3,$A48:$A50,0)) -> 0.12 | E47: =INDEX(E48:E50,MATCH($B$3,$A48:$A50,0)) -> 0.1 | F47: =INDEX(F48:F50,MATCH($B$3,$A48:$A50,0)) -> 0.08 | G47: =INDEX(G48:G50,MATCH($B$3,$A48:$A50,0)) -> 0.05 | H47: Costs are positive loss magnitude; no speculative loss addback.
A48: Base | B48: 0.15 | C48: 0.15 | D48: 0.12 | E48: 0.1 | F48: 0.08 | G48: 0.05
A49: Bull | B49: 0.1 | C49: 0.1 | D49: 0.08 | E49: 0.05 | F49: 0 | G49: 0
A50: Bear | B50: 0.25 | C50: 0.25 | D50: 0.2 | E50: 0.15 | F50: 0.1 | G50: 0.1
A52: Shared AI research cost elasticity | B52: =INDEX(B53:B55,MATCH($B$3,$A53:$A55,0)) -> 0.8 | C52: =INDEX(C53:C55,MATCH($B$3,$A53:$A55,0)) -> 0.8 | D52: =INDEX(D53:D55,MATCH($B$3,$A53:$A55,0)) -> 0.8 | E52: =INDEX(E53:E55,MATCH($B$3,$A53:$A55,0)) -> 0.8 | F52: =INDEX(F53:F55,MATCH($B$3,$A53:$A55,0)) -> 0.8 | G52: =INDEX(G53:G55,MATCH($B$3,$A53:$A55,0)) -> 0.8 | H52: Applied to planned group demand growth from 2027. Other shared costs grow at the separate inflation rate.
A53: Base | B53: 0.8 | C53: 0.8 | D53: 0.8 | E53: 0.8 | F53: 0.8 | G53: 0.8
A54: Bull | B54: 0.65 | C54: 0.65 | D54: 0.65 | E54: 0.65 | F54: 0.65 | G54: 0.65
A55: Bear | B55: 1.1 | C55: 1.1 | D55: 1.1 | E55: 1.1 | F55: 1.1 | G55: 1.1
A57: Cash CapEx / revenue — active | B57: ="" | C57: =INDEX(C58:C60,MATCH($B$3,$A58:$A60,0)) -> 0.35 | D57: =INDEX(D58:D60,MATCH($B$3,$A58:$A60,0)) -> 0.3 | E57: =INDEX(E58:E60,MATCH($B$3,$A58:$A60,0)) -> 0.27 | F57: =INDEX(F58:F60,MATCH($B$3,$A58:$A60,0)) -> 0.24 | G57: =INDEX(G58:G60,MATCH($B$3,$A58:$A60,0)) -> 0.22 | H57: H2 uses annual guidance less H1 actual. Later intensity is provisional; replacement floor applies.
A58: Base | C58: 0.35 | D58: 0.3 | E58: 0.27 | F58: 0.24 | G58: 0.22
A59: Bull | C59: 0.36 | D59: 0.32 | E59: 0.28 | F59: 0.25 | G59: 0.23
A60: Bear | C60: 0.38 | D60: 0.35 | E60: 0.32 | F60: 0.29 | G60: 0.27
A62: Annual deployment rate — active | B62: =INDEX(B63:B65,MATCH($B$3,$A63:$A65,0)) -> 0.6 | C62: =INDEX(C63:C65,MATCH($B$3,$A63:$A65,0)) -> 0.6 | D62: =INDEX(D63:D65,MATCH($B$3,$A63:$A65,0)) -> 0.6 | E62: =INDEX(E63:E65,MATCH($B$3,$A63:$A65,0)) -> 0.6 | F62: =INDEX(F63:F65,MATCH($B$3,$A63:$A65,0)) -> 0.6 | G62: =INDEX(G63:G65,MATCH($B$3,$A63:$A65,0)) -> 0.6 | H62: Fraction commissioned from opening CIP plus half-period spend; applied pro rata in H2. Calibration on this convention (transfers = opening assets not in service + cash CapEx - closing): 60.4% in 2024, 65.9% in 2025, 61.2% in H1 2026 (10-K FY2024/FY2025, Q2 2026 10-Q PP&E notes).
A63: Base | B63: 0.6 | C63: 0.6 | D63: 0.6 | E63: 0.6 | F63: 0.6 | G63: 0.6
A64: Bull | B64: 0.8 | C64: 0.8 | D64: 0.8 | E64: 0.8 | F64: 0.8 | G64: 0.8
A65: Bear | B65: 0.4 | C65: 0.4 | D65: 0.4 | E65: 0.4 | F65: 0.4 | G65: 0.4
A67: New hardware economic life — active | B67: =INDEX(B68:B70,MATCH($B$3,$A68:$A70,0)) -> 5 | C67: =INDEX(C68:C70,MATCH($B$3,$A68:$A70,0)) -> 5 | D67: =INDEX(D68:D70,MATCH($B$3,$A68:$A70,0)) -> 5 | E67: =INDEX(E68:E70,MATCH($B$3,$A68:$A70,0)) -> 5 | F67: =INDEX(F68:F70,MATCH($B$3,$A68:$A70,0)) -> 5 | G67: =INDEX(G68:G70,MATCH($B$3,$A68:$A70,0)) -> 5 | H67: Economic replacement scenarios. Does not claim a change to reported historical depreciation.
A68: Base | B68: 5 | C68: 5 | D68: 5 | E68: 5 | F68: 5 | G68: 5
A69: Bull | B69: 6 | C69: 6 | D69: 6 | E69: 6 | F69: 6 | G69: 6
A70: Bear | B70: 4 | C70: 4 | D70: 4 | E70: 4 | F70: 4 | G70: 4
A72: Hardware share of commissioned assets — active | B72: =INDEX(B73:B75,MATCH($B$3,$A73:$A75,0)) -> 0.6 | C72: =INDEX(C73:C75,MATCH($B$3,$A73:$A75,0)) -> 0.6 | D72: =INDEX(D73:D75,MATCH($B$3,$A73:$A75,0)) -> 0.6 | E72: =INDEX(E73:E75,MATCH($B$3,$A73:$A75,0)) -> 0.6 | F72: =INDEX(F73:F75,MATCH($B$3,$A73:$A75,0)) -> 0.6 | G72: =INDEX(G73:G75,MATCH($B$3,$A73:$A75,0)) -> 0.6 | H72: Provisional allocation; net asset/cohort mix is not publicly disclosed.
A73: Base | B73: 0.6 | C73: 0.6 | D73: 0.6 | E73: 0.6 | F73: 0.6 | G73: 0.6
A74: Bull | B74: 0.6 | C74: 0.6 | D74: 0.6 | E74: 0.6 | F74: 0.6 | G74: 0.6
A75: Bear | B75: 0.6 | C75: 0.6 | D75: 0.6 | E75: 0.6 | F75: 0.6 | G75: 0.6
A77: Forecast operating tax rate — active | B77: =INDEX(B78:B80,MATCH($B$3,$A78:$A80,0)) -> 0.18 | C77: =INDEX(C78:C80,MATCH($B$3,$A78:$A80,0)) -> 0.18 | D77: =INDEX(D78:D80,MATCH($B$3,$A78:$A80,0)) -> 0.18 | E77: =INDEX(E78:E80,MATCH($B$3,$A78:$A80,0)) -> 0.18 | F77: =INDEX(F78:F80,MATCH($B$3,$A78:$A80,0)) -> 0.18 | G77: =INDEX(G78:G80,MATCH($B$3,$A78:$A80,0)) -> 0.18 | H77: Recurring operating rate from the FY2025 rate reconciliation: 16.8% reported, excluding unrecognised-tax-benefit releases (-0.7pp) and other US adjustments (-0.6pp). Fades to the 21% marginal rate (B149) over 2032-2036. Accelerated tax depreciation on CapEx would lower cash taxes further; not modelled.
A78: Base | B78: 0.18 | C78: 0.18 | D78: 0.18 | E78: 0.18 | F78: 0.18 | G78: 0.18
A79: Bull | B79: 0.18 | C79: 0.18 | D79: 0.18 | E79: 0.18 | F79: 0.18 | G79: 0.18
A80: Bear | B80: 0.18 | C80: 0.18 | D80: 0.18 | E80: 0.18 | F80: 0.18 | G80: 0.18
A82: Working-capital method | H82: Component schedule in Working capital; active assumptions at rows 103–141.
A88: Opening asset assumptions | B88: Value | C88: Basis
A89: Hardware share of opening in-service net PP&E | B89: 0.5 | C89: Provisional allocation; not a reported segment asset split.
A90: Remaining life of opening hardware | B90: 3 | C90: Years; existing net book value runs off over this period.
A91: Remaining life of other opening productive PP&E | B91: 15 | C91: Years; provisional blended buildings/other assets.
A92: Useful life of new non-hardware assets | B92: 20 | C92: Years; blended long-lived pool; separate land/buildings refinement remains.
A93: H2 2026 CapEx budget | B93: =AVERAGE('Sources and basis'!B51:B52)-'Historical base'!E35 -> 119402 | C93: Annual guidance midpoint less H1 actual cash CapEx.
A94: 2031 intangible amortisation assumption | B94: =MIN('Sources and basis'!B56,'Sources and basis'!I47) -> 1055 | C94: Not individually disclosed: capped carry-forward of 2030 schedule; provisional.
A95: Reference D&A / revenue | B95: =('Historical base'!E39+'Sources and basis'!D47)/'Historical base'!E16 -> 0.061521516 | C95: Removes H1 D&A burden from reference segment earnings before modelled D&A.
A96: Modelling status | B96: Provisional | C96: Backlog timing, capacity sensitivity, customer-funding exposure, asset mix and cash taxes remain provisional.
A98: Source and calibration: historical links refer to Historical base; guidance and intangible schedule refer to Sources and basis.
A99: Hardware life changes both depreciation and the replacement-spending floor. Deployment affects commissioning; revenue scenarios must be reviewed jointly.
A103: Receivable days — active | B103: =INDEX(B104:B106,MATCH($B$3,$A104:$A106,0)) -> 56.628841 | C103: =INDEX(C104:C106,MATCH($B$3,$A104:$A106,0)) -> 56.628841 | D103: =INDEX(D104:D106,MATCH($B$3,$A104:$A106,0)) -> 56.628841 | E103: =INDEX(E104:E106,MATCH($B$3,$A104:$A106,0)) -> 56.628841 | F103: =INDEX(F104:F106,MATCH($B$3,$A104:$A106,0)) -> 56.628841 | G103: =INDEX(G104:G106,MATCH($B$3,$A104:$A106,0)) -> 56.628841 | H103: June receivables / TTM sales × 365; unchanged collection speed until stronger evidence.
A104: Base | B104: ='Working capital'!$C$36 -> 56.628841 | C104: ='Working capital'!$C$36 -> 56.628841 | D104: ='Working capital'!$C$36 -> 56.628841 | E104: ='Working capital'!$C$36 -> 56.628841 | F104: ='Working capital'!$C$36 -> 56.628841 | G104: ='Working capital'!$C$36 -> 56.628841
A105: Bull | B105: ='Working capital'!$C$36 -> 56.628841 | C105: ='Working capital'!$C$36 -> 56.628841 | D105: ='Working capital'!$C$36 -> 56.628841 | E105: ='Working capital'!$C$36 -> 56.628841 | F105: ='Working capital'!$C$36 -> 56.628841 | G105: ='Working capital'!$C$36 -> 56.628841
A106: Bear | B106: ='Working capital'!$C$36 -> 56.628841 | C106: ='Working capital'!$C$36 -> 56.628841 | D106: ='Working capital'!$C$36 -> 56.628841 | E106: ='Working capital'!$C$36 -> 56.628841 | F106: ='Working capital'!$C$36 -> 56.628841 | G106: ='Working capital'!$C$36 -> 56.628841
A108: Inventory / revenue — active | B108: =INDEX(B109:B111,MATCH($B$3,$A109:$A111,0)) -> 0.022408078 | C108: =INDEX(C109:C111,MATCH($B$3,$A109:$A111,0)) -> 0.014231325 | D108: =INDEX(D109:D111,MATCH($B$3,$A109:$A111,0)) -> 0.0060545731 | E108: =INDEX(E109:E111,MATCH($B$3,$A109:$A111,0)) -> 0.0060545731 | F108: =INDEX(F109:F111,MATCH($B$3,$A109:$A111,0)) -> 0.0060545731 | G108: =INDEX(G109:G111,MATCH($B$3,$A109:$A111,0)) -> 0.0060545731 | H108: Normalises toward the reclassified FY2025 inventory/revenue ratio (0.61%), not zero. Timing remains a scenario assumption; TPU sales may raise the sustainable requirement.
A109: Base | B109: ='Working capital'!$C$37 -> 0.022408078 | C109: =AVERAGE('Working capital'!$B$37:$C$37) -> 0.014231325 | D109: ='Working capital'!$B$37 -> 0.0060545731 | E109: ='Working capital'!$B$37 -> 0.0060545731 | F109: ='Working capital'!$B$37 -> 0.0060545731 | G109: ='Working capital'!$B$37 -> 0.0060545731
A110: Bull | B110: ='Working capital'!$C$37 -> 0.022408078 | C110: ='Working capital'!$B$37 -> 0.0060545731 | D110: ='Working capital'!$B$37 -> 0.0060545731 | E110: ='Working capital'!$B$37 -> 0.0060545731 | F110: ='Working capital'!$B$37 -> 0.0060545731 | G110: ='Working capital'!$B$37 -> 0.0060545731
A111: Bear | B111: ='Working capital'!$C$37 -> 0.022408078 | C111: ='Working capital'!$C$37 -> 0.022408078 | D111: =AVERAGE('Working capital'!$B$37:$C$37) -> 0.014231325 | E111: ='Working capital'!$B$37 -> 0.0060545731 | F111: ='Working capital'!$B$37 -> 0.0060545731 | G111: ='Working capital'!$B$37 -> 0.0060545731
A113: Other operating assets / revenue — active | B113: =INDEX(B114:B116,MATCH($B$3,$A114:$A116,0)) -> 0.033157944 | C113: =INDEX(C114:C116,MATCH($B$3,$A114:$A116,0)) -> 0.033157944 | D113: =INDEX(D114:D116,MATCH($B$3,$A114:$A116,0)) -> 0.033157944 | E113: =INDEX(E114:E116,MATCH($B$3,$A114:$A116,0)) -> 0.033157944 | F113: =INDEX(F114:F116,MATCH($B$3,$A114:$A116,0)) -> 0.033157944 | G113: =INDEX(G114:G116,MATCH($B$3,$A114:$A116,0)) -> 0.033157944 | H113: June / TTM calibration; residual disclosures and acquisition effects limit precision.
A114: Base | B114: ='Working capital'!$C$38 -> 0.033157944 | C114: ='Working capital'!$C$38 -> 0.033157944 | D114: ='Working capital'!$C$38 -> 0.033157944 | E114: ='Working capital'!$C$38 -> 0.033157944 | F114: ='Working capital'!$C$38 -> 0.033157944 | G114: ='Working capital'!$C$38 -> 0.033157944
A115: Bull | B115: ='Working capital'!$C$38 -> 0.033157944 | C115: ='Working capital'!$C$38 -> 0.033157944 | D115: ='Working capital'!$C$38 -> 0.033157944 | E115: ='Working capital'!$C$38 -> 0.033157944 | F115: ='Working capital'!$C$38 -> 0.033157944 | G115: ='Working capital'!$C$38 -> 0.033157944
A116: Bear | B116: ='Working capital'!$C$38 -> 0.033157944 | C116: ='Working capital'!$C$38 -> 0.033157944 | D116: ='Working capital'!$C$38 -> 0.033157944 | E116: ='Working capital'!$C$38 -> 0.033157944 | F116: ='Working capital'!$C$38 -> 0.033157944 | G116: ='Working capital'!$C$38 -> 0.033157944
A118: Operating supplier payables / revenue — active | B118: =INDEX(B119:B121,MATCH($B$3,$A119:$A121,0)) -> 0.016464588 | C118: =INDEX(C119:C121,MATCH($B$3,$A119:$A121,0)) -> 0.016464588 | D118: =INDEX(D119:D121,MATCH($B$3,$A119:$A121,0)) -> 0.016464588 | E118: =INDEX(E119:E121,MATCH($B$3,$A119:$A121,0)) -> 0.016464588 | F118: =INDEX(F119:F121,MATCH($B$3,$A119:$A121,0)) -> 0.016464588 | G118: =INDEX(G119:G121,MATCH($B$3,$A119:$A121,0)) -> 0.016464588 | H118: June / TTM calibration; residual disclosures and acquisition effects limit precision.
A119: Base | B119: ='Working capital'!$C$39 -> 0.016464588 | C119: ='Working capital'!$C$39 -> 0.016464588 | D119: ='Working capital'!$C$39 -> 0.016464588 | E119: ='Working capital'!$C$39 -> 0.016464588 | F119: ='Working capital'!$C$39 -> 0.016464588 | G119: ='Working capital'!$C$39 -> 0.016464588
A120: Bull | B120: ='Working capital'!$C$39 -> 0.016464588 | C120: ='Working capital'!$C$39 -> 0.016464588 | D120: ='Working capital'!$C$39 -> 0.016464588 | E120: ='Working capital'!$C$39 -> 0.016464588 | F120: ='Working capital'!$C$39 -> 0.016464588 | G120: ='Working capital'!$C$39 -> 0.016464588
A121: Bear | B121: ='Working capital'!$C$39 -> 0.016464588 | C121: ='Working capital'!$C$39 -> 0.016464588 | D121: ='Working capital'!$C$39 -> 0.016464588 | E121: ='Working capital'!$C$39 -> 0.016464588 | F121: ='Working capital'!$C$39 -> 0.016464588 | G121: ='Working capital'!$C$39 -> 0.016464588
A123: Compensation accrual / revenue — active | B123: =INDEX(B124:B126,MATCH($B$3,$A124:$A126,0)) -> 0.033835278 | C123: =INDEX(C124:C126,MATCH($B$3,$A124:$A126,0)) -> 0.033835278 | D123: =INDEX(D124:D126,MATCH($B$3,$A124:$A126,0)) -> 0.033835278 | E123: =INDEX(E124:E126,MATCH($B$3,$A124:$A126,0)) -> 0.033835278 | F123: =INDEX(F124:F126,MATCH($B$3,$A124:$A126,0)) -> 0.033835278 | G123: =INDEX(G124:G126,MATCH($B$3,$A124:$A126,0)) -> 0.033835278 | H123: June / TTM calibration; residual disclosures and acquisition effects limit precision.
A124: Base | B124: ='Working capital'!$C$40 -> 0.033835278 | C124: ='Working capital'!$C$40 -> 0.033835278 | D124: ='Working capital'!$C$40 -> 0.033835278 | E124: ='Working capital'!$C$40 -> 0.033835278 | F124: ='Working capital'!$C$40 -> 0.033835278 | G124: ='Working capital'!$C$40 -> 0.033835278
A125: Bull | B125: ='Working capital'!$C$40 -> 0.033835278 | C125: ='Working capital'!$C$40 -> 0.033835278 | D125: ='Working capital'!$C$40 -> 0.033835278 | E125: ='Working capital'!$C$40 -> 0.033835278 | F125: ='Working capital'!$C$40 -> 0.033835278 | G125: ='Working capital'!$C$40 -> 0.033835278
A126: Bear | B126: ='Working capital'!$C$40 -> 0.033835278 | C126: ='Working capital'!$C$40 -> 0.033835278 | D126: ='Working capital'!$C$40 -> 0.033835278 | E126: ='Working capital'!$C$40 -> 0.033835278 | F126: ='Working capital'!$C$40 -> 0.033835278 | G126: ='Working capital'!$C$40 -> 0.033835278
A128: Revenue-share accrual / revenue — active | B128: =INDEX(B129:B131,MATCH($B$3,$A129:$A131,0)) -> 0.023771716 | C128: =INDEX(C129:C131,MATCH($B$3,$A129:$A131,0)) -> 0.023771716 | D128: =INDEX(D129:D131,MATCH($B$3,$A129:$A131,0)) -> 0.023771716 | E128: =INDEX(E129:E131,MATCH($B$3,$A129:$A131,0)) -> 0.023771716 | F128: =INDEX(F129:F131,MATCH($B$3,$A129:$A131,0)) -> 0.023771716 | G128: =INDEX(G129:G131,MATCH($B$3,$A129:$A131,0)) -> 0.023771716 | H128: June / TTM calibration; residual disclosures and acquisition effects limit precision.
A129: Base | B129: ='Working capital'!$C$41 -> 0.023771716 | C129: ='Working capital'!$C$41 -> 0.023771716 | D129: ='Working capital'!$C$41 -> 0.023771716 | E129: ='Working capital'!$C$41 -> 0.023771716 | F129: ='Working capital'!$C$41 -> 0.023771716 | G129: ='Working capital'!$C$41 -> 0.023771716
...

Sheet Discount rate
A1: Alphabet | discount rate and financing claims
A2: USD millions except prices, percentages and ratios. Valuation/information cutoff: 25 October 2026; market closes: 23 October. June balance-sheet proxies and subsequent-event estimates are identified.
A3: Selected case | B3: =Assumptions!B3 -> Base
A4: Valuation date | B4: =Assumptions!B4 -> 46320
A6: Market input | B6: Value | C6: Basis / source
A7: Common-equity market capitalisation | B7: 3916000 | C7: 23 October 2026 group market capitalisation, rounded USDm. https://ycharts.com/companies/GOOGL/market_cap
A8: US Treasury yield | B8: ='Sources and basis'!B89 -> 0.05 | C8: 23 October 2026 US Treasury 10-year par yield: 5.00%. Treasury-based ERP convention.
A9: Damodaran implied ERP | B9: 0.042 | C9: 1 October 2026 implied ERP, trailing-12-month adjusted payout, Treasury convention: 4.20%. https://pages.stern.nyu.edu/adamodar/New_Home_Page/home.htm
A11: Operating beta build | B11: TTM revenue | C11: Revenue weight | D11: Cash-adjusted unlevered beta | E11: Basis
A12: Google Services | B12: ='Historical base'!F12 -> 367091 | C12: =B12/SUM($B$12:$B$14) -> 0.82267741 | D12: 1.01 | E12: Advertising industry proxy; January 2026 US sector data.
A13: Google Cloud | B13: ='Historical base'!F13 -> 77617 | C13: =B13/SUM($B$12:$B$14) -> 0.1739453 | D13: 1.25 | E13: System & application software proxy; infrastructure exposure warrants sensitivity.
A14: Other Bets | B14: ='Historical base'!F14 -> 1507 | C14: =B14/SUM($B$12:$B$14) -> 0.0033772957 | D14: 1.59 | E14: Internet software proxy; small revenue weight understates early-stage option value. Review through SOTP.
A15: Weighted operating beta | B15: =SUMPRODUCT(C12:C14,D12:D14) -> 1.0537057 | C15: Revenue weighting is a provisional substitute for business-value weights; not a regression estimate.
A16: Operating levered beta | B16: =B15*(1+(1-Assumptions!$B$5)*(B22+B23)/B7) -> 1.0758505 | C16: Relever using market debt/common equity. Portfolio leverage approximation; test against alternate peer weights.
A17: Cost of common equity | B17: =B8+B16*B9 -> 0.09518572 | C17: CAPM; https://pages.stern.nyu.edu/adamodar/New_Home_Page/datafile/Betas.html
A19: Debt and financing claims | B19: Amount | C19: Basis
A20: June quoted notes fair value | B20: 94900 | C20: June 2026 quoted notes fair value carried forward as a proxy, not an October bond quote.
A21: Other long-term debt proxy | B21: =1686+'Financial assets'!B70 -> 6686 | C21: June other debt 1,686 plus Waymo's USD5,000m term loan closed 8 October 2026; face value proxy. https://blog.waymo.com/blog/2026/10/waymo-closes-5-billion-debt-financing/
A22: Debt excluding finance leases | B22: =SUM(B20:B21) -> 101586 | C22: Avoid adding the current note portion again; included in outstanding-note fair value.
A23: Finance lease claim | B23: ='Sources and basis'!B55 -> 2590 | C23: June carrying-value proxy; already separate in the enterprise bridge.
A25: Borrowing-cost estimate | B25: Value | C25: Basis
A26: H1 EBIT | B26: ='Historical base'!E24 -> 80466 | C26: Six-month operating earnings; used only to assess interest coverage.
A27: H1 interest expense incl. capitalised | B27: =1811+628 -> 2439 | C27: Q2 2026 Note 7; capitalised interest included to avoid overstating coverage.
A28: Interest coverage | B28: =B26/B27 -> 32.99139 | C28: Same-period numerator and denominator.
A29: Synthetic credit spread | B29: 0.004 | C29: January 2026 Aaa/AAA coverage category synthetic spread; not an observed October traded yield. https://pages.stern.nyu.edu/adamodar/New_Home_Page/datafile/ratings.html
A30: Pre-tax borrowing cost | B30: =B8+B29 -> 0.054 | C30: Treasury plus synthetic spread; test ±50 bps. A dated traded-bond yield can replace this estimate.
A32: Mandatory convertible preferred | B32: Value | C32: Basis
A33: Total depositary shares (millions) | B33: 385 | C33: Q2 2026 Note 11; split evenly between Series A/B.
A34: Series A depositary closing price | B34: 46.32 | C34: 23 October 2026 close, GOOGM. https://www.quiverquant.com/stock/GOOGM/historical-prices/
A35: Series B depositary closing price | B35: 46.17 | C35: 23 October 2026 close, GOOGN. https://businessquant.com/stocks/googn/
A36: Preferred market claim | B36: =B33/2*(B34+B35) -> 17804.325 | C36: Market value includes conversion rights; no additional common-share dilution adjustment.
A37: Preferred required return assumption | B37: =B17 -> 0.09518572 | C37: Uses common-equity cost as a provisional equity-like risk proxy, not the 6.25% coupon or current dividend yield.
A38: Preferred-return WACC sensitivity | B38: =B36/(B7+B22+B23+B36)*(B37-B30) -> 0.00018159671 | C38: WACC change if preferred required return falls from common-equity cost to borrowing cost.
A40: Weighted average cost of capital | B40: Value | C40: Basis
A41: Total financing value | B41: =SUM(B7,B22:B23,B36) -> 4037980.3 | C41: Market values, with June debt and lease proxies.
A42: Common equity weight | B42: =B7/B41 -> 0.96979175
A43: Debt weight | B43: =SUM(B22:B23)/B41 -> 0.025799036
A44: Preferred weight | B44: =B36/B41 -> 0.0044092154
A45: Indicative WACC | B45: =B42*B17+B43*B30*(1-Assumptions!B5)+B44*B37 -> 0.093830607 | C45: One date, one base discount rate; model remains provisional pending peer and market-input review.
A48: NCI / ownership claim | B48: Value | C48: Basis
A49: Reported NCI including redeemable NCI | B49: ='Sources and basis'!B54 -> 7100 | C49: Book value reference only; not automatically credited as market claim.
A50: NCI market-value estimate | B50: =B49 -> 7100 | C50: Book value used as the claim. Waymo's outside stake at the USD 126bn Feb 2026 post-money is not disclosed; a 10-20% outside stake would add about USD 5-18bn of claims (0.1-0.4% of market cap).
A53: Sources: Alphabet Q2 2026 Form 10-Q; Waymo 8 October financing; Treasury 23 October yield; Damodaran January betas/spreads and October ERP; dated market quotes.
A54: Revenue-weighted sector beta and June debt/lease carry-forwards are proxies. The October Waymo borrowing is added explicitly. Preferred cost uses equity risk; its small weight limits WACC sensitivity.
A55: Capped calls are separate assets; issuance premium is not current value. Their unresolved valuation is flagged in Financial assets and must be addressed before a final equity conclusion.

Sheet Operating forecast
A1: Alphabet | operating forecast
A2: USD millions. Provisional scenarios; reference segment margins are adjusted for the explicit group depreciation schedule.
A3: Selected case | B3: =Assumptions!B3 -> Base
A6: Revenue and earnings | B6: FY2025 A | C6: H1 2026 A | D6: TTM Jun26 | E6: H2 2026 E | F6: FY2026 E | G6: 2027 E | H6: 2028 E | I6: 2029 E | J6: 2030 E | K6: 2031 E
A8: Search & other | B8: ='Historical base'!C8 -> 224532 | C8: ='Historical base'!E8 -> 123670 | D8: ='Historical base'!F8 -> 243310 | E8: =('Historical base'!C8-'Historical base'!D8)*(1+Assumptions!B7) -> 141058.22 | F8: =C8+E8 -> 264728.22 | G8: =F8*(1+Assumptions!C7) -> 304437.45 | H8: =G8*(1+Assumptions!D7) -> 344014.32 | I8: =H8*(1+Assumptions!E7) -> 381855.9 | J8: =I8*(1+Assumptions!F7) -> 416222.93 | K8: =J8*(1+Assumptions!G7) -> 449520.76
A9: YouTube advertising | B9: ='Historical base'!C9 -> 40367 | C9: ='Historical base'!E9 -> 20938 | D9: ='Historical base'!F9 -> 42582 | E9: =('Historical base'!C9-'Historical base'!D9)*(1+Assumptions!B12) -> 24204.565 | F9: =C9+E9 -> 45142.565 | G9: =F9*(1+Assumptions!C12) -> 50559.673 | H9: =G9*(1+Assumptions!D12) -> 56121.237 | I9: =H9*(1+Assumptions!E12) -> 61733.361 | J9: =I9*(1+Assumptions!F12) -> 67289.363 | K9: =J9*(1+Assumptions!G12) -> 72672.512
A10: Google Network | B10: ='Historical base'!C10 -> 29792 | C10: ='Historical base'!E10 -> 14274 | D10: ='Historical base'!F10 -> 29456 | E10: =('Historical base'!C10-'Historical base'!D10)*(1+Assumptions!B17) -> 14832.845 | F10: =C10+E10 -> 29106.845 | G10: =F10*(1+Assumptions!C17) -> 28233.64 | H10: =G10*(1+Assumptions!D17) -> 27386.631 | I10: =H10*(1+Assumptions!E17) -> 26838.898 | J10: =I10*(1+Assumptions!F17) -> 26302.12 | K10: =J10*(1+Assumptions!G17) -> 25776.078
A11: Subscriptions / devices | B11: ='Historical base'!C11 -> 48030 | C11: ='Historical base'!E11 -> 25295 | D11: ='Historical base'!F11 -> 51743 | E11: =('Historical base'!C11-'Historical base'!D11)*(1+Assumptions!B22) -> 30998.154 | F11: =C11+E11 -> 56293.154 | G11: =F11*(1+Assumptions!C22) -> 64737.127 | H11: =G11*(1+Assumptions!D22) -> 73152.954 | I11: =H11*(1+Assumptions!E22) -> 81931.308 | J11: =I11*(1+Assumptions!F22) -> 90124.439 | K11: =J11*(1+Assumptions!G22) -> 98235.638
A12: Google Services | B12: ='Historical base'!C12 -> 342721 | C12: ='Historical base'!E12 -> 184177 | D12: ='Historical base'!F12 -> 367091 | E12: =SUM(E8:E11) -> 211093.78 | F12: =C12+E12 -> 395270.78 | G12: =SUM(G8:G11) -> 447967.89 | H12: =SUM(H8:H11) -> 500675.14 | I12: =SUM(I8:I11) -> 552359.46 | J12: =SUM(J8:J11) -> 599938.85 | K12: =SUM(K8:K11) -> 646204.99
A13: Google Cloud | B13: ='Historical base'!C13 -> 58705 | C13: ='Historical base'!E13 -> 44796 | D13: ='Historical base'!F13 -> 77617 | E13: ='Cloud demand'!B28 -> 59763.547 | F13: =C13+E13 -> 104559.55 | G13: ='Cloud demand'!C28 -> 155893.98 | H13: ='Cloud demand'!D28 -> 195122.58 | I13: ='Cloud demand'!E28 -> 233232.95 | J13: ='Cloud demand'!F28 -> 269641.59 | K13: ='Cloud demand'!G28 -> 301344.03
A14: Other Bets | B14: ='Historical base'!C14 -> 1537 | C14: ='Historical base'!E14 -> 793 | D14: ='Historical base'!F14 -> 1507 | E14: =('Historical base'!C14-'Historical base'!D14)*(1+Assumptions!B32) -> 785.4 | F14: =C14+E14 -> 1578.4 | G14: =F14*(1+Assumptions!C32) -> 1736.24 | H14: =G14*(1+Assumptions!D32) -> 1909.864 | I14: =H14*(1+Assumptions!E32) -> 2100.8504 | J14: =I14*(1+Assumptions!F32) -> 2310.9354 | K14: =J14*(1+Assumptions!G32) -> 2542.029
A15: Hedging | B15: ='Historical base'!C15 -> -127 | C15: ='Historical base'!E15 -> -74 | D15: ='Historical base'!F15 -> -349 | E15: =0 -> 0 | F15: =C15+E15 -> -74 | G15: =0 -> 0 | H15: =0 -> 0 | I15: =0 -> 0 | J15: =0 -> 0 | K15: =0 -> 0
A16: Total revenue | B16: ='Historical base'!C16 -> 402836 | C16: ='Historical base'!E16 -> 229692 | D16: ='Historical base'!F16 -> 445866 | E16: =SUM(E12:E15) -> 271642.73 | F16: =C16+E16 -> 501334.73 | G16: =SUM(G12:G15) -> 605598.12 | H16: =SUM(H12:H15) -> 697707.59 | I16: =SUM(I12:I15) -> 787693.26 | J16: =SUM(J12:J15) -> 871891.37 | K16: =SUM(K12:K15) -> 950091.05
A19: Segment reference earnings
A20: Services reference EBIT | B20: ='Historical base'!C20 -> 139404 | C20: ='Historical base'!E20 -> 80133 | D20: ='Historical base'!F20 -> 153792 | E20: =E12*Assumptions!B37-E48-E50 -> 92639.365 | F20: =C20+E20 -> 172772.36 | G20: =G12*Assumptions!C37-G48-G50 -> 196697.73 | H20: =H12*Assumptions!D37-H48-H50 -> 222595.92 | I20: =I12*Assumptions!E37-I48-I50 -> 245290.64 | J20: =J12*Assumptions!F37-J48-J50 -> 265730.67 | K20: =K12*Assumptions!G37-K48-K50 -> 288446.29
A21: Cloud reference EBIT | B21: ='Historical base'!C21 -> 13910 | C21: ='Historical base'!E21 -> 15412 | D21: ='Historical base'!F21 -> 24319 | E21: =E13*Assumptions!B42 -> 20561.563 | F21: =C21+E21 -> 35973.563 | G21: =G13*Assumptions!C42 -> 54562.894 | H21: =H13*Assumptions!D42 -> 70244.128 | I21: =I13*Assumptions!E42 -> 86296.191 | J21: =J13*Assumptions!F42 -> 102463.8 | K21: =K13*Assumptions!G42 -> 114510.73
A22: Other Bets loss | B22: ='Historical base'!C22 -> -7515 | C22: ='Historical base'!E22 -> -3899 | D22: ='Historical base'!F22 -> -8942 | E22: =('Historical base'!C22-'Historical base'!D22)*(1+Assumptions!B47) -> -5799.45 | F22: =C22+E22 -> -9698.45 | G22: =F22*(1+Assumptions!C47) -> -11153.218 | H22: =G22*(1+Assumptions!D47) -> -12491.604 | I22: =H22*(1+Assumptions!E47) -> -13740.764 | J22: =I22*(1+Assumptions!F47) -> -14840.025 | K22: =J22*(1+Assumptions!G47) -> -15582.026
A23: Alphabet-level costs | B23: ='Historical base'!C23 -> -16760 | C23: ='Historical base'!E23 -> -11180 | D23: ='Historical base'!F23 -> -21541 | E23: =-E64 -> -12107.692 | F23: =C23+E23 -> -23287.692 | G23: =-G64 -> -26561.556 | H23: =-H64 -> -29364.375 | I23: =-I64 -> -32072.836 | J23: =-J64 -> -34570.908 | K23: =-K64 -> -36860.523
A24: Group earnings at reference D&A | B24: ='Historical base'!C24 -> 129039 | C24: ='Historical base'!E24 -> 80466 | D24: ='Historical base'!F24 -> 147628 | E24: =SUM(E20:E23) -> 95293.786 | F24: =C24+E24 -> 175759.79 | G24: =SUM(G20:G23) -> 213545.85 | H24: =SUM(H20:H23) -> 250984.07 | I24: =SUM(I20:I23) -> 285773.23 | J24: =SUM(J20:J23) -> 318783.54 | K24: =SUM(K20:K23) -> 350514.47
A25: Reference D&A added back | C25: =C30+C31 -> 14131 | E25: =E16*Assumptions!$B$95 -> 16711.873 | F25: =C25+E25 -> 30842.873 | G25: =G16*Assumptions!$B$95 -> 37257.314 | H25: =H16*Assumptions!$B$95 -> 42924.028 | I25: =I16*Assumptions!$B$95 -> 48460.083 | J25: =J16*Assumptions!$B$95 -> 53640.079 | K25: =K16*Assumptions!$B$95 -> 58451.042
A26: Pre-D&A operating earnings (SBC retained) | C26: =C24+C25 -> 94597 | E26: =SUM(E24:E25) -> 112005.66 | F26: =C26+E26 -> 206602.66 | G26: =SUM(G24:G25) -> 250803.17 | H26: =SUM(H24:H25) -> 293908.09 | I26: =SUM(I24:I25) -> 334233.31 | J26: =SUM(J24:J25) -> 372423.62 | K26: =SUM(K24:K25) -> 408965.51
A29: Explicit depreciation and tax
A30: Modelled PP&E depreciation | C30: ='Historical base'!E39 -> 13586 | E30: ='Capital and FCFF'!B24 -> 21756.208 | F30: =C30+E30 -> 35342.207 | G30: ='Capital and FCFF'!C24 -> 59679.306 | H30: ='Capital and FCFF'!D24 -> 85811.887 | I30: ='Capital and FCFF'!E24 -> 97481.522 | J30: ='Capital and FCFF'!F24 -> 110008.95 | K30: ='Capital and FCFF'!G24 -> 137711.47
A31: Intangible amortisation | C31: ='Sources and basis'!D47 -> 545 | E31: ='Capital and FCFF'!B25 -> 747 | F31: =C31+E31 -> 1292 | G31: ='Capital and FCFF'!C25 -> 1304 | H31: ='Capital and FCFF'!D25 -> 1142 | I31: ='Capital and FCFF'!E25 -> 1096 | J31: ='Capital and FCFF'!F25 -> 1055 | K31: ='Capital and FCFF'!G25 -> 1055
A33: Consolidated EBIT | B33: ='Historical base'!C24 -> 129039 | C33: ='Historical base'!E24 -> 80466 | D33: ='Historical base'!F24 -> 147628 | E33: =E26-E30-E31 -> 89502.451 | F33: =C33+E33 -> 169968.45 | G33: =G26-G30-G31 -> 189819.86 | H33: =H26-H30-H31 -> 206954.21 | I33: =I26-I30-I31 -> 235655.79 | J33: =J26-J30-J31 -> 261359.67 | K33: =K26-K30-K31 -> 270199.04
A34: Consolidated operating margin | B34: ='Historical base'!C28 -> 0.32032639 | C34: ='Historical base'!E28 -> 0.3503213 | D34: ='Historical base'!F28 -> 0.33110396 | E34: =E33/E16 -> 0.3294859 | F34: =F33/F16 -> 0.33903187 | G34: =G33/G16 -> 0.31344196 | H34: =H33/H16 -> 0.29662026 | I34: =I33/I16 -> 0.29917203 | J34: =J33/J16 -> 0.29976173 | K34: =K33/K16 -> 0.28439279
A35: Operating tax | C35: =C33-C36 -> 16897.86 | E35: =MAX(0,E33+E31*(1-Assumptions!$B$239))*Assumptions!B77 -> 16244.901 | F35: =C35+E35 -> 33142.761 | G35: =MAX(0,G33+G31*(1-Assumptions!$B$239))*Assumptions!C77 -> 34402.295 | H35: =MAX(0,H33+H31*(1-Assumptions!$B$239))*Assumptions!D77 -> 37457.317 | I35: =MAX(0,I33+I31*(1-Assumptions!$B$239))*Assumptions!E77 -> 42615.323 | J35: =MAX(0,J33+J31*(1-Assumptions!$B$239))*Assumptions!F77 -> 47234.641 | K35: =MAX(0,K33+K31*(1-Assumptions!$B$239))*Assumptions!G77 -> 48825.728
A36: NOPAT | B36: ='Historical base'!C30 -> 101940.81 | C36: ='Historical base'!E30 -> 63568.14 | D36: ='Historical base'!F30 -> 116626.12 | E36: =E33-E35 -> 73257.55 | F36: =C36+E36 -> 136825.69 | G36: =G33-G35 -> 155417.57 | H36: =H33-H35 -> 169496.89 | I36: =I33-I35 -> 193040.47 | J36: =J33-J35 -> 214125.03 | K36: =K33-K35 -> 221373.31
A38: Cash CapEx | B38: ='Historical base'!C35 -> 91447 | C38: ='Historical base'!E35 -> 80598 | D38: ='Historical base'!F35 -> 132402 | E38: ='Capital and FCFF'!B12 -> 119402 | F38: =C38+E38 -> 200000 | G38: ='Capital and FCFF'!C12 -> 212413.98 | H38: ='Capital and FCFF'!D12 -> 209722.86 | I38: ='Capital and FCFF'!E12 -> 213367.43 | J38: ='Capital and FCFF'!F12 -> 210183.72 | K38: ='Capital and FCFF'!G12 -> 210118.62
A40: Model interpretation
A41: Reference segment EBIT uses scenario margins at the H1 2026 D&A/revenue burden. That burden is added back and replaced once by the capital schedule.
A42: Segment D&A allocation is not disclosed; forecast segment reference EBIT is not a claim of independently modelled segment GAAP profit.
A43: H2 uses prior-year H2 product revenue × selected YoY growth. FY2026 combines H1 actual and H2 estimate; only future cash flows enter the DCF.
A45: Services cost sensitivities
A46: Advertising revenue | E46: =SUM(E8:E10) -> 180095.63 | F46: =SUM(F8:F10) -> 338977.63 | G46: =SUM(G8:G10) -> 383230.77 | H46: =SUM(H8:H10) -> 427522.19 | I46: =SUM(I8:I10) -> 470428.16 | J46: =SUM(J8:J10) -> 509814.41 | K46: =SUM(K8:K10) -> 547969.35
A47: TAC rate change vs. reference | E47: =Assumptions!B153+E57 -> -0.002991728 | G47: =Assumptions!C153+G57 -> -0.0064670292 | H47: =Assumptions!D153+H57 -> -0.010312516 | I47: =Assumptions!E153+I57 -> -0.013115277 | J47: =Assumptions!F153+J57 -> -0.01529948 | K47: =Assumptions!G153+K57 -> -0.017120396
A48: Incremental TAC cost | E48: =E46*E47 -> -538.79714 | F48: =E48 -> -538.79714 | G48: =G46*G47 -> -2478.3645 | H48: =H46*H47 -> -4408.8294 | I48: =I46*I47 -> -6169.7957 | J48: =J46*J47 -> -7799.8954 | K48: =K46*K47 -> -9381.4523
A49: AI serving-cost change | E49: =Assumptions!$B$217*(E58-1) -> -0.0012147563 | G49: =Assumptions!$B$217*(G58-1) -> -0.003556448 | H49: =Assumptions!$B$217*(H58-1) -> -0.0057857385 | I49: =Assumptions!$B$217*(I58-1) -> -0.0079080231 | J49: =Assumptions!$B$217*(J58-1) -> -0.009928438 | K49: =Assumptions!$B$217*(K58-1) -> -0.011851873
A50: Incremental AI serving cost | E50: =E12*E49 -> -256.42751 | F50: =E50 -> -256.42751 | G50: =G12*G49 -> -1593.1745 | H50: =H12*H49 -> -2896.7755 | I50: =I12*I49 -> -4368.0714 | J50: =J12*J49 -> -5956.4557 | K50: =K12*K49 -> -7658.7394
A52: Reference margins already include baseline TAC, content and infrastructure costs. Only changes versus that reference are applied; D&A is replaced once at group level.
A54: Services cost drivers
A55: Reference Network share of advertising | E55: ='Historical base'!$E$10/SUM('Historical base'!$E$8:$E$10) -> 0.089840259 | G55: ='Historical base'!$E$10/SUM('Historical base'!$E$8:$E$10) -> 0.089840259 | H55: ='Historical base'!$E$10/SUM('Historical base'!$E$8:$E$10) -> 0.089840259 | I55: ='Historical base'!$E$10/SUM('Historical base'!$E$8:$E$10) -> 0.089840259 | J55: ='Historical base'!$E$10/SUM('Historical base'!$E$8:$E$10) -> 0.089840259 | K55: ='Historical base'!$E$10/SUM('Historical base'!$E$8:$E$10) -> 0.089840259
A56: Forecast Network share | E56: =E10/E46 -> 0.082360939 | G56: =G10/G46 -> 0.073672686 | H56: =H10/H46 -> 0.064058969 | I56: =I10/I46 -> 0.057052066 | J56: =J10/J46 -> 0.051591559 | K56: =K10/K46 -> 0.047039269
A57: TAC mix effect (percentage points) | E57: =(E56-E55)*Assumptions!$B$227 -> -0.002991728 | G57: =(G56-G55)*Assumptions!$B$227 -> -0.0064670292 | H57: =(H56-H55)*Assumptions!$B$227 -> -0.010312516 | I57: =(I56-I55)*Assumptions!$B$227 -> -0.013115277 | J57: =(J56-J55)*Assumptions!$B$227 -> -0.01529948 | K57: =(K56-K55)*Assumptions!$B$227 -> -0.017120396
A58: AI serving cost intensity factor | E58: =((1-Assumptions!$B$207)*(1+Assumptions!$B$212))^0.5 -> 0.97570487 | F58: =E58 -> 0.97570487 | G58: =F58*(1-Assumptions!$B$207)*(1+Assumptions!$B$212) -> 0.92887104 | H58: =G58*(1-Assumptions!$B$207)*(1+Assumptions!$B$212) -> 0.88428523 | I58: =H58*(1-Assumptions!$B$207)*(1+Assumptions!$B$212) -> 0.84183954 | J58: =I58*(1-Assumptions!$B$207)*(1+Assumptions!$B$212) -> 0.80143124 | K58: =J58*(1-Assumptions!$B$207)*(1+Assumptions!$B$212) -> 0.76296254
A60: Shared costs and planned demand
A61: Planned group revenue | E61: ='Cloud demand'!B31 -> 272338.01 | F61: =C16+E61 -> 502030.01 | G61: ='Cloud demand'!C31 -> 606897.07 | H61: ='Cloud demand'!D31 -> 699076.18 | I61: ='Cloud demand'!E31 -> 790249.73 | J61: ='Cloud demand'!F31 -> 875765.5 | K61: ='Cloud demand'!G31 -> 955084.62
A62: Shared AI research expense | E62: =ABS($C$23)*Assumptions!$B$220*(1+Assumptions!$B$222) -> 9838.4 | F62: =ABS(C23)*Assumptions!B220+E62 -> 18782.4 | G62: =F62*(1+(G61/F61-1)*Assumptions!C52) -> 21921.105 | H62: =G62*(1+(H61/G61-1)*Assumptions!D52) -> 24584.711 | I62: =H62*(1+(I61/H61-1)*Assumptions!E52) -> 27149.782 | J62: =I62*(1+(J61/I61-1)*Assumptions!F52) -> 29500.162 | K62: =J62*(1+(K61/J61-1)*Assumptions!G52) -> 31637.654
A63: Other shared corporate expense | E63: =ABS($C$23)*(1-Assumptions!$B$220)*(1+Assumptions!$B$221)^0.5 -> 2269.2922 | F63: =ABS(C23)*(1-Assumptions!B220)+E63 -> 4505.2922 | G63: =F63*(1+Assumptions!$B$221) -> 4640.4509 | H63: =G63*(1+Assumptions!$B$221) -> 4779.6644 | I63: =H63*(1+Assumptions!$B$221) -> 4923.0544 | J63: =I63*(1+Assumptions!$B$221) -> 5070.746 | K63: =J63*(1+Assumptions!$B$221) -> 5222.8684
A64: Total Alphabet-level expense | E64: =SUM(E62:E63) -> 12107.692 | F64: =SUM(F62:F63) -> 23287.692 | G64: =SUM(G62:G63) -> 26561.556 | H64: =SUM(H62:H63) -> 29364.375 | I64: =SUM(I62:I63) -> 32072.836 | J64: =SUM(J62:J63) -> 34570.908 | K64: =SUM(K62:K63) -> 36860.523
A66: TAC change combines an explicit partner-pricing stress and a Network-mix sensitivity. Reference margins already include baseline TAC.
A67: AI serving cost = assumed starting exposure × cumulative unit-cost improvement × workload intensity. This excludes shared research and D&A.
A68: Shared research follows planned demand with scenario elasticity. The non-AI residual follows inflation; spending does not instantly disappear when delivery disappoints.
A69: The 5% serving-cost exposure, 80% research split and 40pp Network differential are analyst sensitivities, not disclosed company metrics.

Sheet Cloud demand
A1: Alphabet | Cloud demand and delivery
A2: USD millions. Opening backlog is recognised once; new contracts, renewals and usage are shown separately. Financing and capacity exposures are analyst sensitivities.
A3: Selected scenario | B3: =Assumptions!B3 -> Base
A4: Valuation date | B4: =Assumptions!B4 -> 46320
A6: Cloud revenue build | B6: H2 2026 | C6: 2027 | D6: 2028 | E6: 2029 | F6: 2030 | G6: 2031 | H6: Basis
A7: June 2026 Cloud backlog | B7: ='Sources and basis'!$B$92 -> 513900 | C7: ='Sources and basis'!$B$92 -> 513900 | D7: ='Sources and basis'!$B$92 -> 513900 | E7: ='Sources and basis'!$B$92 -> 513900 | F7: ='Sources and basis'!$B$92 -> 513900 | G7: ='Sources and basis'!$B$92 -> 513900
A8: Scheduled share of opening backlog | B8: =Assumptions!B167 -> 0.1 | C8: =Assumptions!C167 -> 0.26 | D8: =Assumptions!D167 -> 0.24 | E8: =Assumptions!E167 -> 0.18 | F8: =Assumptions!F167 -> 0.13 | G8: =Assumptions!G167 -> 0.09
A9: Scheduled opening-backlog recognition | B9: =B7*B8 -> 51390 | C9: =C7*C8 -> 133614 | D9: =D7*D8 -> 123336 | E9: =E7*E8 -> 92502 | F9: =F7*F8 -> 66807 | G9: =G7*G8 -> 46251
A10: Reference demand growth | B10: =Assumptions!B27 -> 0.73064441 | C10: =Assumptions!C27 -> 0.35 | D10: =Assumptions!D27 -> 0.25 | E10: =Assumptions!E27 -> 0.2 | F10: =Assumptions!F27 -> 0.16 | G10: =Assumptions!G27 -> 0.12
A11: Revenue demand before backlog floor | B11: =('Historical base'!C13-'Historical base'!D13)*(1+B10) -> 56801.48 | C11: =('Historical base'!E13+B12)*(1+C10) -> 142094.01 | D11: =C12*(1+D10) -> 196491.18 | E11: =D12*(1+E10) -> 235789.41 | F11: =E12*(1+F10) -> 273515.72 | G11: =F12*(1+G10) -> 306337.6
A12: Planned Cloud demand | B12: =MAX(B11,B9/(1-Assumptions!$B$171)) -> 60458.824 | C12: =MAX(C11,C9/(1-Assumptions!$B$171)) -> 157192.94 | D12: =MAX(D11,D9/(1-Assumptions!$B$171)) -> 196491.18 | E12: =MAX(E11,E9/(1-Assumptions!$B$171)) -> 235789.41 | F12: =MAX(F11,F9/(1-Assumptions!$B$171)) -> 273515.72 | G12: =MAX(G11,G9/(1-Assumptions!$B$171)) -> 306337.6
A13: New contracts / usage outside opening backlog | B13: =B12-B9 -> 9068.8235 | C13: =C12-C9 -> 23578.941 | D13: =D12-D9 -> 73155.176 | E13: =E12-E9 -> 143287.41 | F13: =F12-F9 -> 206708.72 | G13: =G12-G9 -> 260086.6
A14: Opening unrecognised June backlog | B14: =B7 -> 513900 | C14: =B23 -> 463023.9 | D14: =C23 -> 330237.28 | E14: =D23 -> 206806.77 | F14: =E23 -> 113995.49 | G14: =F23 -> 46928.445
A15: Opening deferred recognition | B15: =0 -> 0 | C15: =B24 -> 513.9 | D15: =C24 -> 1341.279 | E15: =D24 -> 1246.7728 | F15: =E24 -> 937.48773 | G15: =F24 -> 677.44488
A16: Recognition due including delays | B16: =B9+B15 -> 51390 | C16: =C9+C15 -> 134127.9 | D16: =D9+D15 -> 124677.28 | E16: =E9+E15 -> 93748.773 | F16: =F9+F15 -> 67744.488 | G16: =G9+G15 -> 46928.445
A17: Required in-service PP&E (capacity requirement × annualised demand) | B17: =B31/'Capital and FCFF'!B7*Assumptions!B234 -> 214874.69 | C17: =C31/'Capital and FCFF'!C7*Assumptions!C234 -> 289611.28 | D17: =D31/'Capital and FCFF'!D7*Assumptions!D234 -> 403506.77 | E17: =E31/'Capital and FCFF'!E7*Assumptions!E234 -> 513346.22 | F17: =F31/'Capital and FCFF'!F7*Assumptions!F234 -> 617151.95 | G17: =G31/'Capital and FCFF'!G7*Assumptions!G234 -> 702942.28
A18: Average in-service PP&E | B18: =AVERAGE('Capital and FCFF'!B20-'Capital and FCFF'!B13,'Capital and FCFF'!B27) -> 214897.15 | C18: =AVERAGE('Capital and FCFF'!C20-'Capital and FCFF'!C13,'Capital and FCFF'!C27) -> 289657.19 | D18: =AVERAGE('Capital and FCFF'!D20-'Capital and FCFF'!D13,'Capital and FCFF'!D27) -> 403572.88 | E18: =AVERAGE('Capital and FCFF'!E20-'Capital and FCFF'!E13,'Capital and FCFF'!E27) -> 513374.76 | F18: =AVERAGE('Capital and FCFF'!F20-'Capital and FCFF'!F13,'Capital and FCFF'!F27) -> 617205.17 | G18: =AVERAGE('Capital and FCFF'!G20-'Capital and FCFF'!G13,'Capital and FCFF'!G27) -> 702953.24
A19: Capacity coverage (capped at 100%) | B19: =IF(B17>0,MIN(1,B18/B17),1) -> 1 | C19: =IF(C17>0,MIN(1,C18/C17),1) -> 1 | D19: =IF(D17>0,MIN(1,D18/D17),1) -> 1 | E19: =IF(E17>0,MIN(1,E18/E17),1) -> 1 | F19: =IF(F17>0,MIN(1,F18/F17),1) -> 1 | G19: =IF(G17>0,MIN(1,G18/G17),1) -> 1
A20: Delivery factor | B20: =1-Assumptions!$B$187+Assumptions!$B$187*B19 -> 1 | C20: =1-Assumptions!$B$187+Assumptions!$B$187*C19 -> 1 | D20: =1-Assumptions!$B$187+Assumptions!$B$187*D19 -> 1 | E20: =1-Assumptions!$B$187+Assumptions!$B$187*E19 -> 1 | F20: =1-Assumptions!$B$187+Assumptions!$B$187*F19 -> 1 | G20: =1-Assumptions!$B$187+Assumptions!$B$187*G19 -> 1
A21: Funding-related recognition factor | B21: =1-Assumptions!$B$172*Assumptions!$B$177 -> 0.99 | C21: =1-Assumptions!$B$172*Assumptions!$B$177 -> 0.99 | D21: =1-Assumptions!$B$172*Assumptions!$B$177 -> 0.99 | E21: =1-Assumptions!$B$172*Assumptions!$B$177 -> 0.99 | F21: =1-Assumptions!$B$172*Assumptions!$B$177 -> 0.99 | G21: =1-Assumptions!$B$172*Assumptions!$B$177 -> 0.99
A22: Opening backlog recognised | B22: =MIN(B14,B16*B20*B21) -> 50876.1 | C22: =MIN(C14,C16*C20*C21) -> 132786.62 | D22: =MIN(D14,D16*D20*D21) -> 123430.51 | E22: =MIN(E14,E16*E20*E21) -> 92811.285 | F22: =MIN(F14,F16*F20*F21) -> 67067.043 | G22: =MIN(G14,G16*G20*G21) -> 46459.16
A23: Closing unrecognised June backlog | B23: =B14-B22 -> 463023.9 | C23: =C14-C22 -> 330237.28 | D23: =D14-D22 -> 206806.77 | E23: =E14-E22 -> 113995.49 | F23: =F14-F22 -> 46928.445 | G23: =G14-G22 -> 469.28445
A24: Delayed recognition carried forward | B24: =MAX(0,B16-B22) -> 513.9 | C24: =MAX(0,C16-C22) -> 1341.279 | D24: =MAX(0,D16-D22) -> 1246.7728 | E24: =MAX(0,E16-E22) -> 937.48773 | F24: =MAX(0,F16-F22) -> 677.44488 | G24: =MAX(0,G16-G22) -> 469.28445
A25: New business after delivery constraint | B25: =B13*MIN(1,B20) -> 9068.8235 | C25: =C13*MIN(1,C20) -> 23578.941 | D25: =D13*MIN(1,D20) -> 73155.176 | E25: =E13*MIN(1,E20) -> 143287.41 | F25: =F13*MIN(1,F20) -> 206708.72 | G25: =G13*MIN(1,G20) -> 260086.6
A26: Financing-related new-business reduction | B26: =B25*Assumptions!$B$172*Assumptions!$B$182 -> 181.37647 | C26: =C25*Assumptions!$B$172*Assumptions!$B$182 -> 471.57882 | D26: =D25*Assumptions!$B$172*Assumptions!$B$182 -> 1463.1035 | E26: =E25*Assumptions!$B$172*Assumptions!$B$182 -> 2865.7482 | F26: =F25*Assumptions!$B$172*Assumptions!$B$182 -> 4134.1744 | G26: =G25*Assumptions!$B$172*Assumptions!$B$182 -> 5201.7321
A27: New business recognised | B27: =B25-B26 -> 8887.4471 | C27: =C25-C26 -> 23107.362 | D27: =D25-D26 -> 71692.073 | E27: =E25-E26 -> 140421.66 | F27: =F25-F26 -> 202574.54 | G27: =G25-G26 -> 254884.87
A28: Forecast Cloud revenue | B28: =SUM(B22,B27) -> 59763.547 | C28: =SUM(C22,C27) -> 155893.98 | D28: =SUM(D22,D27) -> 195122.58 | E28: =SUM(E22,E27) -> 233232.95 | F28: =SUM(F22,F27) -> 269641.59 | G28: =SUM(G22,G27) -> 301344.03
A29: Actual forecast revenue growth | B29: =B28/('Historical base'!C13-'Historical base'!D13)-1 -> 0.82089355 | C29: =C28/('Historical base'!E13+B28)-1 -> 0.49095886 | D29: =D28/C28-1 -> 0.25163637 | E29: =E28/D28-1 -> 0.19531501 | F29: =F28/E28-1 -> 0.15610418 | G29: =G28/F28-1 -> 0.11757254
A30: Demand less delivered revenue | B30: =B12-B28 -> 695.27647 | C30: =C12-C28 -> 1298.9578 | D30: =D12-D28 -> 1368.5973 | E30: =E12-E28 -> 2556.4632 | F30: =F12-F28 -> 3874.1315 | G30: =G12-G28 -> 4993.5716
A31: Group demand for CapEx planning | B31: =SUM('Operating forecast'!E12,'Operating forecast'!E14:'Operating forecast'!E15,B12) -> 272338.01 | C31: =SUM('Operating forecast'!G12,'Operating forecast'!G14:'Operating forecast'!G15,C12) -> 606897.07 | D31: =SUM('Operating forecast'!H12,'Operating forecast'!H14:'Operating forecast'!H15,D12) -> 699076.18 | E31: =SUM('Operating forecast'!I12,'Operating forecast'!I14:'Operating forecast'!I15,E12) -> 790249.73 | F31: =SUM('Operating forecast'!J12,'Operating forecast'!J14:'Operating forecast'!J15,F12) -> 875765.5 | G31: =SUM('Operating forecast'!K12,'Operating forecast'!K14:'Operating forecast'!K15,G12) -> 955084.62
A32: Opening backlog reconciliation | B32: =B14-B22-B23 -> 0 | C32: =C14-C22-C23 -> 0 | D32: =D14-D22-D23 -> 0 | E32: =E14-E22-E23 -> 0 | F32: =F14-F22-F23 -> 0 | G32: =G14-G22-G23 -> 0
A34: 24-month reference recognition share | B34: =SUM(B8:C8)+Assumptions!B168 -> 0.51
A35: 24-month delivered share (timing proxy) | B35: =(SUM(B22:C22)+D22*Assumptions!B168/D8)/B7 -> 0.50750494
A36: June backlog remaining at end 2031 | B36: =G23 -> 469.28445
A37: AWS H1 2026 operating margin | B37: ='Sources and basis'!B101/'Sources and basis'!B100 -> 0.38564753
A38: Cloud 2031 reference operating margin | B38: =Assumptions!G42 -> 0.38
A40: Timing: 51% by June 2028 is an analyst approximation to group guidance of just over 50%; the 2031 tail is assumed, not a disclosed contract expiry.
A41: Delivery compares average in-service PP&E with the capacity that planned demand requires (Assumptions row 234, calibrated so the Base build just covers Base demand). A shortfall cuts the delivery-sensitive half of Cloud revenue; surplus capacity does not accelerate contracted revenue. This is a capacity proxy, not measured workloads or utilisation. Delayed opening backlog stays in the roll-forward.
A42: New-business demand is the residual after opening-backlog recognition, subject to a 15% minimum mix assumption. No separate new-bookings balance is claimed.
A43: Financing exposure (20%) is an illustrative sensitivity, not an identified customer share. Deferred conversion and weaker new business are modelled separately.
A44: Backlog extends beyond June 2028. Existing contracts are not added to the enterprise bridge; remaining performance obligations are future operating revenue.
A45: Sources: Alphabet Q2 2026 Form 10-Q Note 2; Google Cloud 6 April 2026 Anthropic capacity announcement; Amazon 30 July 2026 earnings release.
A46: Opening backlog allocation check | B46: =IF(ABS(SUM(B8:G8)-1)<0.000001,"PASS","REVIEW") -> PASS
A47: 24-month profile vs timing benchmark | B47: =IF(ABS(B34-Assumptions!B169)<0.000001,"PASS","REVIEW") -> PASS

Sheet Working capital
A1: Alphabet | operating working capital
A2: USD millions. Non-cash operating balances exclude financing and identified non-operating items. Required operating cash is added in rows 58–62; residual classifications remain provisional.
A3: Selected case | B3: =Assumptions!B3 -> Base
A4: Opening non-cash operating WC | B4: =C29 -> 26257
A6: Operating balance | B6: Dec 2025 A | C6: Jun 2026 A | E6: Dec 2026 E | F6: 2027 E | G6: 2028 E | H6: 2029 E | I6: 2030 E | J6: 2031 E
A7: Operating current assets
A8: Trade receivables | B8: ='Balance sheet'!G11 -> 62886 | C8: ='Balance sheet'!I11 -> 69175 | E8: =E35/365*Assumptions!B103 -> 77780.836 | F8: =F35/365*Assumptions!C103 -> 93957.04 | G8: =G35/365*Assumptions!D103 -> 108247.6 | H8: =H35/365*Assumptions!E103 -> 122208.65 | I8: =I35/365*Assumptions!F103 -> 135271.78 | J8: =J35/365*Assumptions!G103 -> 147404.26
A9: Inventory | B9: ='Sources and basis'!B97 -> 2439 | C9: ='Balance sheet'!I12 -> 9991 | E9: =E35*Assumptions!B108 -> 11233.948 | F9: =F35*Assumptions!C108 -> 8618.4639 | G9: =G35*Assumptions!D108 -> 4224.3216 | H9: =H35*Assumptions!E108 -> 4769.1464 | I9: =I35*Assumptions!F108 -> 5278.93 | J9: =J35*Assumptions!G108 -> 5752.3957
A10: Other current assets / operating residual | B10: ='Sources and basis'!B98 -> 13870 | C10: ='Balance sheet'!I13 -> 21884 | E10: =E35*Assumptions!B113 -> 16623.229 | F10: =F35*Assumptions!C113 -> 20080.389 | G10: =G35*Assumptions!D113 -> 23134.549 | H10: =H35*Assumptions!E113 -> 26118.289 | I10: =I35*Assumptions!F113 -> 28910.126 | J10: =J35*Assumptions!G113 -> 31503.066
A11: Less: held-for-sale PP&E | B11: ='Sources and basis'!B84 -> 0 | C11: ='Sources and basis'!C84 -> 7100
A12: Less: further non-operating adjustments | B12: 0 | C12: 0
A13: Operating current assets | B13: =SUM(B8:B10)-SUM(B11:B12) -> 79195 | C13: =SUM(C8:C10)-SUM(C11:C12) -> 93950 | E13: =SUM(E8:E10) -> 105638.01 | F13: =SUM(F8:F10) -> 122655.89 | G13: =SUM(G8:G10) -> 135606.47 | H13: =SUM(H8:H10) -> 153096.08 | I13: =SUM(I8:I10) -> 169460.83 | J13: =SUM(J8:J10) -> 184659.72
A15: Operating current liabilities
A16: Reported accounts payable | B16: ='Balance sheet'!G27 -> 12200 | C16: ='Balance sheet'!I27 -> 20258
A17: Less: CapEx creditors in AP | B17: ='Sources and basis'!D42-'Sources and basis'!B86 -> 6213 | C17: ='Sources and basis'!E42-'Sources and basis'!C86 -> 12917
A18: Operating supplier payables | B18: =B16-B17 -> 5987 | C18: =C16-C17 -> 7341 | E18: =E35*Assumptions!B118 -> 8254.2698 | F18: =F35*Assumptions!C118 -> 9970.9235 | G18: =G35*Assumptions!D118 -> 11487.468 | H18: =H35*Assumptions!E118 -> 12969.045 | I18: =I35*Assumptions!F118 -> 14355.332 | J18: =J35*Assumptions!G118 -> 15642.858
A19: Accrued compensation | B19: ='Balance sheet'!G28 -> 17546 | C19: ='Balance sheet'!I28 -> 15086 | E19: =E35*Assumptions!B123 -> 16962.8 | F19: =F35*Assumptions!C123 -> 20490.581 | G19: =G35*Assumptions!D123 -> 23607.13 | H19: =H35*Assumptions!E123 -> 26651.82 | I19: =I35*Assumptions!F123 -> 29500.687 | J19: =J35*Assumptions!G123 -> 32146.595
A20: Accrued revenue share | B20: ='Balance sheet'!G30 -> 10864 | C20: ='Balance sheet'!I30 -> 10599 | E20: =E35*Assumptions!B128 -> 11917.587 | F20: =F35*Assumptions!C128 -> 14396.107 | G20: =G35*Assumptions!D128 -> 16585.707 | H20: =H35*Assumptions!E128 -> 18724.821 | I20: =I35*Assumptions!F128 -> 20726.354 | J20: =J35*Assumptions!G128 -> 22585.295
A21: Deferred revenue | B21: ='Balance sheet'!G31 -> 6578 | C21: ='Balance sheet'!I31 -> 7154 | E21: =E35*Assumptions!B133 -> 8044.0057 | F21: =F35*Assumptions!C133 -> 9716.9305 | G21: =G35*Assumptions!D133 -> 11194.843 | H21: =H35*Assumptions!E133 -> 12638.68 | I21: =I35*Assumptions!F133 -> 13989.654 | J21: =J35*Assumptions!G133 -> 15244.381
A22: Reported other current liabilities | B22: ='Balance sheet'!G29 -> 55557 | C22: ='Balance sheet'!I29 -> 73014
A23: Less: financing, tax, leases and brokers | B23: =SUM('Sources and basis'!D36:D41) -> 7119 | C23: =SUM('Sources and basis'!E36:E41) -> 11949
A24: Less: CapEx creditors in accruals | B24: ='Sources and basis'!B86 -> 8877 | C24: ='Sources and basis'!C86 -> 16196
A25: Less: accrued fines and settlements | B25: ='Sources and basis'!B85 -> 15594 | C25: ='Sources and basis'!C85 -> 17356
A26: Residual operating accruals | B26: =B22-SUM(B23:B25) -> 23967 | C26: =C22-SUM(C23:C25) -> 27513 | E26: =E35*Assumptions!B138 -> 30935.802 | F26: =F35*Assumptions!C138 -> 37369.571 | G26: =G35*Assumptions!D138 -> 43053.359 | H26: =H35*Assumptions!E138 -> 48606.094 | I26: =I35*Assumptions!F138 -> 53801.697 | J26: =J35*Assumptions!G138 -> 58627.155
A27: Operating current liabilities | B27: =SUM(B18:B21)+B26 -> 64942 | C27: =SUM(C18:C21)+C26 -> 67693 | E27: =SUM(E18:E21)+E26 -> 76114.465 | F27: =SUM(F18:F21)+F26 -> 91944.112 | G27: =SUM(G18:G21)+G26 -> 105928.51 | H27: =SUM(H18:H21)+H26 -> 119590.46 | I27: =SUM(I18:I21)+I26 -> 132373.72 | J27: =SUM(J18:J21)+J26 -> 144246.28
A29: Net operating working capital | B29: =B13-B27 -> 14253 | C29: =C13-C27 -> 26257 | E29: =E13-E27 -> 29523.548 | F29: =F13-F27 -> 30711.781 | G29: =G13-G27 -> 29677.959 | H29: =H13-H27 -> 33505.625 | I29: =I13-I27 -> 37087.108 | J29: =J13-J27 -> 40413.44
A30: Published historical proxy | B30: ='Historical base'!D71 -> -1341 | C30: ='Historical base'!E71 -> 16001
A31: Proxy after identified adjustments | B31: =B30-B11-B12+B25 -> 14253 | C31: =C30-C11-C12+C25 -> 26257
A32: Reconciliation check | B32: =ROUND(B29-B31,6) -> 0 | C32: =ROUND(C29-C31,6) -> 0
A34: Forecast calibration
A35: Annual / TTM revenue basis | B35: ='Historical base'!C16 -> 402836 | C35: ='Historical base'!F16 -> 445866 | E35: ='Operating forecast'!F16 -> 501334.73 | F35: ='Operating forecast'!G16 -> 605598.12 | G35: ='Operating forecast'!H16 -> 697707.59 | H35: ='Operating forecast'!I16 -> 787693.26 | I35: ='Operating forecast'!J16 -> 871891.37 | J35: ='Operating forecast'!K16 -> 950091.05
A36: Receivable days | B36: =B8/B35*365 -> 56.97949 | C36: =C8/C35*365 -> 56.628841 | E36: =E8/E35*365 -> 56.628841 | F36: =F8/F35*365 -> 56.628841 | G36: =G8/G35*365 -> 56.628841 | H36: =H8/H35*365 -> 56.628841 | I36: =I8/I35*365 -> 56.628841 | J36: =J8/J35*365 -> 56.628841
A37: Inventory / revenue | B37: =B9/B35 -> 0.0060545731 | C37: =C9/C35 -> 0.022408078 | E37: =E9/E35 -> 0.022408078 | F37: =F9/F35 -> 0.014231325 | G37: =G9/G35 -> 0.0060545731 | H37: =H9/H35 -> 0.0060545731 | I37: =I9/I35 -> 0.0060545731 | J37: =J9/J35 -> 0.0060545731
A38: Other operating assets / revenue | B38: =(B10-B11-B12)/B35 -> 0.034430885 | C38: =(C10-C11-C12)/C35 -> 0.033157944 | E38: =(E10-E11-E12)/E35 -> 0.033157944 | F38: =(F10-F11-F12)/F35 -> 0.033157944 | G38: =(G10-G11-G12)/G35 -> 0.033157944 | H38: =(H10-H11-H12)/H35 -> 0.033157944 | I38: =(I10-I11-I12)/I35 -> 0.033157944 | J38: =(J10-J11-J12)/J35 -> 0.033157944
A39: Operating payables / revenue | B39: =B18/B35 -> 0.014862128 | C39: =C18/C35 -> 0.016464588 | E39: =E18/E35 -> 0.016464588 | F39: =F18/F35 -> 0.016464588 | G39: =G18/G35 -> 0.016464588 | H39: =H18/H35 -> 0.016464588 | I39: =I18/I35 -> 0.016464588 | J39: =J18/J35 -> 0.016464588
A40: Compensation accrual / revenue | B40: =B19/B35 -> 0.043556187 | C40: =C19/C35 -> 0.033835278 | E40: =E19/E35 -> 0.033835278 | F40: =F19/F35 -> 0.033835278 | G40: =G19/G35 -> 0.033835278 | H40: =H19/H35 -> 0.033835278 | I40: =I19/I35 -> 0.033835278 | J40: =J19/J35 -> 0.033835278
A41: Revenue-share accrual / revenue | B41: =B20/B35 -> 0.026968791 | C41: =C20/C35 -> 0.023771716 | E41: =E20/E35 -> 0.023771716 | F41: =F20/F35 -> 0.023771716 | G41: =G20/G35 -> 0.023771716 | H41: =H20/H35 -> 0.023771716 | I41: =I20/I35 -> 0.023771716 | J41: =J20/J35 -> 0.023771716
A42: Deferred revenue / revenue | B42: =B21/B35 -> 0.016329226 | C42: =C21/C35 -> 0.016045179 | E42: =E21/E35 -> 0.016045179 | F42: =F21/F35 -> 0.016045179 | G42: =G21/G35 -> 0.016045179 | H42: =H21/H35 -> 0.016045179 | I42: =I21/I35 -> 0.016045179 | J42: =J21/J35 -> 0.016045179
A43: Other operating accruals / revenue | B43: =B26/B35 -> 0.059495676 | C43: =C26/C35 -> 0.061706881 | E43: =E26/E35 -> 0.061706881 | F43: =F26/F35 -> 0.061706881 | G43: =G26/G35 -> 0.061706881 | H43: =H26/H35 -> 0.061706881 | I43: =I26/I35 -> 0.061706881 | J43: =J26/J35 -> 0.061706881
A44: NOWC / revenue | B44: =B29/B35 -> 0.035381644 | C44: =C29/C35 -> 0.058889891 | E44: =E29/E35 -> 0.058889891 | F44: =F29/F35 -> 0.050713138 | G44: =G29/G35 -> 0.042536386 | H44: =H29/H35 -> 0.042536386 | I44: =I29/I35 -> 0.042536386 | J44: =J29/J35 -> 0.042536386
A46: Forecast cash investment
A47: Opening operating working capital | E47: =C29 -> 26257 | F47: =E29 -> 29523.548 | G47: =F29 -> 30711.781 | H47: =G29 -> 29677.959 | I47: =H29 -> 33505.625 | J47: =I29 -> 37087.108
A48: Increase in operating working capital | E48: =E29-E47 -> 3266.5475 | F48: =F29-F47 -> 1188.2335 | G48: =G29-G47 -> -1033.8218 | H48: =H29-H47 -> 3827.6655 | I48: =I29-I47 -> 3581.4832 | J48: =J29-J47 -> 3326.3318
A51: Forecast opening NOWC removes held-for-sale PP&E and legal accruals from the historical proxy. Required operating cash is added separately below.
A52: Residual other assets/liabilities may include derivatives or collateral not separately disclosed as current. Additional exclusion inputs default to zero, pending evidence.
A53: Legal settlements are excluded from recurring NOWC and handled in the valuation bridge. The July payment reduces cash; unpaid claims must not disappear.
A54: GFiber's reclassified assets are excluded from recurring working capital, not assumed worthless. Disposal / retained-interest value requires a separate assessment.
A55: Inventory normalises to the reclassified FY2025 ratio, approximately 0.61% of sales. The Q2 2026 comparative separates inventory from other current assets without changing historical NOWC.
A57: Required operating cash and total working capital
A58: Required operating cash | B58: =B35*'Financial assets'!$B$30 -> 8056.72 | C58: =C35*'Financial assets'!$B$30 -> 8917.32 | E58: =E35*'Financial assets'!$B$30 -> 10026.695 | F58: =F35*'Financial assets'!$B$30 -> 12111.962 | G58: =G35*'Financial assets'!$B$30 -> 13954.152 | H58: =H35*'Financial assets'!$B$30 -> 15753.865 | I58: =I35*'Financial assets'!$B$30 -> 17437.827 | J58: =J35*'Financial assets'!$B$30 -> 19001.821
A59: Operating WC including required cash | B59: =B29+B58 -> 22309.72 | C59: =C29+C58 -> 35174.32 | E59: =E29+E58 -> 39550.242 | F59: =F29+F58 -> 42823.743 | G59: =G29+G58 -> 43632.111 | H59: =H29+H58 -> 49259.49 | I59: =I29+I58 -> 54524.935 | J59: =J29+J58 -> 59415.261
A60: Opening required operating cash | E60: =C58 -> 8917.32 | F60: =E58 -> 10026.695 | G60: =F58 -> 12111.962 | H60: =G58 -> 13954.152 | I60: =H58 -> 15753.865 | J60: =I58 -> 17437.827
A61: Increase in required cash | E61: =E58-E60 -> 1109.3746 | F61: =F58-F60 -> 2085.2677 | G61: =G58-G60 -> 1842.1894 | H61: =H58-H60 -> 1799.7135 | I61: =I58-I60 -> 1683.9622 | J61: =J58-J60 -> 1563.9936
A62: Total operating WC investment | E62: =E48+E61 -> 4375.9221 | F62: =F48+F61 -> 3273.5012 | G62: =G48+G61 -> 808.36756 | H62: =H48+H61 -> 5627.379 | I62: =I48+I61 -> 5265.4454 | J62: =J48+J61 -> 4890.3254
A64: Required operating cash uses Financial assets!B30 (2% of annual/TTM sales). The June reserve is withheld from surplus cash; future increases reduce FCFF and remain in operating capital.
A65: 2032–2036 carries forward the 2031 total operating-WC/revenue ratio. Terminal g/return reinvestment includes cash funding; no second cash deduction is applied.

Sheet Capital and FCFF
A1: Alphabet | capital deployment and FCFF
A2: USD millions. Economic depreciation / replacement prototype; asset allocation, tax treatment and deployment rates are provisional.
A3: Selected case | B3: =Assumptions!B3 -> Base
A6: Cash-flow forecast | B6: H2 2026 | C6: 2027 | D6: 2028 | E6: 2029 | F6: 2030 | G6: 2031 | H6: 2032 | I6: 2033 | J6: 2034 | K6: 2035 | L6: 2036
A7: Period length (years) | B7: 0.5 | C7: 1 | D7: 1 | E7: 1 | F7: 1 | G7: 1 | H7: 1 | I7: 1 | J7: 1 | K7: 1 | L7: 1
A8: Years since June 2026, period end | B8: =B7 -> 0.5 | C8: =B8+C7 -> 1.5 | D8: =C8+D7 -> 2.5 | E8: =D8+E7 -> 3.5 | F8: =E8+F7 -> 4.5 | G8: =F8+G7 -> 5.5 | H8: =G8+H7 -> 6.5 | I8: =H8+I7 -> 7.5 | J8: =I8+J7 -> 8.5 | ... L8: =K8+L7 -> 10.5
A9: Cash investment and deployment
A10: Planned cash CapEx | B10: =Assumptions!B93 -> 119402 | C10: ='Cloud demand'!C31*Assumptions!C57 -> 212413.98 | D10: ='Cloud demand'!D31*Assumptions!D57 -> 209722.86 | E10: ='Cloud demand'!E31*Assumptions!E57 -> 213367.43 | F10: ='Cloud demand'!F31*Assumptions!F57 -> 210183.72 | G10: ='Cloud demand'!G31*Assumptions!G57 -> 210118.62 | H10: =H95 -> 221869.37 | I10: =I95 -> 224301.41 | J10: =J95 -> 221755.27 | K10: =K95 -> 213824.35 | L10: =L95 -> 245718.64
A11: Replacement-spending floor | B11: =SUM(B21:B22,B78:B88) -> 19839.8 | C11: =SUM(C21:C22,C78:C88) -> 39679.6 | D11: =SUM(D21:D22,D78:D88) -> 39679.6 | E11: =SUM(E21:E22,E78:E88) -> 23146.433 | F11: =SUM(F21:F22,F78:F88) -> 6613.2667 | G11: =SUM(G21:G22,G78:G88) -> 39465.967 | H11: =SUM(H21:H22,H78:H88) -> 112333.92 | I11: =SUM(I21:I22,I78:I88) -> 124886.16 | ... L11: =SUM(L21:L22,L78:L88) -> 132517.84
A12: Cash CapEx | B12: =B10 -> 119402 | C12: =MAX(C10,C11) -> 212413.98 | D12: =MAX(D10,D11) -> 209722.86 | E12: =MAX(E10,E11) -> 213367.43 | F12: =MAX(F10,F11) -> 210183.72 | G12: =MAX(G10,G11) -> 210118.62 | H12: =MAX(H10,H11) -> 221869.37 | I12: =MAX(I10,I11) -> 224301.41 | J12: =MAX(J10,J11) -> 221755.27 | ... L12: =MAX(L10,L11) -> 245718.64
A13: Opening assets not in service | B13: ='Historical base'!E74 -> 122814 | C13: =B15 -> 187461.5 | D13: =C15 -> 223674.38 | E13: =D15 -> 236275.75 | F13: =E15 -> 243867.5 | G13: =F15 -> 244675.6 | H13: =G15 -> 244953.27 | I13: =H15 -> 253289.87 | J13: =I15 -> 258326.94 | ... L13: =K15 -> 253100.83
A14: Commissioned assets | B14: =MIN(B13+B12,(B13+0.5*B12)*Assumptions!B62*B7) -> 54754.5 | C14: =MIN(C13+C12,(C13+0.5*C12)*Assumptions!C62*C7) -> 176201.09 | D14: =MIN(D13+D12,(D13+0.5*D12)*Assumptions!D62*D7) -> 197121.49 | E14: =MIN(E13+E12,(E13+0.5*E12)*Assumptions!E62*E7) -> 205775.68 | F14: =MIN(F13+F12,(F13+0.5*F12)*Assumptions!F62*F7) -> 209375.62 | G14: =MIN(G13+G12,(G13+0.5*G12)*Assumptions!G62*G7) -> 209840.95 | H14: =MIN(H13+H12,(H13+0.5*H12)*Assumptions!$G$62) -> 213532.78 | I14: =MIN(I13+I12,(I13+0.5*I12)*Assumptions!$G$62) -> 219264.35 | J14: =MIN(J13+J12,(J13+0.5*J12)*Assumptions!$G$62) -> 221522.74 | K14: =MIN(K13+K12,(K13+0.5*K12)*Assumptions!$G$62) -> 219282.98 | L14: =MIN(L13+L12,(L13+0.5*L12)*Assumptions!$G$62) -> 225576.09
A15: Closing assets not in service | B15: =B13+B12-B14 -> 187461.5 | C15: =C13+C12-C14 -> 223674.38 | D15: =D13+D12-D14 -> 236275.75 | E15: =E13+E12-E14 -> 243867.5 | F15: =F13+F12-F14 -> 244675.6 | G15: =G13+G12-G14 -> 244953.27 | H15: =H13+H12-H14 -> 253289.87 | I15: =I13+I12-I14 -> 258326.94 | ... L15: =L13+L12-L14 -> 273243.38
A16: Hardware commissioned | B16: =B14*Assumptions!B72 -> 32852.7 | C16: =C14*Assumptions!C72 -> 105720.66 | D16: =D14*Assumptions!D72 -> 118272.89 | E16: =E14*Assumptions!E72 -> 123465.41 | F16: =F14*Assumptions!F72 -> 125625.37 | G16: =G14*Assumptions!G72 -> 125904.57 | H16: =H14*Assumptions!$G$72 -> 128119.67 | I16: =I14*Assumptions!$G$72 -> 131558.61 | J16: =J14*Assumptions!$G$72 -> 132913.65 | K16: =K14*Assumptions!$G$72 -> 131569.79 | L16: =L14*Assumptions!$G$72 -> 135345.65
A17: Other assets commissioned | B17: =B14-B16 -> 21901.8 | C17: =C14-C16 -> 70480.437 | D17: =D14-D16 -> 78848.595 | E17: =E14-E16 -> 82310.272 | F17: =F14-F16 -> 83750.246 | G17: =G14-G16 -> 83936.379 | H17: =H14-H16 -> 85413.111 | I17: =I14-I16 -> 87705.738 | ... L17: =L14-L16 -> 90230.435
A19: Capital and depreciation
A20: Opening net PP&E | B20: ='Historical base'!E72 -> 321212 | C20: =B26 -> 418857.79 | D20: =C26 -> 571592.46 | E20: =D26 -> 695503.43 | F20: =E26 -> 811389.33 | G20: =F26 -> 911564.11 | H20: =G26 -> 983971.26 | I20: =H26 -> 1053993 | J20: =I26 -> 1118550.3 | ... L20: =K26 -> 1215331.8
A21: Opening-asset hardware depreciation | B21: =$B$44/$B$46*MAX(0,MIN(B8,$B$46)-MAX(B8-B7,0)) -> 16533.167 | C21: =$B$44/$B$46*MAX(0,MIN(C8,$B$46)-MAX(C8-C7,0)) -> 33066.333 | D21: =$B$44/$B$46*MAX(0,MIN(D8,$B$46)-MAX(D8-D7,0)) -> 33066.333 | E21: =$B$44/$B$46*MAX(0,MIN(E8,$B$46)-MAX(E8-E7,0)) -> 16533.167 | F21: =$B$44/$B$46*MAX(0,MIN(F8,$B$46)-MAX(F8-F7,0)) -> 0 | G21: =$B$44/$B$46*MAX(0,MIN(G8,$B$46)-MAX(G8-G7,0)) -> 0 | H21: =$B$44/$B$46*MAX(0,MIN(H8,$B$46)-MAX(H8-H7,0)) -> 0 | I21: =$B$44/$B$46*MAX(0,MIN(I8,$B$46)-MAX(I8-I7,0)) -> 0 | ... L21: =$B$44/$B$46*MAX(0,MIN(L8,$B$46)-MAX(L8-L7,0)) -> 0
A22: Opening-asset other depreciation | B22: =$B$45/$B$47*MAX(0,MIN(B8,$B$47)-MAX(B8-B7,0)) -> 3306.6333 | C22: =$B$45/$B$47*MAX(0,MIN(C8,$B$47)-MAX(C8-C7,0)) -> 6613.2667 | D22: =$B$45/$B$47*MAX(0,MIN(D8,$B$47)-MAX(D8-D7,0)) -> 6613.2667 | E22: =$B$45/$B$47*MAX(0,MIN(E8,$B$47)-MAX(E8-E7,0)) -> 6613.2667 | F22: =$B$45/$B$47*MAX(0,MIN(F8,$B$47)-MAX(F8-F7,0)) -> 6613.2667 | G22: =$B$45/$B$47*MAX(0,MIN(G8,$B$47)-MAX(G8-G7,0)) -> 6613.2667 | H22: =$B$45/$B$47*MAX(0,MIN(H8,$B$47)-MAX(H8-H7,0)) -> 6613.2667 | I22: =$B$45/$B$47*MAX(0,MIN(I8,$B$47)-MAX(I8-I7,0)) -> 6613.2667 | ... L22: =$B$45/$B$47*MAX(0,MIN(L8,$B$47)-MAX(L8-L7,0)) -> 6613.2667
A23: Depreciation of new commissioned assets | B23: =SUM(B50:B60,B64:B74) -> 1916.4075 | C23: =SUM(C50:C60,C64:C74) -> 19999.706 | D23: =SUM(D50:D60,D64:D74) -> 46132.287 | E23: =SUM(E50:E60,E64:E74) -> 74335.089 | F23: =SUM(F50:F60,F64:F74) -> 103395.68 | G23: =SUM(G50:G60,G64:G74) -> 131098.2 | H23: =SUM(H50:H60,H64:H74) -> 145234.39 | I23: =SUM(I50:I60,I64:I74) -> 153130.84 | ... L23: =SUM(L50:L60,L64:L74) -> 171746.57
A24: Total PP&E economic depreciation | B24: =SUM(B21:B23) -> 21756.208 | C24: =SUM(C21:C23) -> 59679.306 | D24: =SUM(D21:D23) -> 85811.887 | E24: =SUM(E21:E23) -> 97481.522 | F24: =SUM(F21:F23) -> 110008.95 | G24: =SUM(G21:G23) -> 137711.47 | H24: =SUM(H21:H23) -> 151847.66 | I24: =SUM(I21:I23) -> 159744.1 | ... L24: =SUM(L21:L23) -> 178359.83
A25: Intangible amortisation | B25: ='Sources and basis'!E47 -> 747 | C25: ='Sources and basis'!F47 -> 1304 | D25: ='Sources and basis'!G47 -> 1142 | E25: ='Sources and basis'!H47 -> 1096 | F25: ='Sources and basis'!I47 -> 1055 | G25: =Assumptions!B94 -> 1055 | H25: =MIN(MAX(0,'Sources and basis'!$B$56-SUM($G$25:G25)),Assumptions!$B$237/Assumptions!$B$238) -> 499 | I25: =MIN(MAX(0,'Sources and basis'!$B$56-SUM($G$25:H25)),Assumptions!$B$237/Assumptions!$B$238) -> 499 | J25: =MIN(MAX(0,'Sources and basis'!$B$56-SUM($G$25:I25)),Assumptions!$B$237/Assumptions!$B$238) -> 499 | K25: =MIN(MAX(0,'Sources and basis'!$B$56-SUM($G$25:J25)),Assumptions!$B$237/Assumptions!$B$238) -> 499 | L25: =MIN(MAX(0,'Sources and basis'!$B$56-SUM($G$25:K25)),Assumptions!$B$237/Assumptions!$B$238) -> 499
A26: Closing net PP&E | B26: =B20+B12-B24 -> 418857.79 | C26: =C20+C12-C24 -> 571592.46 | D26: =D20+D12-D24 -> 695503.43 | E26: =E20+E12-E24 -> 811389.33 | F26: =F20+F12-F24 -> 911564.11 | G26: =G20+G12-G24 -> 983971.26 | H26: =H20+H12-H24 -> 1053993 | I26: =I20+I12-I24 -> 1118550.3 | ... L26: =L20+L12-L24 -> 1282690.6
A27: Closing in-service net PP&E | B27: =B26-B15 -> 231396.29 | C27: =C26-C15 -> 347918.08 | D27: =D26-D15 -> 459227.68 | E27: =E26-E15 -> 567521.83 | F27: =F26-F15 -> 666888.5 | G27: =G26-G15 -> 739017.98 | H27: =H26-H15 -> 800703.1 | I27: =I26-I15 -> 860223.34 | ... L27: =L26-L15 -> 1009447.3
A28: PP&E roll-forward check | B28: =B26-B20-B12+B24 -> 0 | C28: =C26-C20-C12+C24 -> 0 | D28: =D26-D20-D12+D24 -> 0 | E28: =E26-E20-E12+E24 -> 0 | F28: =F26-F20-F12+F24 -> 0 | G28: =G26-G20-G12+G24 -> 0 | H28: =H26-H20-H12+H24 -> -2.0372681e-10 | I28: =I26-I20-I12+I24 -> 1.4551915e-10 | ... L28: =L26-L20-L12+L24 -> 0
A30: Free cash flow
A31: NOPAT | B31: ='Operating forecast'!E36 -> 73257.55 | C31: ='Operating forecast'!G36 -> 155417.57 | D31: ='Operating forecast'!H36 -> 169496.89 | E31: ='Operating forecast'!I36 -> 193040.47 | F31: ='Operating forecast'!J36 -> 214125.03 | G31: ='Operating forecast'!K36 -> 221373.31 | H31: =Transition!C13 -> 237492.18 | I31: =Transition!D13 -> 251285.6 | J31: =Transition!E13 -> 262880.3 | K31: =Transition!F13 -> 271872.83 | L31: =Transition!G13 -> 277929.34
A32: PP&E depreciation added back | B32: =B24 -> 21756.208 | C32: =C24 -> 59679.306 | D32: =D24 -> 85811.887 | E32: =E24 -> 97481.522 | F32: =F24 -> 110008.95 | G32: =G24 -> 137711.47 | H32: =H24 -> 151847.66 | I32: =I24 -> 159744.1 | ... L32: =L24 -> 178359.83
A33: Intangible amortisation added back | B33: =B25 -> 747 | C33: =C25 -> 1304 | D33: =D25 -> 1142 | E33: =E25 -> 1096 | F33: =F25 -> 1055 | G33: =G25 -> 1055 | H33: =H25 -> 499 | I33: =I25 -> 499 | ... L33: =L25 -> 499
A34: Cash CapEx deducted | B34: =B12 -> 119402 | C34: =C12 -> 212413.98 | D34: =D12 -> 209722.86 | E34: =E12 -> 213367.43 | F34: =F12 -> 210183.72 | G34: =G12 -> 210118.62 | H34: =H12 -> 221869.37 | I34: =I12 -> 224301.41 | ... L34: =L12 -> 245718.64
A35: Closing operating WC including cash | B35: ='Working capital'!E59 -> 39550.242 | C35: ='Working capital'!F59 -> 42823.743 | D35: ='Working capital'!G59 -> 43632.111 | E35: ='Working capital'!H59 -> 49259.49 | F35: ='Working capital'!I59 -> 54524.935 | G35: ='Working capital'!J59 -> 59415.261 | H35: =Transition!C9*('Working capital'!$J$59/'Operating forecast'!$K$16) -> 64034.902 | I35: =Transition!D9*('Working capital'!$J$59/'Operating forecast'!$K$16) -> 68249.284 | J35: =Transition!E9*('Working capital'!$J$59/'Operating forecast'!$K$16) -> 71926.274 | K35: =Transition!F9*('Working capital'!$J$59/'Operating forecast'!$K$16) -> 74942.714 | L35: =Transition!G9*('Working capital'!$J$59/'Operating forecast'!$K$16) -> 77190.995
A36: Opening operating WC including cash | B36: ='Working capital'!C59 -> 35174.32 | C36: ='Working capital'!E59 -> 39550.242 | D36: ='Working capital'!F59 -> 42823.743 | E36: ='Working capital'!G59 -> 43632.111 | F36: ='Working capital'!H59 -> 49259.49 | G36: ='Working capital'!I59 -> 54524.935 | H36: =G35 -> 59415.261 | I36: =H35 -> 64034.902 | J36: =I35 -> 68249.284 | K36: =J35 -> 71926.274 | L36: =K35 -> 74942.714
A37: Increase in operating WC including cash | B37: ='Working capital'!E62 -> 4375.9221 | C37: ='Working capital'!F62 -> 3273.5012 | D37: ='Working capital'!G62 -> 808.36756 | E37: ='Working capital'!H62 -> 5627.379 | F37: ='Working capital'!I62 -> 5265.4454 | G37: ='Working capital'!J62 -> 4890.3254 | H37: =H35-H36 -> 4619.6413 | I37: =I35-I36 -> 4214.3817 | J37: =J35-J36 -> 3676.9904 | K37: =K35-K36 -> 3016.4398 | L37: =L35-L36 -> 2248.2814
A38: Projected FCFF | B38: =SUM(B31:B33)-B34-B37 -> -28017.165 | C38: =SUM(C31:C33)-C34-C37 -> 713.39555 | D38: =SUM(D31:D33)-D34-D37 -> 45919.555 | E38: =SUM(E31:E33)-E34-E37 -> 72623.186 | F38: =SUM(F31:F33)-F34-F37 -> 109739.81 | G38: =SUM(G31:G33)-G34-G37 -> 145130.84 | H38: =SUM(H31:H33)-H34-H37 -> 163349.82 | I38: =SUM(I31:I33)-I34-I37 -> 183012.91 | ... L38: =SUM(L31:L33)-L34-L37 -> 208821.25
A39: Average tangible operating capital | B39: =AVERAGE(B20+B36,B26+B35) -> 407397.18 | C39: =AVERAGE(C20+C36,C26+C35) -> 536412.12 | D39: =AVERAGE(D20+D36,D26+D35) -> 676775.87 | E39: =AVERAGE(E20+E36,E26+E35) -> 799892.18 | F39: =AVERAGE(F20+F36,F26+F35) -> 913368.93 | G39: =AVERAGE(G20+G36,G26+G35) -> 1004737.8 | H39: =AVERAGE(H20+H36,H26+H35) -> 1080707.2 | I39: =AVERAGE(I20+I36,I26+I35) -> 1152413.7 | ... L39: =AVERAGE(L20+L36,L26+L35) -> 1325078.1
A40: Return on tangible operating capital | B40: =B31/B7/B39 -> 0.359637 | C40: =C31/C7/C39 -> 0.28973537 | D40: =D31/D7/D39 -> 0.2504476 | E40: =E31/E7/E39 -> 0.24133311 | F40: =F31/F7/F39 -> 0.23443432 | G40: =G31/G7/G39 -> 0.22032944 | H40: =H31/H39 -> 0.21975627 | I40: =I31/I39 -> 0.21805155 | J40: =J31/J39 -> 0.2161306 | K40: =K31/K39 -> 0.2144039 | L40: =L31/L39 -> 0.20974563
A41: Cash CapEx / period revenue | B41: =B12/'Operating forecast'!E16 -> 0.43955529 | C41: =C12/'Operating forecast'!G16 -> 0.35075072 | D41: =D12/'Operating forecast'!H16 -> 0.30058847 | E41: =E12/'Operating forecast'!I16 -> 0.27087629 | F41: =F12/'Operating forecast'!J16 -> 0.24106641 | G41: =G12/'Operating forecast'!K16 -> 0.2211563 | H41: =H12/Transition!C9 -> 0.21667729 | I41: =I12/Transition!D9 -> 0.20552596 | J41: =J12/Transition!E9 -> 0.19280539 | K41: =K12/Transition!F9 -> 0.17842698 | L41: =L12/Transition!G9 -> 0.19906928
A43: Opening productive asset pools
A44: Opening hardware net book value | B44: ='Historical base'!E75*Assumptions!B89 -> 99199
A45: Opening other productive net book value | B45: ='Historical base'!E75-B44 -> 99199
A46: Opening hardware remaining life | B46: =Assumptions!B90 -> 3
A47: Opening other remaining life | B47: =Assumptions!B91 -> 15
A49: Hardware depreciation by commissioning cohort
A50: H2 2026 hardware | B50: =$B$16/Assumptions!$B$67*MAX(0,MIN(B$8,($B$8-$B$7/2)+Assumptions!$B$67)-MAX((B$8-B$7),($B$8-$B$7/2))) -> 1642.635 | C50: =$B$16/Assumptions!$B$67*MAX(0,MIN(C$8,($B$8-$B$7/2)+Assumptions!$B$67)-MAX((C$8-C$7),($B$8-$B$7/2))) -> 6570.54 | D50: =$B$16/Assumptions!$B$67*MAX(0,MIN(D$8,($B$8-$B$7/2)+Assumptions!$B$67)-MAX((D$8-D$7),($B$8-$B$7/2))) -> 6570.54 | E50: =$B$16/Assumptions!$B$67*MAX(0,MIN(E$8,($B$8-$B$7/2)+Assumptions!$B$67)-MAX((E$8-E$7),($B$8-$B$7/2))) -> 6570.54 | F50: =$B$16/Assumptions!$B$67*MAX(0,MIN(F$8,($B$8-$B$7/2)+Assumptions!$B$67)-MAX((F$8-F$7),($B$8-$B$7/2))) -> 6570.54 | G50: =$B$16/Assumptions!$B$67*MAX(0,MIN(G$8,($B$8-$B$7/2)+Assumptions!$B$67)-MAX((G$8-G$7),($B$8-$B$7/2))) -> 4927.905 | H50: =$B$16/Assumptions!$B$67*MAX(0,MIN(H$8,($B$8-$B$7/2)+Assumptions!$B$67)-MAX((H$8-H$7),($B$8-$B$7/2))) -> 0 | I50: =$B$16/Assumptions!$B$67*MAX(0,MIN(I$8,($B$8-$B$7/2)+Assumptions!$B$67)-MAX((I$8-I$7),($B$8-$B$7/2))) -> 0 | ... L50: =$B$16/Assumptions!$B$67*MAX(0,MIN(L$8,($B$8-$B$7/2)+Assumptions!$B$67)-MAX((L$8-L$7),($B$8-$B$7/2))) -> 0
A51: 2027 hardware | B51: =0 -> 0 | C51: =$C$16/Assumptions!$C$67*MAX(0,MIN(C$8,($C$8-$C$7/2)+Assumptions!$C$67)-MAX((C$8-C$7),($C$8-$C$7/2))) -> 10572.066 | D51: =$C$16/Assumptions!$C$67*MAX(0,MIN(D$8,($C$8-$C$7/2)+Assumptions!$C$67)-MAX((D$8-D$7),($C$8-$C$7/2))) -> 21144.131 | E51: =$C$16/Assumptions!$C$67*MAX(0,MIN(E$8,($C$8-$C$7/2)+Assumptions!$C$67)-MAX((E$8-E$7),($C$8-$C$7/2))) -> 21144.131 | F51: =$C$16/Assumptions!$C$67*MAX(0,MIN(F$8,($C$8-$C$7/2)+Assumptions!$C$67)-MAX((F$8-F$7),($C$8-$C$7/2))) -> 21144.131 | G51: =$C$16/Assumptions!$C$67*MAX(0,MIN(G$8,($C$8-$C$7/2)+Assumptions!$C$67)-MAX((G$8-G$7),($C$8-$C$7/2))) -> 21144.131 | H51: =$C$16/Assumptions!$C$67*MAX(0,MIN(H$8,($C$8-$C$7/2)+Assumptions!$C$67)-MAX((H$8-H$7),($C$8-$C$7/2))) -> 10572.066 | I51: =$C$16/Assumptions!$C$67*MAX(0,MIN(I$8,($C$8-$C$7/2)+Assumptions!$C$67)-MAX((I$8-I$7),($C$8-$C$7/2))) -> 0 | J51: =$C$16/Assumptions!$C$67*MAX(0,MIN(J$8,($C$8-$C$7/2)+Assumptions!$C$67)-MAX((J$8-J$7),($C$8-$C$7/2))) -> 0 | ... L51: =$C$16/Assumptions!$C$67*MAX(0,MIN(L$8,($C$8-$C$7/2)+Assumptions!$C$67)-MAX((L$8-L$7),($C$8-$C$7/2))) -> 0
A52: 2028 hardware | B52: =0 -> 0 | C52: =0 -> 0 | D52: =$D$16/Assumptions!$D$67*MAX(0,MIN(D$8,($D$8-$D$7/2)+Assumptions!$D$67)-MAX((D$8-D$7),($D$8-$D$7/2))) -> 11827.289 | E52: =$D$16/Assumptions!$D$67*MAX(0,MIN(E$8,($D$8-$D$7/2)+Assumptions!$D$67)-MAX((E$8-E$7),($D$8-$D$7/2))) -> 23654.578 | F52: =$D$16/Assumptions!$D$67*MAX(0,MIN(F$8,($D$8-$D$7/2)+Assumptions!$D$67)-MAX((F$8-F$7),($D$8-$D$7/2))) -> 23654.578 | G52: =$D$16/Assumptions!$D$67*MAX(0,MIN(G$8,($D$8-$D$7/2)+Assumptions!$D$67)-MAX((G$8-G$7),($D$8-$D$7/2))) -> 23654.578 | H52: =$D$16/Assumptions!$D$67*MAX(0,MIN(H$8,($D$8-$D$7/2)+Assumptions!$D$67)-MAX((H$8-H$7),($D$8-$D$7/2))) -> 23654.578 | I52: =$D$16/Assumptions!$D$67*MAX(0,MIN(I$8,($D$8-$D$7/2)+Assumptions!$D$67)-MAX((I$8-I$7),($D$8-$D$7/2))) -> 11827.289 | J52: =$D$16/Assumptions!$D$67*MAX(0,MIN(J$8,($D$8-$D$7/2)+Assumptions!$D$67)-MAX((J$8-J$7),($D$8-$D$7/2))) -> 0 | K52: =$D$16/Assumptions!$D$67*MAX(0,MIN(K$8,($D$8-$D$7/2)+Assumptions!$D$67)-MAX((K$8-K$7),($D$8-$D$7/2))) -> 0 | L52: =$D$16/Assumptions!$D$67*MAX(0,MIN(L$8,($D$8-$D$7/2)+Assumptions!$D$67)-MAX((L$8-L$7),($D$8-$D$7/2))) -> 0
A53: 2029 hardware | B53: =0 -> 0 | C53: =0 -> 0 | D53: =0 -> 0 | E53: =$E$16/Assumptions!$E$67*MAX(0,MIN(E$8,($E$8-$E$7/2)+Assumptions!$E$67)-MAX((E$8-E$7),($E$8-$E$7/2))) -> 12346.541 | F53: =$E$16/Assumptions!$E$67*MAX(0,MIN(F$8,($E$8-$E$7/2)+Assumptions!$E$67)-MAX((F$8-F$7),($E$8-$E$7/2))) -> 24693.081 | G53: =$E$16/Assumptions!$E$67*MAX(0,MIN(G$8,($E$8-$E$7/2)+Assumptions!$E$67)-MAX((G$8-G$7),($E$8-$E$7/2))) -> 24693.081 | H53: =$E$16/Assumptions!$E$67*MAX(0,MIN(H$8,($E$8-$E$7/2)+Assumptions!$E$67)-MAX((H$8-H$7),($E$8-$E$7/2))) -> 24693.081 | I53: =$E$16/Assumptions!$E$67*MAX(0,MIN(I$8,($E$8-$E$7/2)+Assumptions!$E$67)-MAX((I$8-I$7),($E$8-$E$7/2))) -> 24693.081 | J53: =$E$16/Assumptions!$E$67*MAX(0,MIN(J$8,($E$8-$E$7/2)+Assumptions!$E$67)-MAX((J$8-J$7),($E$8-$E$7/2))) -> 12346.541 | K53: =$E$16/Assumptions!$E$67*MAX(0,MIN(K$8,($E$8-$E$7/2)+Assumptions!$E$67)-MAX((K$8-K$7),($E$8-$E$7/2))) -> 0 | L53: =$E$16/Assumptions!$E$67*MAX(0,MIN(L$8,($E$8-$E$7/2)+Assumptions!$E$67)-MAX((L$8-L$7),($E$8-$E$7/2))) -> 0
A54: 2030 hardware | B54: =0 -> 0 | C54: =0 -> 0 | D54: =0 -> 0 | E54: =0 -> 0 | F54: =$F$16/Assumptions!$F$67*MAX(0,MIN(F$8,($F$8-$F$7/2)+Assumptions!$F$67)-MAX((F$8-F$7),($F$8-$F$7/2))) -> 12562.537 | G54: =$F$16/Assumptions!$F$67*MAX(0,MIN(G$8,($F$8-$F$7/2)+Assumptions!$F$67)-MAX((G$8-G$7),($F$8-$F$7/2))) -> 25125.074 | H54: =$F$16/Assumptions!$F$67*MAX(0,MIN(H$8,($F$8-$F$7/2)+Assumptions!$F$67)-MAX((H$8-H$7),($F$8-$F$7/2))) -> 25125.074 | I54: =$F$16/Assumptions!$F$67*MAX(0,MIN(I$8,($F$8-$F$7/2)+Assumptions!$F$67)-MAX((I$8-I$7),($F$8-$F$7/2))) -> 25125.074 | J54: =$F$16/Assumptions!$F$67*MAX(0,MIN(J$8,($F$8-$F$7/2)+Assumptions!$F$67)-MAX((J$8-J$7),($F$8-$F$7/2))) -> 25125.074 | K54: =$F$16/Assumptions!$F$67*MAX(0,MIN(K$8,($F$8-$F$7/2)+Assumptions!$F$67)-MAX((K$8-K$7),($F$8-$F$7/2))) -> 12562.537 | L54: =$F$16/Assumptions!$F$67*MAX(0,MIN(L$8,($F$8-$F$7/2)+Assumptions!$F$67)-MAX((L$8-L$7),($F$8-$F$7/2))) -> 0
A55: 2031 hardware | B55: =0 -> 0 | C55: =0 -> 0 | D55: =0 -> 0 | E55: =0 -> 0 | F55: =0 -> 0 | G55: =$G$16/Assumptions!$G$67*MAX(0,MIN(G$8,($G$8-$G$7/2)+Assumptions!$G$67)-MAX((G$8-G$7),($G$8-$G$7/2))) -> 12590.457 | H55: =$G$16/Assumptions!$G$67*MAX(0,MIN(H$8,($G$8-$G$7/2)+Assumptions!$G$67)-MAX((H$8-H$7),($G$8-$G$7/2))) -> 25180.914 | I55: =$G$16/Assumptions!$G$67*MAX(0,MIN(I$8,($G$8-$G$7/2)+Assumptions!$G$67)-MAX((I$8-I$7),($G$8-$G$7/2))) -> 25180.914 | J55: =$G$16/Assumptions!$G$67*MAX(0,MIN(J$8,($G$8-$G$7/2)+Assumptions!$G$67)-MAX((J$8-J$7),($G$8-$G$7/2))) -> 25180.914 | K55: =$G$16/Assumptions!$G$67*MAX(0,MIN(K$8,($G$8-$G$7/2)+Assumptions!$G$67)-MAX((K$8-K$7),($G$8-$G$7/2))) -> 25180.914 | L55: =$G$16/Assumptions!$G$67*MAX(0,MIN(L$8,($G$8-$G$7/2)+Assumptions!$G$67)-MAX((L$8-L$7),($G$8-$G$7/2))) -> 12590.457
A56: 2032 hardware | B56: =0 -> 0 | C56: =0 -> 0 | D56: =0 -> 0 | E56: =0 -> 0 | F56: =0 -> 0 | G56: =0 -> 0 | H56: =$H$16/Assumptions!$G$67*MAX(0,MIN(H$8,($H$8-$H$7/2)+Assumptions!$G$67)-MAX((H$8-H$7),($H$8-$H$7/2))) -> 12811.967 | I56: =$H$16/Assumptions!$G$67*MAX(0,MIN(I$8,($H$8-$H$7/2)+Assumptions!$G$67)-MAX((I$8-I$7),($H$8-$H$7/2))) -> 25623.933 | J56: =$H$16/Assumptions!$G$67*MAX(0,MIN(J$8,($H$8-$H$7/2)+Assumptions!$G$67)-MAX((J$8-J$7),($H$8-$H$7/2))) -> 25623.933 | K56: =$H$16/Assumptions!$G$67*MAX(0,MIN(K$8,($H$8-$H$7/2)+Assumptions!$G$67)-MAX((K$8-K$7),($H$8-$H$7/2))) -> 25623.933 | L56: =$H$16/Assumptions!$G$67*MAX(0,MIN(L$8,($H$8-$H$7/2)+Assumptions!$G$67)-MAX((L$8-L$7),($H$8-$H$7/2))) -> 25623.933
A57: 2033 hardware | B57: =0 -> 0 | C57: =0 -> 0 | D57: =0 -> 0 | E57: =0 -> 0 | F57: =0 -> 0 | G57: =0 -> 0 | H57: =0 -> 0 | I57: =$I$16/Assumptions!$G$67*MAX(0,MIN(I$8,($I$8-$I$7/2)+Assumptions!$G$67)-MAX((I$8-I$7),($I$8-$I$7/2))) -> 13155.861 | J57: =$I$16/Assumptions!$G$67*MAX(0,MIN(J$8,($I$8-$I$7/2)+Assumptions!$G$67)-MAX((J$8-J$7),($I$8-$I$7/2))) -> 26311.721 | K57: =$I$16/Assumptions!$G$67*MAX(0,MIN(K$8,($I$8-$I$7/2)+Assumptions!$G$67)-MAX((K$8-K$7),($I$8-$I$7/2))) -> 26311.721 | L57: =$I$16/Assumptions!$G$67*MAX(0,MIN(L$8,($I$8-$I$7/2)+Assumptions!$G$67)-MAX((L$8-L$7),($I$8-$I$7/2))) -> 26311.721
A58: 2034 hardware | B58: =0 -> 0 | C58: =0 -> 0 | D58: =0 -> 0 | E58: =0 -> 0 | F58: =0 -> 0 | G58: =0 -> 0 | H58: =0 -> 0 | I58: =0 -> 0 | J58: =$J$16/Assumptions!$G$67*MAX(0,MIN(J$8,($J$8-$J$7/2)+Assumptions!$G$67)-MAX((J$8-J$7),($J$8-$J$7/2))) -> 13291.365 | K58: =$J$16/Assumptions!$G$67*MAX(0,MIN(K$8,($J$8-$J$7/2)+Assumptions!$G$67)-MAX((K$8-K$7),($J$8-$J$7/2))) -> 26582.729 | L58: =$J$16/Assumptions!$G$67*MAX(0,MIN(L$8,($J$8-$J$7/2)+Assumptions!$G$67)-MAX((L$8-L$7),($J$8-$J$7/2))) -> 26582.729
A59: 2035 hardware | B59: =0 -> 0 | C59: =0 -> 0 | D59: =0 -> 0 | E59: =0 -> 0 | F59: =0 -> 0 | G59: =0 -> 0 | H59: =0 -> 0 | I59: =0 -> 0 | J59: =0 -> 0 | K59: =$K$16/Assumptions!$G$67*MAX(0,MIN(K$8,($K$8-$K$7/2)+Assumptions!$G$67)-MAX((K$8-K$7),($K$8-$K$7/2))) -> 13156.979 | L59: =$K$16/Assumptions!$G$67*MAX(0,MIN(L$8,($K$8-$K$7/2)+Assumptions!$G$67)-MAX((L$8-L$7),($K$8-$K$7/2))) -> 26313.958
A60: 2036 hardware | B60: =0 -> 0 | C60: =0 -> 0 | D60: =0 -> 0 | E60: =0 -> 0 | F60: =0 -> 0 | G60: =0 -> 0 | H60: =0 -> 0 | I60: =0 -> 0 | ... K60: =0 -> 0 | L60: =$L$16/Assumptions!$G$67*MAX(0,MIN(L$8,($L$8-$L$7/2)+Assumptions!$G$67)-MAX((L$8-L$7),($L$8-$L$7/2))) -> 13534.565
A63: Other-asset depreciation by commissioning cohort
A64: H2 2026 other assets | B64: =$B$17/Assumptions!$B$92*MAX(0,MIN(B$8,($B$8-$B$7/2)+Assumptions!$B$92)-MAX((B$8-B$7),($B$8-$B$7/2))) -> 273.7725 | C64: =$B$17/Assumptions!$B$92*MAX(0,MIN(C$8,($B$8-$B$7/2)+Assumptions!$B$92)-MAX((C$8-C$7),($B$8-$B$7/2))) -> 1095.09 | D64: =$B$17/Assumptions!$B$92*MAX(0,MIN(D$8,($B$8-$B$7/2)+Assumptions!$B$92)-MAX((D$8-D$7),($B$8-$B$7/2))) -> 1095.09 | E64: =$B$17/Assumptions!$B$92*MAX(0,MIN(E$8,($B$8-$B$7/2)+Assumptions!$B$92)-MAX((E$8-E$7),($B$8-$B$7/2))) -> 1095.09 | F64: =$B$17/Assumptions!$B$92*MAX(0,MIN(F$8,($B$8-$B$7/2)+Assumptions!$B$92)-MAX((F$8-F$7),($B$8-$B$7/2))) -> 1095.09 | G64: =$B$17/Assumptions!$B$92*MAX(0,MIN(G$8,($B$8-$B$7/2)+Assumptions!$B$92)-MAX((G$8-G$7),($B$8-$B$7/2))) -> 1095.09 | H64: =$B$17/Assumptions!$B$92*MAX(0,MIN(H$8,($B$8-$B$7/2)+Assumptions!$B$92)-MAX((H$8-H$7),($B$8-$B$7/2))) -> 1095.09 | I64: =$B$17/Assumptions!$B$92*MAX(0,MIN(I$8,($B$8-$B$7/2)+Assumptions!$B$92)-MAX((I$8-I$7),($B$8-$B$7/2))) -> 1095.09 | ... L64: =$B$17/Assumptions!$B$92*MAX(0,MIN(L$8,($B$8-$B$7/2)+Assumptions!$B$92)-MAX((L$8-L$7),($B$8-$B$7/2))) -> 1095.09
A65: 2027 other assets | B65: =0 -> 0 | C65: =$C$17/Assumptions!$B$92*MAX(0,MIN(C$8,($C$8-$C$7/2)+Assumptions!$B$92)-MAX((C$8-C$7),($C$8-$C$7/2))) -> 1762.0109 | D65: =$C$17/Assumptions!$B$92*MAX(0,MIN(D$8,($C$8-$C$7/2)+Assumptions!$B$92)-MAX((D$8-D$7),($C$8-$C$7/2))) -> 3524.0219 | E65: =$C$17/Assumptions!$B$92*MAX(0,MIN(E$8,($C$8-$C$7/2)+Assumptions!$B$92)-MAX((E$8-E$7),($C$8-$C$7/2))) -> 3524.0219 | F65: =$C$17/Assumptions!$B$92*MAX(0,MIN(F$8,($C$8-$C$7/2)+Assumptions!$B$92)-MAX((F$8-F$7),($C$8-$C$7/2))) -> 3524.0219 | G65: =$C$17/Assumptions!$B$92*MAX(0,MIN(G$8,($C$8-$C$7/2)+Assumptions!$B$92)-MAX((G$8-G$7),($C$8-$C$7/2))) -> 3524.0219 | H65: =$C$17/Assumptions!$B$92*MAX(0,MIN(H$8,($C$8-$C$7/2)+Assumptions!$B$92)-MAX((H$8-H$7),($C$8-$C$7/2))) -> 3524.0219 | I65: =$C$17/Assumptions!$B$92*MAX(0,MIN(I$8,($C$8-$C$7/2)+Assumptions!$B$92)-MAX((I$8-I$7),($C$8-$C$7/2))) -> 3524.0219 | J65: =$C$17/Assumptions!$B$92*MAX(0,MIN(J$8,($C$8-$C$7/2)+Assumptions!$B$92)-MAX((J$8-J$7),($C$8-$C$7/2))) -> 3524.0219 | ... L65: =$C$17/Assumptions!$B$92*MAX(0,MIN(L$8,($C$8-$C$7/2)+Assumptions!$B$92)-MAX((L$8-L$7),($C$8-$C$7/2))) -> 3524.0219
A66: 2028 other assets | B66: =0 -> 0 | C66: =0 -> 0 | D66: =$D$17/Assumptions!$B$92*MAX(0,MIN(D$8,($D$8-$D$7/2)+Assumptions!$B$92)-MAX((D$8-D$7),($D$8-$D$7/2))) -> 1971.2149 | E66: =$D$17/Assumptions!$B$92*MAX(0,MIN(E$8,($D$8-$D$7/2)+Assumptions!$B$92)-MAX((E$8-E$7),($D$8-$D$7/2))) -> 3942.4297 | F66: =$D$17/Assumptions!$B$92*MAX(0,MIN(F$8,($D$8-$D$7/2)+Assumptions!$B$92)-MAX((F$8-F$7),($D$8-$D$7/2))) -> 3942.4297 | G66: =$D$17/Assumptions!$B$92*MAX(0,MIN(G$8,($D$8-$D$7/2)+Assumptions!$B$92)-MAX((G$8-G$7),($D$8-$D$7/2))) -> 3942.4297 | H66: =$D$17/Assumptions!$B$92*MAX(0,MIN(H$8,($D$8-$D$7/2)+Assumptions!$B$92)-MAX((H$8-H$7),($D$8-$D$7/2))) -> 3942.4297 | I66: =$D$17/Assumptions!$B$92*MAX(0,MIN(I$8,($D$8-$D$7/2)+Assumptions!$B$92)-MAX((I$8-I$7),($D$8-$D$7/2))) -> 3942.4297 | J66: =$D$17/Assumptions!$B$92*MAX(0,MIN(J$8,($D$8-$D$7/2)+Assumptions!$B$92)-MAX((J$8-J$7),($D$8-$D$7/2))) -> 3942.4297 | K66: =$D$17/Assumptions!$B$92*MAX(0,MIN(K$8,($D$8-$D$7/2)+Assumptions!$B$92)-MAX((K$8-K$7),($D$8-$D$7/2))) -> 3942.4297 | L66: =$D$17/Assumptions!$B$92*MAX(0,MIN(L$8,($D$8-$D$7/2)+Assumptions!$B$92)-MAX((L$8-L$7),($D$8-$D$7/2))) -> 3942.4297
A67: 2029 other assets | B67: =0 -> 0 | C67: =0 -> 0 | D67: =0 -> 0 | E67: =$E$17/Assumptions!$B$92*MAX(0,MIN(E$8,($E$8-$E$7/2)+Assumptions!$B$92)-MAX((E$8-E$7),($E$8-$E$7/2))) -> 2057.7568 | F67: =$E$17/Assumptions!$B$92*MAX(0,MIN(F$8,($E$8-$E$7/2)+Assumptions!$B$92)-MAX((F$8-F$7),($E$8-$E$7/2))) -> 4115.5136 | G67: =$E$17/Assumptions!$B$92*MAX(0,MIN(G$8,($E$8-$E$7/2)+Assumptions!$B$92)-MAX((G$8-G$7),($E$8-$E$7/2))) -> 4115.5136 | H67: =$E$17/Assumptions!$B$92*MAX(0,MIN(H$8,($E$8-$E$7/2)+Assumptions!$B$92)-MAX((H$8-H$7),($E$8-$E$7/2))) -> 4115.5136 | I67: =$E$17/Assumptions!$B$92*MAX(0,MIN(I$8,($E$8-$E$7/2)+Assumptions!$B$92)-MAX((I$8-I$7),($E$8-$E$7/2))) -> 4115.5136 | J67: =$E$17/Assumptions!$B$92*MAX(0,MIN(J$8,($E$8-$E$7/2)+Assumptions!$B$92)-MAX((J$8-J$7),($E$8-$E$7/2))) -> 4115.5136 | K67: =$E$17/Assumptions!$B$92*MAX(0,MIN(K$8,($E$8-$E$7/2)+Assumptions!$B$92)-MAX((K$8-K$7),($E$8-$E$7/2))) -> 4115.5136 | L67: =$E$17/Assumptions!$B$92*MAX(0,MIN(L$8,($E$8-$E$7/2)+Assumptions!$B$92)-MAX((L$8-L$7),($E$8-$E$7/2))) -> 4115.5136
A68: 2030 other assets | B68: =0 -> 0 | C68: =0 -> 0 | D68: =0 -> 0 | E68: =0 -> 0 | F68: =$F$17/Assumptions!$B$92*MAX(0,MIN(F$8,($F$8-$F$7/2)+Assumptions!$B$92)-MAX((F$8-F$7),($F$8-$F$7/2))) -> 2093.7562 | G68: =$F$17/Assumptions!$B$92*MAX(0,MIN(G$8,($F$8-$F$7/2)+Assumptions!$B$92)-MAX((G$8-G$7),($F$8-$F$7/2))) -> 4187.5123 | H68: =$F$17/Assumptions!$B$92*MAX(0,MIN(H$8,($F$8-$F$7/2)+Assumptions!$B$92)-MAX((H$8-H$7),($F$8-$F$7/2))) -> 4187.5123 | I68: =$F$17/Assumptions!$B$92*MAX(0,MIN(I$8,($F$8-$F$7/2)+Assumptions!$B$92)-MAX((I$8-I$7),($F$8-$F$7/2))) -> 4187.5123 | J68: =$F$17/Assumptions!$B$92*MAX(0,MIN(J$8,($F$8-$F$7/2)+Assumptions!$B$92)-MAX((J$8-J$7),($F$8-$F$7/2))) -> 4187.5123 | K68: =$F$17/Assumptions!$B$92*MAX(0,MIN(K$8,($F$8-$F$7/2)+Assumptions!$B$92)-MAX((K$8-K$7),($F$8-$F$7/2))) -> 4187.5123 | L68: =$F$17/Assumptions!$B$92*MAX(0,MIN(L$8,($F$8-$F$7/2)+Assumptions!$B$92)-MAX((L$8-L$7),($F$8-$F$7/2))) -> 4187.5123
A69: 2031 other assets | B69: =0 -> 0 | C69: =0 -> 0 | D69: =0 -> 0 | E69: =0 -> 0 | F69: =0 -> 0 | G69: =$G$17/Assumptions!$B$92*MAX(0,MIN(G$8,($G$8-$G$7/2)+Assumptions!$B$92)-MAX((G$8-G$7),($G$8-$G$7/2))) -> 2098.4095 | H69: =$G$17/Assumptions!$B$92*MAX(0,MIN(H$8,($G$8-$G$7/2)+Assumptions!$B$92)-MAX((H$8-H$7),($G$8-$G$7/2))) -> 4196.819 | I69: =$G$17/Assumptions!$B$92*MAX(0,MIN(I$8,($G$8-$G$7/2)+Assumptions!$B$92)-MAX((I$8-I$7),($G$8-$G$7/2))) -> 4196.819 | J69: =$G$17/Assumptions!$B$92*MAX(0,MIN(J$8,($G$8-$G$7/2)+Assumptions!$B$92)-MAX((J$8-J$7),($G$8-$G$7/2))) -> 4196.819 | K69: =$G$17/Assumptions!$B$92*MAX(0,MIN(K$8,($G$8-$G$7/2)+Assumptions!$B$92)-MAX((K$8-K$7),($G$8-$G$7/2))) -> 4196.819 | L69: =$G$17/Assumptions!$B$92*MAX(0,MIN(L$8,($G$8-$G$7/2)+Assumptions!$B$92)-MAX((L$8-L$7),($G$8-$G$7/2))) -> 4196.819
A70: 2032 other assets | B70: =0 -> 0 | C70: =0 -> 0 | D70: =0 -> 0 | E70: =0 -> 0 | F70: =0 -> 0 | G70: =0 -> 0 | H70: =$H$17/Assumptions!$B$92*MAX(0,MIN(H$8,($H$8-$H$7/2)+Assumptions!$B$92)-MAX((H$8-H$7),($H$8-$H$7/2))) -> 2135.3278 | I70: =$H$17/Assumptions!$B$92*MAX(0,MIN(I$8,($H$8-$H$7/2)+Assumptions!$B$92)-MAX((I$8-I$7),($H$8-$H$7/2))) -> 4270.6555 | J70: =$H$17/Assumptions!$B$92*MAX(0,MIN(J$8,($H$8-$H$7/2)+Assumptions!$B$92)-MAX((J$8-J$7),($H$8-$H$7/2))) -> 4270.6555 | K70: =$H$17/Assumptions!$B$92*MAX(0,MIN(K$8,($H$8-$H$7/2)+Assumptions!$B$92)-MAX((K$8-K$7),($H$8-$H$7/2))) -> 4270.6555 | L70: =$H$17/Assumptions!$B$92*MAX(0,MIN(L$8,($H$8-$H$7/2)+Assumptions!$B$92)-MAX((L$8-L$7),($H$8-$H$7/2))) -> 4270.6555
A71: 2033 other assets | B71: =0 -> 0 | C71: =0 -> 0 | D71: =0 -> 0 | E71: =0 -> 0 | F71: =0 -> 0 | G71: =0 -> 0 | H71: =0 -> 0 | I71: =$I$17/Assumptions!$B$92*MAX(0,MIN(I$8,($I$8-$I$7/2)+Assumptions!$B$92)-MAX((I$8-I$7),($I$8-$I$7/2))) -> 2192.6435 | J71: =$I$17/Assumptions!$B$92*MAX(0,MIN(J$8,($I$8-$I$7/2)+Assumptions!$B$92)-MAX((J$8-J$7),($I$8-$I$7/2))) -> 4385.2869 | K71: =$I$17/Assumptions!$B$92*MAX(0,MIN(K$8,($I$8-$I$7/2)+Assumptions!$B$92)-MAX((K$8-K$7),($I$8-$I$7/2))) -> 4385.2869 | L71: =$I$17/Assumptions!$B$92*MAX(0,MIN(L$8,($I$8-$I$7/2)+Assumptions!$B$92)-MAX((L$8-L$7),($I$8-$I$7/2))) -> 4385.2869
A72: 2034 other assets | B72: =0 -> 0 | C72: =0 -> 0 | D72: =0 -> 0 | E72: =0 -> 0 | F72: =0 -> 0 | G72: =0 -> 0 | H72: =0 -> 0 | I72: =0 -> 0 | J72: =$J$17/Assumptions!$B$92*MAX(0,MIN(J$8,($J$8-$J$7/2)+Assumptions!$B$92)-MAX((J$8-J$7),($J$8-$J$7/2))) -> 2215.2274 | K72: =$J$17/Assumptions!$B$92*MAX(0,MIN(K$8,($J$8-$J$7/2)+Assumptions!$B$92)-MAX((K$8-K$7),($J$8-$J$7/2))) -> 4430.4549 | L72: =$J$17/Assumptions!$B$92*MAX(0,MIN(L$8,($J$8-$J$7/2)+Assumptions!$B$92)-MAX((L$8-L$7),($J$8-$J$7/2))) -> 4430.4549
A73: 2035 other assets | B73: =0 -> 0 | C73: =0 -> 0 | D73: =0 -> 0 | E73: =0 -> 0 | F73: =0 -> 0 | G73: =0 -> 0 | H73: =0 -> 0 | I73: =0 -> 0 | J73: =0 -> 0 | K73: =$K$17/Assumptions!$B$92*MAX(0,MIN(K$8,($K$8-$K$7/2)+Assumptions!$B$92)-MAX((K$8-K$7),($K$8-$K$7/2))) -> 2192.8298 | L73: =$K$17/Assumptions!$B$92*MAX(0,MIN(L$8,($K$8-$K$7/2)+Assumptions!$B$92)-MAX((L$8-L$7),($K$8-$K$7/2))) -> 4385.6596
A74: 2036 other assets | B74: =0 -> 0 | C74: =0 -> 0 | D74: =0 -> 0 | E74: =0 -> 0 | F74: =0 -> 0 | G74: =0 -> 0 | H74: =0 -> 0 | I74: =0 -> 0 | ... K74: =0 -> 0 | L74: =$L$17/Assumptions!$B$92*MAX(0,MIN(L$8,($L$8-$L$7/2)+Assumptions!$B$92)-MAX((L$8-L$7),($L$8-$L$7/2))) -> 2255.7609
A77: Hardware replacement at cohort expiry
A78: H2 2026 hardware renewal | B78: =0 -> 0 | C78: =IF(AND(($B$8-$B$7/2)+Assumptions!$B$67>(C$8-C$7),($B$8-$B$7/2)+Assumptions!$B$67<=C$8),$B$16,0) -> 0 | D78: =IF(AND(($B$8-$B$7/2)+Assumptions!$B$67>(D$8-D$7),($B$8-$B$7/2)+Assumptions!$B$67<=D$8),$B$16,0) -> 0 | E78: =IF(AND(($B$8-$B$7/2)+Assumptions!$B$67>(E$8-E$7),($B$8-$B$7/2)+Assumptions!$B$67<=E$8),$B$16,0) -> 0 | F78: =IF(AND(($B$8-$B$7/2)+Assumptions!$B$67>(F$8-F$7),($B$8-$B$7/2)+Assumptions!$B$67<=F$8),$B$16,0) -> 0 | G78: =IF(AND(($B$8-$B$7/2)+Assumptions!$B$67>(G$8-G$7),($B$8-$B$7/2)+Assumptions!$B$67<=G$8),$B$16,0) -> 32852.7 | H78: =IF(AND(($B$8-$B$7/2)+Assumptions!$B$67>(H$8-H$7),($B$8-$B$7/2)+Assumptions!$B$67<=H$8),$B$16,0) -> 0 | I78: =IF(AND(($B$8-$B$7/2)+Assumptions!$B$67>(I$8-I$7),($B$8-$B$7/2)+Assumptions!$B$67<=I$8),$B$16,0) -> 0 | J78: =IF(AND(($B$8-$B$7/2)+Assumptions!$B$67>(J$8-J$7),($B$8-$B$7/2)+Assumptions!$B$67<=J$8),$B$16,0) -> 0 | ... L78: =IF(AND(($B$8-$B$7/2)+Assumptions!$B$67>(L$8-L$7),($B$8-$B$7/2)+Assumptions!$B$67<=L$8),$B$16,0) -> 0
A79: 2027 hardware renewal | B79: =0 -> 0 | C79: =0 -> 0 | D79: =IF(AND(($C$8-$C$7/2)+Assumptions!$C$67>(D$8-D$7),($C$8-$C$7/2)+Assumptions!$C$67<=D$8),$C$16,0) -> 0 | E79: =IF(AND(($C$8-$C$7/2)+Assumptions!$C$67>(E$8-E$7),($C$8-$C$7/2)+Assumptions!$C$67<=E$8),$C$16,0) -> 0 | F79: =IF(AND(($C$8-$C$7/2)+Assumptions!$C$67>(F$8-F$7),($C$8-$C$7/2)+Assumptions!$C$67<=F$8),$C$16,0) -> 0 | G79: =IF(AND(($C$8-$C$7/2)+Assumptions!$C$67>(G$8-G$7),($C$8-$C$7/2)+Assumptions!$C$67<=G$8),$C$16,0) -> 0 | H79: =IF(AND(($C$8-$C$7/2)+Assumptions!$C$67>(H$8-H$7),($C$8-$C$7/2)+Assumptions!$C$67<=H$8),$C$16,0) -> 105720.66 | I79: =IF(AND(($C$8-$C$7/2)+Assumptions!$C$67>(I$8-I$7),($C$8-$C$7/2)+Assumptions!$C$67<=I$8),$C$16,0) -> 0 | J79: =IF(AND(($C$8-$C$7/2)+Assumptions!$C$67>(J$8-J$7),($C$8-$C$7/2)+Assumptions!$C$67<=J$8),$C$16,0) -> 0 | K79: =IF(AND(($C$8-$C$7/2)+Assumptions!$C$67>(K$8-K$7),($C$8-$C$7/2)+Assumptions!$C$67<=K$8),$C$16,0) -> 0 | L79: =IF(AND(($C$8-$C$7/2)+Assumptions!$C$67>(L$8-L$7),($C$8-$C$7/2)+Assumptions!$C$67<=L$8),$C$16,0) -> 0
A80: 2028 hardware renewal | B80: =0 -> 0 | C80: =0 -> 0 | D80: =0 -> 0 | E80: =IF(AND(($D$8-$D$7/2)+Assumptions!$D$67>(E$8-E$7),($D$8-$D$7/2)+Assumptions!$D$67<=E$8),$D$16,0) -> 0 | F80: =IF(AND(($D$8-$D$7/2)+Assumptions!$D$67>(F$8-F$7),($D$8-$D$7/2)+Assumptions!$D$67<=F$8),$D$16,0) -> 0 | G80: =IF(AND(($D$8-$D$7/2)+Assumptions!$D$67>(G$8-G$7),($D$8-$D$7/2)+Assumptions!$D$67<=G$8),$D$16,0) -> 0 | H80: =IF(AND(($D$8-$D$7/2)+Assumptions!$D$67>(H$8-H$7),($D$8-$D$7/2)+Assumptions!$D$67<=H$8),$D$16,0) -> 0 | I80: =IF(AND(($D$8-$D$7/2)+Assumptions!$D$67>(I$8-I$7),($D$8-$D$7/2)+Assumptions!$D$67<=I$8),$D$16,0) -> 118272.89 | J80: =IF(AND(($D$8-$D$7/2)+Assumptions!$D$67>(J$8-J$7),($D$8-$D$7/2)+Assumptions!$D$67<=J$8),$D$16,0) -> 0 | K80: =IF(AND(($D$8-$D$7/2)+Assumptions!$D$67>(K$8-K$7),($D$8-$D$7/2)+Assumptions!$D$67<=K$8),$D$16,0) -> 0 | L80: =IF(AND(($D$8-$D$7/2)+Assumptions!$D$67>(L$8-L$7),($D$8-$D$7/2)+Assumptions!$D$67<=L$8),$D$16,0) -> 0
A81: 2029 hardware renewal | B81: =0 -> 0 | C81: =0 -> 0 | D81: =0 -> 0 | E81: =0 -> 0 | F81: =IF(AND(($E$8-$E$7/2)+Assumptions!$E$67>(F$8-F$7),($E$8-$E$7/2)+Assumptions!$E$67<=F$8),$E$16,0) -> 0 | G81: =IF(AND(($E$8-$E$7/2)+Assumptions!$E$67>(G$8-G$7),($E$8-$E$7/2)+Assumptions!$E$67<=G$8),$E$16,0) -> 0 | H81: =IF(AND(($E$8-$E$7/2)+Assumptions!$E$67>(H$8-H$7),($E$8-$E$7/2)+Assumptions!$E$67<=H$8),$E$16,0) -> 0 | I81: =IF(AND(($E$8-$E$7/2)+Assumptions!$E$67>(I$8-I$7),($E$8-$E$7/2)+Assumptions!$E$67<=I$8),$E$16,0) -> 0 | J81: =IF(AND(($E$8-$E$7/2)+Assumptions!$E$67>(J$8-J$7),($E$8-$E$7/2)+Assumptions!$E$67<=J$8),$E$16,0) -> 123465.41 | K81: =IF(AND(($E$8-$E$7/2)+Assumptions!$E$67>(K$8-K$7),($E$8-$E$7/2)+Assumptions!$E$67<=K$8),$E$16,0) -> 0 | L81: =IF(AND(($E$8-$E$7/2)+Assumptions!$E$67>(L$8-L$7),($E$8-$E$7/2)+Assumptions!$E$67<=L$8),$E$16,0) -> 0
A82: 2030 hardware renewal | B82: =0 -> 0 | C82: =0 -> 0 | D82: =0 -> 0 | E82: =0 -> 0 | F82: =0 -> 0 | G82: =IF(AND(($F$8-$F$7/2)+Assumptions!$F$67>(G$8-G$7),($F$8-$F$7/2)+Assumptions!$F$67<=G$8),$F$16,0) -> 0 | H82: =IF(AND(($F$8-$F$7/2)+Assumptions!$F$67>(H$8-H$7),($F$8-$F$7/2)+Assumptions!$F$67<=H$8),$F$16,0) -> 0 | I82: =IF(AND(($F$8-$F$7/2)+Assumptions!$F$67>(I$8-I$7),($F$8-$F$7/2)+Assumptions!$F$67<=I$8),$F$16,0) -> 0 | J82: =IF(AND(($F$8-$F$7/2)+Assumptions!$F$67>(J$8-J$7),($F$8-$F$7/2)+Assumptions!$F$67<=J$8),$F$16,0) -> 0 | K82: =IF(AND(($F$8-$F$7/2)+Assumptions!$F$67>(K$8-K$7),($F$8-$F$7/2)+Assumptions!$F$67<=K$8),$F$16,0) -> 125625.37 | L82: =IF(AND(($F$8-$F$7/2)+Assumptions!$F$67>(L$8-L$7),($F$8-$F$7/2)+Assumptions!$F$67<=L$8),$F$16,0) -> 0
A83: 2031 hardware renewal | B83: =0 -> 0 | C83: =0 -> 0 | D83: =0 -> 0 | E83: =0 -> 0 | F83: =0 -> 0 | G83: =0 -> 0 | H83: =IF(AND(($G$8-$G$7/2)+Assumptions!$G$67>(H$8-H$7),($G$8-$G$7/2)+Assumptions!$G$67<=H$8),$G$16,0) -> 0 | I83: =IF(AND(($G$8-$G$7/2)+Assumptions!$G$67>(I$8-I$7),($G$8-$G$7/2)+Assumptions!$G$67<=I$8),$G$16,0) -> 0 | J83: =IF(AND(($G$8-$G$7/2)+Assumptions!$G$67>(J$8-J$7),($G$8-$G$7/2)+Assumptions!$G$67<=J$8),$G$16,0) -> 0 | K83: =IF(AND(($G$8-$G$7/2)+Assumptions!$G$67>(K$8-K$7),($G$8-$G$7/2)+Assumptions!$G$67<=K$8),$G$16,0) -> 0 | L83: =IF(AND(($G$8-$G$7/2)+Assumptions!$G$67>(L$8-L$7),($G$8-$G$7/2)+Assumptions!$G$67<=L$8),$G$16,0) -> 125904.57
A84: 2032 hardware renewal | B84: =0 -> 0 | C84: =0 -> 0 | D84: =0 -> 0 | E84: =0 -> 0 | F84: =0 -> 0 | G84: =0 -> 0 | H84: =0 -> 0 | I84: =IF(AND(($H$8-$H$7/2)+Assumptions!$G$67>(I$8-I$7),($H$8-$H$7/2)+Assumptions!$G$67<=I$8),$H$16,0) -> 0 | J84: =IF(AND(($H$8-$H$7/2)+Assumptions!$G$67>(J$8-J$7),($H$8-$H$7/2)+Assumptions!$G$67<=J$8),$H$16,0) -> 0 | K84: =IF(AND(($H$8-$H$7/2)+Assumptions!$G$67>(K$8-K$7),($H$8-$H$7/2)+Assumptions!$G$67<=K$8),$H$16,0) -> 0 | L84: =IF(AND(($H$8-$H$7/2)+Assumptions!$G$67>(L$8-L$7),($H$8-$H$7/2)+Assumptions!$G$67<=L$8),$H$16,0) -> 0
A85: 2033 hardware renewal | B85: =0 -> 0 | C85: =0 -> 0 | D85: =0 -> 0 | E85: =0 -> 0 | F85: =0 -> 0 | G85: =0 -> 0 | H85: =0 -> 0 | I85: =0 -> 0 | J85: =IF(AND(($I$8-$I$7/2)+Assumptions!$G$67>(J$8-J$7),($I$8-$I$7/2)+Assumptions!$G$67<=J$8),$I$16,0) -> 0 | K85: =IF(AND(($I$8-$I$7/2)+Assumptions!$G$67>(K$8-K$7),($I$8-$I$7/2)+Assumptions!$G$67<=K$8),$I$16,0) -> 0 | L85: =IF(AND(($I$8-$I$7/2)+Assumptions!$G$67>(L$8-L$7),($I$8-$I$7/2)+Assumptions!$G$67<=L$8),$I$16,0) -> 0
A86: 2034 hardware renewal | B86: =0 -> 0 | C86: =0 -> 0 | D86: =0 -> 0 | E86: =0 -> 0 | F86: =0 -> 0 | G86: =0 -> 0 | H86: =0 -> 0 | I86: =0 -> 0 | J86: =0 -> 0 | K86: =IF(AND(($J$8-$J$7/2)+Assumptions!$G$67>(K$8-K$7),($J$8-$J$7/2)+Assumptions!$G$67<=K$8),$J$16,0) -> 0 | L86: =IF(AND(($J$8-$J$7/2)+Assumptions!$G$67>(L$8-L$7),($J$8-$J$7/2)+Assumptions!$G$67<=L$8),$J$16,0) -> 0
A87: 2035 hardware renewal | B87: =0 -> 0 | C87: =0 -> 0 | D87: =0 -> 0 | E87: =0 -> 0 | F87: =0 -> 0 | G87: =0 -> 0 | H87: =0 -> 0 | I87: =0 -> 0 | ... K87: =0 -> 0 | L87: =IF(AND(($K$8-$K$7/2)+Assumptions!$G$67>(L$8-L$7),($K$8-$K$7/2)+Assumptions!$G$67<=L$8),$K$16,0) -> 0
A88: 2036 hardware renewal | B88: =0 -> 0 | C88: =0 -> 0 | D88: =0 -> 0 | E88: =0 -> 0 | F88: =0 -> 0 | G88: =0 -> 0 | H88: =0 -> 0 | I88: =0 -> 0 | ... L88: =0 -> 0
A90: Growth-implied tangible reinvestment | H90: =Transition!C38 -> 74641.355 | I90: =Transition!D38 -> 68771.688 | J90: =Transition!E38 -> 59006.892 | K90: =Transition!F38 -> 44468.092 | L90: =Transition!G38 -> 69607.084
A91: Depreciation from earlier new cohorts | H91: =SUM(H50:H55,H64:H69) -> 130287.1 | I91: =SUM(I50:I56,I64:I70) -> 137782.33 | J91: =SUM(J50:J57,J64:J71) -> 144305.51 | K91: =SUM(K50:K58,K64:K72) -> 150409.62 | L91: =SUM(L50:L59,L64:L73) -> 155956.24
A92: Current-cohort D&A per commissioned dollar | H92: =0.5*(Assumptions!$G$72/Assumptions!$G$67+(1-Assumptions!$G$72)/Assumptions!$B$92) -> 0.07 | I92: =0.5*(Assumptions!$G$72/Assumptions!$G$67+(1-Assumptions!$G$72)/Assumptions!$B$92) -> 0.07 | J92: =0.5*(Assumptions!$G$72/Assumptions!$G$67+(1-Assumptions!$G$72)/Assumptions!$B$92) -> 0.07 | K92: =0.5*(Assumptions!$G$72/Assumptions!$G$67+(1-Assumptions!$G$72)/Assumptions!$B$92) -> 0.07 | L92: =0.5*(Assumptions!$G$72/Assumptions!$G$67+(1-Assumptions!$G$72)/Assumptions!$B$92) -> 0.07
A93: Depreciation independent of current CapEx | H93: =SUM(H21:H22,H91)+H13*Assumptions!$G$62*H92 -> 147188.4 | I93: =SUM(I21:I22,I91)+I13*Assumptions!$G$62*I92 -> 155033.77 | J93: =SUM(J21:J22,J91)+J13*Assumptions!$G$62*J92 -> 161768.51 | K93: =SUM(K21:K22,K91)+K13*Assumptions!$G$62*K92 -> 167882.38 | L93: =SUM(L21:L22,L91)+L13*Assumptions!$G$62*L92 -> 173199.74
A94: Depreciation per current CapEx dollar | H94: =0.5*Assumptions!$G$62*H92 -> 0.021 | I94: =0.5*Assumptions!$G$62*I92 -> 0.021 | J94: =0.5*Assumptions!$G$62*J92 -> 0.021 | K94: =0.5*Assumptions!$G$62*K92 -> 0.021 | L94: =0.5*Assumptions!$G$62*L92 -> 0.021
A95: Cash CapEx solving for growth investment | H95: =MAX(0,(H90+H93-H37)/(1-H94)) -> 221869.37 | I95: =MAX(0,(I90+I93-I37)/(1-I94)) -> 224301.41 | J95: =MAX(0,(J90+J93-J37)/(1-J94)) -> 221755.27 | K95: =MAX(0,(K90+K93-K37)/(1-K94)) -> 213824.35 | L95: =MAX(0,(L90+L93-L37)/(1-L94)) -> 245718.64
A96: Net tangible cash reinvestment | B96: =B34+B37-B32 -> 102021.71 | C96: =C34+C37-C32 -> 156008.17 | D96: =D34+D37-D32 -> 124719.34 | E96: =E34+E37-E32 -> 121513.28 | F96: =F34+F37-F32 -> 105440.22 | G96: =G34+G37-G32 -> 77297.472 | H96: =H34+H37-H32 -> 74641.355 | I96: =I34+I37-I32 -> 68771.688 | ... L96: =L34+L37-L32 -> 69607.084
A97: Additional reinvestment from renewal floor | H97: =MAX(0,H96-H90) -> 0 | I97: =MAX(0,I96-I90) -> 0 | J97: =MAX(0,J96-J90) -> 0 | K97: =MAX(0,K96-K90) -> 0 | L97: =MAX(0,L96-L90) -> 0
A98: Depreciation solution reconciliation | H98: =H24-(H93+H94*H12) -> 0 | I98: =I24-(I93+I94*I12) -> 0 | J98: =J24-(J93+J94*J12) -> 0 | K98: =K24-(K93+K94*K12) -> 0 | L98: =L24-(L93+L94*L12) -> 0
A101: 2032–2036 retains the asset cohorts and renewal floor. Required gross CapEx is solved algebraically from target net investment and depreciation to avoid a circular formula.
A102: Commissioning is a delivery proxy. Asset mix and lives are scenario assumptions; no separate physical workload or Cloud-only asset allocation is disclosed.
A103: Transition EBIT follows the mature-margin assumption. Renewal costs can increase cash reinvestment above the growth-implied amount and lower realised incremental returns.
A104: Existing finite intangibles run off through 2036: disclosed schedule through 2030, retained 2031 estimate, residual spread over 2032–2036. No future acquisitions assumed; R&D remains expensed.
A105: Economic depreciation is not tax depreciation. Cash tax timing and finance-lease additions remain unresolved calibration items.
A107: Existing acquired-intangible roll-forward
A108: Opening definite-lived intangibles | B108: =SUM('Sources and basis'!E47:I47)+'Sources and basis'!B56 -> 8894 | C108: =B110 -> 8147 | D108: =C110 -> 6843 | E108: =D110 -> 5701 | F108: =E110 -> 4605 | G108: =F110 -> 3550 | H108: =G110 -> 2495 | I108: =H110 -> 1996 | J108: =I110 -> 1497 | ... L108: =K110 -> 499
A109: Amortisation of existing intangibles | B109: =B25 -> 747 | C109: =C25 -> 1304 | D109: =D25 -> 1142 | E109: =E25 -> 1096 | F109: =F25 -> 1055 | G109: =G25 -> 1055 | H109: =H25 -> 499 | I109: =I25 -> 499 | ... L109: =L25 -> 499
A110: Closing definite-lived intangibles | B110: =MAX(0,B108-B109) -> 8147 | C110: =MAX(0,C108-C109) -> 6843 | D110: =MAX(0,D108-D109) -> 5701 | E110: =MAX(0,E108-E109) -> 4605 | F110: =MAX(0,F108-F109) -> 3550 | G110: =MAX(0,G108-G109) -> 2495 | H110: =MAX(0,H108-H109) -> 1996 | I110: =MAX(0,I108-I109) -> 1497 | ... L110: =MAX(0,L108-L109) -> 0
A111: Closing indefinite-lived intangibles | B111: ='Balance sheet'!$I$22-$B$108 -> 211 | C111: ='Balance sheet'!$I$22-$B$108 -> 211 | D111: ='Balance sheet'!$I$22-$B$108 -> 211 | E111: ='Balance sheet'!$I$22-$B$108 -> 211 | F111: ='Balance sheet'!$I$22-$B$108 -> 211 | G111: ='Balance sheet'!$I$22-$B$108 -> 211 | H111: ='Balance sheet'!$I$22-$B$108 -> 211 | I111: ='Balance sheet'!$I$22-$B$108 -> 211 | ... L111: ='Balance sheet'!$I$22-$B$108 -> 211
A112: Total closing intangible book value | B112: =SUM(B110:B111) -> 8358 | C112: =SUM(C110:C111) -> 7054 | D112: =SUM(D110:D111) -> 5912 | E112: =SUM(E110:E111) -> 4816 | F112: =SUM(F110:F111) -> 3761 | G112: =SUM(G110:G111) -> 2706 | H112: =SUM(H110:H111) -> 2207 | I112: =SUM(I110:I111) -> 1708 | ... L112: =SUM(L110:L111) -> 211
A114: Existing goodwill (no amortisation) | B114: ='Balance sheet'!$I$21 -> 57828 | C114: ='Balance sheet'!$I$21 -> 57828 | D114: ='Balance sheet'!$I$21 -> 57828 | E114: ='Balance sheet'!$I$21 -> 57828 | F114: ='Balance sheet'!$I$21 -> 57828 | G114: ='Balance sheet'!$I$21 -> 57828 | H114: ='Balance sheet'!$I$21 -> 57828 | I114: ='Balance sheet'!$I$21 -> 57828 | ... L114: ='Balance sheet'!$I$21 -> 57828
A116: Thereafter allocation check | B116: =SUM(G25:L25)-'Sources and basis'!B56 -> 0
...

Sheet Transition
A1: Alphabet | transition to steady state
A2: USD millions. Five-year transition after 2031; growth and reinvestment fade gradually. No assumed margin recovery unless separately justified.
A3: Selected case | B3: =Assumptions!B3 -> Base
A6: Steady-state transition | B6: 2031 anchor | C6: 2032 E | D6: 2033 E | E6: 2034 E | F6: 2035 E | G6: 2036 E | H6: 2037 terminal
A7: Transition completed | B7: =0 -> 0 | C7: =MIN(1,(2-1)/Assumptions!$B$147) -> 0.2 | D7: =MIN(1,(3-1)/Assumptions!$B$147) -> 0.4 | E7: =MIN(1,(4-1)/Assumptions!$B$147) -> 0.6 | F7: =MIN(1,(5-1)/Assumptions!$B$147) -> 0.8 | G7: =MIN(1,(6-1)/Assumptions!$B$147) -> 1 | H7: =1 -> 1
A8: Revenue growth | B8: ='Operating forecast'!K16/'Operating forecast'!J16-1 -> 0.089689705 | C8: =$B$8+($B$24-$B$8)*C7 -> 0.077751764 | D8: =$B$8+($B$24-$B$8)*D7 -> 0.065813823 | E8: =$B$8+($B$24-$B$8)*E7 -> 0.053875882 | F8: =$B$8+($B$24-$B$8)*F7 -> 0.041937941 | G8: =$B$8+($B$24-$B$8)*G7 -> 0.03 | H8: =$B$8+($B$24-$B$8)*H7 -> 0.03
A9: Revenue | B9: ='Operating forecast'!K16 -> 950091.05 | C9: =B9*(1+C8) -> 1023962.3 | D9: =C9*(1+D8) -> 1091353.2 | E9: =D9*(1+E8) -> 1150150.8 | F9: =E9*(1+F8) -> 1198385.8 | G9: =F9*(1+G8) -> 1234337.3 | H9: =G9*(1+H8) -> 1271367.4
A10: Operating margin | B10: ='Operating forecast'!K34 -> 0.28439279 | C10: =$B$55+($B$27-$B$55)*C7-C56/C9 -> 0.28504316 | D10: =$B$55+($B$27-$B$55)*D7-D56/D9 -> 0.28507325 | E10: =$B$55+($B$27-$B$55)*E7-E56/E9 -> 0.28509663 | F10: =$B$55+($B$27-$B$55)*F7-F56/F9 -> 0.28511409 | G10: =$B$55+($B$27-$B$55)*G7-G56/G9 -> 0.28512622 | H10: =$B$55+($B$27-$B$55)*H7-H56/H9 -> 0.28553048
A11: Operating profit | B11: ='Operating forecast'!K33 -> 270199.04 | C11: =C9*C10 -> 291873.45 | D11: =D9*D10 -> 311115.6 | E11: =E9*E10 -> 327904.11 | F11: =F9*F10 -> 341676.66 | G11: =G9*G10 -> 351941.93 | H11: =H9*H10 -> 363014.16
A12: Operating tax rate | B12: =Assumptions!G77 -> 0.18 | C12: =$B$12+(Assumptions!$B$149-$B$12)*C7 -> 0.186 | D12: =$B$12+(Assumptions!$B$149-$B$12)*D7 -> 0.192 | E12: =$B$12+(Assumptions!$B$149-$B$12)*E7 -> 0.198 | F12: =$B$12+(Assumptions!$B$149-$B$12)*F7 -> 0.204 | G12: =$B$12+(Assumptions!$B$149-$B$12)*G7 -> 0.21 | H12: =$B$12+(Assumptions!$B$149-$B$12)*H7 -> 0.21
A13: NOPAT | B13: ='Operating forecast'!K36 -> 221373.31 | C13: =C57-C56+C58 -> 237492.18 | D13: =D57-D56+D58 -> 251285.6 | E13: =E57-E56+E58 -> 262880.3 | F13: =F57-F56+F58 -> 271872.83 | G13: =G57-G56+G58 -> 277929.34 | H13: =H57-H56+H58 -> 286781.19
A14: Net tangible reinvestment / pre-amort NOPAT | B14: =B15/B57 -> 0.34751633 | C14: =IF(ISNUMBER(C15),C15/C57,"") -> 0.31363077 | D14: =IF(ISNUMBER(D15),D15/D57,"") -> 0.27313699 | E14: =IF(ISNUMBER(E15),E15/E57,"") -> 0.2240377 | F14: =IF(ISNUMBER(F15),F15/F57,"") -> 0.16326245 | G14: =IF(ISNUMBER(G15),G15/G57,"") -> 0.25 | H14: =$B$26 -> 0.25
A15: Net tangible cash reinvestment | B15: ='Capital and FCFF'!G96 -> 77297.472 | C15: ='Capital and FCFF'!H96 -> 74641.355 | D15: ='Capital and FCFF'!I96 -> 68771.688 | E15: ='Capital and FCFF'!J96 -> 59006.892 | F15: ='Capital and FCFF'!K96 -> 44468.092 | G15: ='Capital and FCFF'!L96 -> 69607.084 | H15: =H13*H14 -> 71695.297
A16: FCFF | B16: =B13+B56-B15 -> 145130.84 | C16: =C13+C56-C15 -> 163349.82 | D16: =D13+D56-D15 -> 183012.91 | E16: =E13+E56-E15 -> 204372.41 | F16: =F13+F56-F15 -> 227903.74 | G16: =G13+G56-G15 -> 208821.25 | H16: =H13+H56-H15 -> 215085.89
A18: Cash-flow date | B18: =DATE(2031,12,31) -> 48213 | C18: =DATE(2032,12,31) -> 48579 | D18: =DATE(2033,12,31) -> 48944 | E18: =DATE(2034,12,31) -> 49309 | F18: =DATE(2035,12,31) -> 49674 | G18: =DATE(2036,12,31) -> 50040 | H18: =DATE(2037,12,31) -> 50405
A19: Years from valuation date | B19: =YEARFRAC(Valuation!$B$4,B18,3)-IF(Valuation!$B$24=1,0.5,0) -> 4.6863014 | C19: =YEARFRAC(Valuation!$B$4,C18,3)-IF(Valuation!$B$24=1,0.5,0) -> 5.6890411 | D19: =YEARFRAC(Valuation!$B$4,D18,3)-IF(Valuation!$B$24=1,0.5,0) -> 6.6890411 | E19: =YEARFRAC(Valuation!$B$4,E18,3)-IF(Valuation!$B$24=1,0.5,0) -> 7.6890411 | F19: =YEARFRAC(Valuation!$B$4,F18,3)-IF(Valuation!$B$24=1,0.5,0) -> 8.6890411 | G19: =YEARFRAC(Valuation!$B$4,G18,3)-IF(Valuation!$B$24=1,0.5,0) -> 9.6917808 | H19: =YEARFRAC(Valuation!$B$4,H18,3)-IF(Valuation!$B$24=1,0.5,0) -> 10.691781
A20: Present value of transition FCFF | C20: =IF(AND(ISNUMBER(Valuation!$B$29),Valuation!$B$29>0),C16/(1+Valuation!$B$29)^C19,"") -> 98068.63 | D20: =IF(AND(ISNUMBER(Valuation!$B$29),Valuation!$B$29>0),D16/(1+Valuation!$B$29)^D19,"") -> 100448.42 | E20: =IF(AND(ISNUMBER(Valuation!$B$29),Valuation!$B$29>0),E16/(1+Valuation!$B$29)^E19,"") -> 102549.5 | F20: =IF(AND(ISNUMBER(Valuation!$B$29),Valuation!$B$29>0),F16/(1+Valuation!$B$29)^F19,"") -> 104547.26 | G20: =IF(AND(ISNUMBER(Valuation!$B$29),Valuation!$B$29>0),G16/(1+Valuation!$B$29)^G19,"") -> 87554.635
A23: Terminal controls
A24: Steady-state growth | B24: =Valuation!B21 -> 0.03
A25: Steady-state return on capital | B25: =MIN(B36,Assumptions!B192) -> 0.12
A26: Steady-state reinvestment rate | B26: =B24/B25 -> 0.25
A27: Margin target used | B27: =IF(ISNUMBER(Assumptions!B148),Assumptions!B148,B55) -> 0.28553048
A28: Terminal growth check | B28: =IF(AND(ISNUMBER(Valuation!B29),B24<Valuation!B29,B24<B25),"Ready","Review WACC / terminal inputs") -> Ready
A31: Growth fades over 2032–2036. The terminal return is capped at the starting implied return, so a weak case does not automatically recover to an arbitrary 15%.
A32: Growth-implied net investment funds next-year NOPAT. Capital and FCFF extends depreciation and hardware renewal through 2036; a binding renewal floor increases actual reinvestment.
A33: Incremental returns use pre-acquired-amortisation NOPAT and net tangible reinvestment. Finite amortisation runoff and related tax benefits do not represent growth earned on new investment.
A35: Incremental return and reinvestment
A36: Return on new capital — next-year convention | B36: =(C57-B59)/B60 -> 0.20099496 | C36: =$B$36+($B$25-$B$36)*C7 -> 0.18479597 | D36: =$B$36+($B$25-$B$36)*D7 -> 0.16859698 | E36: =$B$36+($B$25-$B$36)*E7 -> 0.15239798 | F36: =$B$36+($B$25-$B$36)*F7 -> 0.13619899 | G36: =$B$36+($B$25-$B$36)*G7 -> 0.12 | H36: =$B$25 -> 0.12
A37: Next-year pre-amortisation NOPAT increase | B37: =C57-B59 -> 15541.611 | C37: =D57-C57 -> 13793.422 | D37: =E57-D57 -> 11594.699 | E37: =F57-E57 -> 8992.5314 | F37: =G57-F57 -> 6056.5093 | G37: =H57-G57 -> 8352.8501 | H37: =H57*$B$24 -> 8603.4356
A38: Growth-implied net investment before renewal floor | C38: =IF(C36>0,C37/C36,NA()) -> 74641.355 | D38: =IF(D36>0,D37/D36,NA()) -> 68771.688 | E38: =IF(E36>0,E37/E36,NA()) -> 59006.892 | F38: =IF(F36>0,F37/F36,NA()) -> 44468.092 | G38: =IF(G36>0,G37/G36,NA()) -> 69607.084
A39: Return supported by actual cash reinvestment | C39: =IF(C15>0,C37/C15,NA()) -> 0.18479597 | D39: =IF(D15>0,D37/D15,NA()) -> 0.16859698 | E39: =IF(E15>0,E37/E15,NA()) -> 0.15239798 | F39: =IF(F15>0,F37/F15,NA()) -> 0.13619899 | G39: =IF(G15>0,G37/G15,NA()) -> 0.12
A40: Extra investment required by renewal floor | C40: ='Capital and FCFF'!H97 -> 0 | D40: ='Capital and FCFF'!I97 -> 0 | E40: ='Capital and FCFF'!J97 -> 0 | F40: ='Capital and FCFF'!K97 -> 0 | G40: ='Capital and FCFF'!L97 -> 0
A42: Terminal FCFF change vs final transition | B42: =H16/G16-1 -> 0.03 | C42: Review large discontinuities; terminal reinvestment must cover a sustainable replacement burden.
A43: Terminal investment / final net investment | B43: =H15/G15 -> 1.03 | C43: A large decline requires an economic explanation, not just a formula transition.
A44: Terminal FCFF continuity | B44: =IF(ABS(B42)<=0.25,"Within 25% review threshold","Review terminal transition") -> Within 25% review threshold | C44: Analyst review threshold, not an assertion of fair value.
A46: Construction-in-progress normalisation before the terminal period
A47: 2031 closing assets not in service | B47: ='Capital and FCFF'!G15 -> 244953.27
A48: Normal level at historical commissioning rate | B48: ='Capital and FCFF'!G12*(1/Assumptions!B170-0.5) -> 245138.39
A49: Excess / (shortfall) versus normal | B49: =B47-B48 -> -185.113
A50: Annual depreciation per commissioned dollar | B50: =Assumptions!G72/Assumptions!G67+(1-Assumptions!G72)/Assumptions!B92 -> 0.14
A51: Depreciation normalisation | B51: =B49*B50 -> -25.91582
A52: Normalised 2031 operating margin | B52: =B10-B51/B9 -> 0.28442006
A53: Normalised 2031 NOPAT after acquired amortisation | B53: =B9*B52-MAX(0,B9*B52+B56*(1-Assumptions!B239))*B12 -> 221394.57
A54: Build timing is normalised for the earnings baseline: depreciation is charged as if construction in progress were at its normal level of (1/rate − 0.5) years of CapEx. The asset schedule retains actual construction balances and scenario commissioning rates. The transition starts from the normalised margin before acquired amortisation (B55), then deducts the finite runoff schedule. The starting incremental return uses normalised pre-amortisation NOPAT (B59) and tangible reinvestment (B60), so legacy amortisation expiry does not create investment returns. The Base build is already near its normal level.
A55: Normalised margin before acquired amortisation | B55: =B52+'Capital and FCFF'!G25/B9 -> 0.28553048
A56: Existing acquired amortisation | B56: ='Capital and FCFF'!G25 -> 1055 | C56: ='Capital and FCFF'!H25 -> 499 | D56: ='Capital and FCFF'!I25 -> 499 | E56: ='Capital and FCFF'!J25 -> 499 | F56: ='Capital and FCFF'!K25 -> 499 | G56: ='Capital and FCFF'!L25 -> 499 | H56: =0 -> 0
A57: NOPAT before acquired amortisation | B57: =(B11+B56)-MAX(0,B11+B56)*B12 -> 222428.31 | C57: =(C11+C56)-MAX(0,C11+C56)*C12 -> 237991.18 | D57: =(D11+D56)-MAX(0,D11+D56)*D12 -> 251784.6 | E57: =(E11+E56)-MAX(0,E11+E56)*E12 -> 263379.3 | F57: =(F11+F56)-MAX(0,F11+F56)*F12 -> 272371.83 | G57: =(G11+G56)-MAX(0,G11+G56)*G12 -> 278428.34 | H57: =(H11+H56)-MAX(0,H11+H56)*H12 -> 286781.19
A58: Cash tax benefit from acquired amortisation | B58: =MAX(0,B11+B56)*B12-MAX(0,B11+B56*(1-Assumptions!$B$239))*B12 -> 0 | C58: =MAX(0,C11+C56)*C12-MAX(0,C11+C56*(1-Assumptions!$B$239))*C12 -> 0 | D58: =MAX(0,D11+D56)*D12-MAX(0,D11+D56*(1-Assumptions!$B$239))*D12 -> 0 | E58: =MAX(0,E11+E56)*E12-MAX(0,E11+E56*(1-Assumptions!$B$239))*E12 -> 0 | F58: =MAX(0,F11+F56)*F12-MAX(0,F11+F56*(1-Assumptions!$B$239))*F12 -> 0 | G58: =MAX(0,G11+G56)*G12-MAX(0,G11+G56*(1-Assumptions!$B$239))*G12 -> 0 | H58: =MAX(0,H11+H56)*H12-MAX(0,H11+H56*(1-Assumptions!$B$239))*H12 -> 0
A59: Normalised pre-amortisation NOPAT | B59: =B9*B55-MAX(0,B9*B55)*B12 -> 222449.57
A60: Normalised 2031 tangible reinvestment | B60: =B15-B51 -> 77323.388

Sheet Relative valuation
A1: Alphabet | relative valuation and multiples-based sum of the parts
A2: USD millions. Valuation 25 October 2026; market closes 23 October. Latest available filings are used. EV adds financing and explicit settlement claims; excludes operating leases (rent remains in EBIT); deducts non-operating financial assets and retains 2% of revenue as operating cash. Book/face-value claims remain proxies.
A4: Peer valuation: 23 October 2026 market closes
A5: USD millions unless stated | B5: Alphabet | C5: Meta | D5: Microsoft | E5: Oracle | F5: Amazon (AWS benchmark) | G5: Basis / source
A6: Period used | B6: TTM Jun 2026 | C6: TTM Sep 2026 | D6: FY Jun 2026 | E6: TTM Aug 2026 | F6: TTM Jun 2026 (AWS) | G6: Meta September and Oracle August are newly reported; Alphabet and AWS remain June, Microsoft FY June.
A7: Share price, 23 Oct 2026 close (USD) | C7: 642.62 | D7: 524.51 | E7: 126.16 | F7: 248 | G7: Google Finance dated 23 October closes: https://www.google.com/finance/quote/META:NASDAQ (MSFT, ORCL, AMZN same provider). Alphabet group cap from YCharts.
A8: Shares outstanding (millions) | C8: 2556.2413 | D8: 7425.5455 | E8: 3023.736 | F8: 10783 | G8: Latest filing cover shares: Meta 16 Oct (A+B); Microsoft 23 Jul; Oracle 7 Sep; Amazon Q2. Share-count carry-forwards may miss subsequent issuance/repurchases.
A9: Market capitalisation | B9: =Valuation!B7 -> 3916000 | C9: =C7*C8 -> 1642691.8 | D9: =D7*D8 -> 3894772.9 | E9: =E7*E8 -> 381474.53 | F9: =F7*F8 -> 2674184
A10: Financing and settlement claims | C10: =B73+B74+B75+B76 -> 108151 | D10: 106888 | E10: =7625+117712+749+8436+4954+424 -> 139900 | G10: Meta: current/long debt + finance-lease ROU proxy + non-contingent settlement nominal proxy. Microsoft: notes 40,294 + finance leases 66,594. Oracle: current/long notes + finance leases + 4,954 preferred proxy + 424 NCI.
A11: Less: cash and marketable securities | C11: =11222+71227 -> 82449 | D11: 76843 | E11: =36369+708 -> 37077 | G11: Meta 30 September; Microsoft 30 June; Oracle 31 August. Meta restricted cash is excluded from the non-operating credit.
A12: Less: non-marketable and equity investments | C12: 32624 | D12: 36348 | E12: 2400 | G12: Private/equity investment balances: Meta September, Microsoft June, Oracle August (primarily TikTok USDS). Carrying-value proxies.
A13: Add: operating cash reserve (2% of revenue) | C13: =0.02*C15 -> 4832.1 | D13: =0.02*D15 -> 6636.78 | E13: =0.02*E15 -> 1435.52 | G13: Same 2% reserve as Financial assets!B30.
A14: Enterprise value (Alphabet: market-implied operating EV) | B14: =Valuation!B52 -> 3749969.9 | C14: =C9+C10-C11-C12+C13 -> 1640601.9 | D14: =D9+D10-D11-D12+D13 -> 3895106.6 | E14: =E9+E10-E11-E12+E13 -> 483333.05 | G14: Amazon EV not computed: finance leases not collected and retail dominates; AWS used for operating comparison only.
A15: Revenue | B15: ='Historical base'!F16 -> 445866 | C15: =200966+181712-141073 -> 241605 | D15: 331839 | E15: =67357+19345-14926 -> 71776 | F15: 148404 | G15: TTM = latest full year + current YTD − prior YTD. Meta 9 months; Oracle first quarter. Filing inputs sourced below.
A16: Revenue growth vs prior twelve months | B16: ='Historical base'!F16/371399-1 -> 0.20050404 | C16: =C15/B78-1 -> 0.27524306 | D16: =331839/281724-1 -> 0.17788687 | E16: =E15/(57399+14926-13307)-1 -> 0.21617134 | F16: 0.2752 | G16: Same-period prior-TTM growth; Meta base reconciled below. Oracle FY2025 + Q1FY2026 − Q1FY2025; Alphabet/AWS prior bases unchanged.
A17: Operating income (EBIT) | B17: ='Historical base'!F24 -> 147628 | C17: =83276+54635-58531 -> 79380 | D17: 155237 | E17: =20606+6728-4277 -> 23057 | F17: 54681 | G17: GAAP EBIT for peer table. Meta includes a 9,890 settlement charge; Services valuation uses separately normalised group/FoA EBIT, adding this charge back.
A18: Operating margin | B18: =B17/B15 -> 0.33110396 | C18: =C17/C15 -> 0.3285528 | D18: =D17/D15 -> 0.46780818 | E18: =E17/E15 -> 0.32123551 | F18: =F17/F15 -> 0.36846042
A19: Cash purchases of property and equipment | B19: ='Historical base'!F35 -> 132402 | C19: =69691+83055-48308 -> 104438 | D19: 115948 | E19: =55663+28499-8502 -> 75660 | G19: Cash PP&E purchases only, excluding lease additions. Meta 9-month and Oracle first-quarter TTM bridges; Microsoft FYJune. Oracle includes accelerated construction spending.
A20: Cash CapEx / revenue | B20: =B19/B15 -> 0.29695469 | C20: =C19/C15 -> 0.43226754 | D20: =D19/D15 -> 0.34941041 | E20: =E19/E15 -> 1.0541128
A21: EV / EBIT | B21: =B14/B17 -> 25.401481 | C21: =C14/C17 -> 20.667698 | D21: =D14/D17 -> 25.091355 | E21: =E14/E17 -> 20.96253 | G21: Trailing multiple; Alphabet at its market-implied operating EV.
A22: DCF-implied EV / EBIT (Alphabet) | B22: =Valuation!B48/B17 -> 14.680604 | G22: Our Base operating EV over the same trailing EBIT.
A24: Segment benchmarks | B24: Revenue | C24: Growth | D24: EBIT | E24: Margin | G24: Basis / source
A25: Alphabet Google Cloud (TTM Jun 2026) | B25: ='Historical base'!F13 -> 77617 | C25: 0.578 | D25: ='Historical base'!F21 -> 24319 | E25: =D25/B25 -> 0.31332054 | G25: Prior TTM 49,192 (FY2024 43,229 + H1 2025 25,884 - H1 2024 19,921).
A26: Amazon Web Services (TTM Jun 2026) | B26: 148404 | C26: 0.2752 | D26: 54681 | E26: =D26/B26 -> 0.36846042 | G26: Amazon Q2 2026 release.
A27: Microsoft Intelligent Cloud (FY Jun 2026) | B27: 137791 | C27: =137791/106265-1 -> 0.29667341 | D27: 56972 | E27: =D27/B27 -> 0.41346677 | G27: Microsoft FY2026 Q4 release; segment includes server products and enterprise services.
A28: Oracle Cloud Infrastructure (FY May 2026) | B28: 18101 | C28: =18101/10234-1 -> 0.76871214 | G28: Oracle FY2026 Q4 release; segment profit not disclosed.
A29: Alphabet Google Services (TTM Jun 2026) | B29: ='Historical base'!F12 -> 367091 | D29: ='Historical base'!F20 -> 153792 | E29: =D29/B29 -> 0.41894789 | G29: Segment operating income before Alphabet-level costs.
A30: Meta Family of Apps (TTM Sep 2026) | D30: =102469+67410-71702 -> 98177 | G30: GAAP FoA EBIT. Add the disclosed 9,890 legal charge for the recurring-profit benchmark in B72.
A33: Multiples and inputs
B34: Low | C34: Central | D34: High | G34: Basis
A35: Services EV/EBIT (Meta) | B35: =C14/$B$72 -> 15.18134 | C35: =AVERAGE(B35,D35) -> 16.779658 | D35: =C14/$B$71 -> 18.377975 | G35: Meta settlement charge added back to group/FoA EBIT, with its unpaid non-contingent claim added to EV. Low: Reality Labs worth zero; high: RL losses continue. This avoids capitalising the one-off charge as recurring.
A36: Cloud EV/EBIT (Microsoft, Oracle) | B36: =MIN(D21,E21) -> 20.96253 | C36: =AVERAGE(D21,E21) -> 23.026942 | D36: =MAX(D21,E21) -> 25.091355 | G36: Imperfect references: neither is a pure cloud business, and AWS has no separate market value. A growth premium is tested through the required multiple in row 60, not assumed.
A37: Cloud EBIT applied | B37: =D25 -> 24319 | C37: =D25 -> 24319 | D37: =2*'Historical base'!E21 -> 30824 | G37: TTM Jun 2026; high case uses annualised H1 2026 EBIT (15,412 x 2), labelled as run-rate, not a forecast.
A38: Alphabet-level cost multiple (EBIT-weighted blend) | B38: =($D$29*B35+B37*B36)/($D$29+B37) -> 15.970695 | C38: =($D$29*C35+C37*C36)/($D$29+C37) -> 17.632652 | D38: =($D$29*D35+D37*D36)/($D$29+D37) -> 19.49886 | G38: Shared costs (TTM 21,541, mostly AI research) are deducted at the same blend of segment multiples; they are not allocated to segments, so they are counted once.
A39: Waymo post-money valuation, Feb 2026 | B39: 126000 | C39: 126000 | D39: 126000 | G39: Waymo USD 16bn round (Waymo, 2026). A funding price is not a measure of intrinsic value.
A40: Alphabet ownership of Waymo | B40: 0.6 | C40: 0.75 | D40: 0.9 | G40: Not disclosed; Alphabet is the majority investor. Range is analyst judgement.
A41: Waymo share of Other Bets losses | B41: 0.5 | C41: 0.65 | D41: 0.8 | G41: Not disclosed; allocation sensitivity. The remainder belongs to residual ventures.
A42: Residual-venture loss horizon (years) | B42: 5 | C42: 5 | D42: 5 | G42: Assumes continued investment for five years, then restructuring or closure; losses after tax at the 21% benchmark, discounted at WACC.
A43: Waymo cash inside the round value | B43: 16000 | C43: 8000 | D43: 0 | G43: Cash already embedded in the February equity-round price, bounded by the 16bn equity raise. October loan proceeds and debt offset in the group bridge and are not deducted a second time.
A45: Sum of the parts | B45: Low | C45: Central | D45: High | G45: Basis
A46: Google Services | B46: =$D$29*B35 -> 2334768.6 | C46: =$D$29*C35 -> 2580577.1 | D46: =$D$29*D35 -> 2826385.6 | G46: TTM segment operating income x Services multiple.
A47: Google Cloud | B47: =B37*B36 -> 509787.77 | C47: =C37*C36 -> 559992.21 | D47: =D37*D36 -> 773415.92 | G47: Cloud EBIT x Cloud multiple.
A48: Less: Alphabet-level costs | B48: ='Historical base'!$F$23*B38 -> -344024.73 | C48: ='Historical base'!$F$23*C38 -> -379824.96 | D48: ='Historical base'!$F$23*D38 -> -420024.94 | G48: TTM 21,541 x blended multiple.
A49: Waymo, attributable | B49: =B39*B40 -> 75600 | C49: =C39*C40 -> 94500 | D49: =D39*D40 -> 113400 | G49: Post-money x ownership. Alphabet's share of Waymo cash is inside this value.
A50: Less: residual ventures | B50: ='Historical base'!$F$22*(1-B41)*(1-Assumptions!$B$5)*(1-(1+Valuation!$B$29)^-B42)/Valuation!$B$29 -> -13603.127 | C50: ='Historical base'!$F$22*(1-C41)*(1-Assumptions!$B$5)*(1-(1+Valuation!$B$29)^-C42)/Valuation!$B$29 -> -9522.1889 | D50: ='Historical base'!$F$22*(1-D41)*(1-Assumptions!$B$5)*(1-(1+Valuation!$B$29)^-D42)/Valuation!$B$29 -> -5441.2508 | G50: Present value of residual Other Bets losses over the horizon.
A51: Value of parts before group bridge | B51: =SUM(B46:B50) -> 2562528.5 | C51: =SUM(C46:C50) -> 2845722.2 | D51: =SUM(D46:D50) -> 3287735.3 | G51: Mixes operating values with Waymo attributable equity, so it is not an operating EV and is not divided by consolidated EBIT.
A52: Add: non-operating assets | B52: =Valuation!$B$49 -> 307266.47 | C52: =Valuation!$B$49 -> 307266.47 | D52: =Valuation!$B$49 -> 307266.47 | G52: Same credit as the DCF bridge.
A53: Less: all Waymo cash credited in the bridge | B53: =-B43 -> -16000 | C53: =-C43 -> -8000 | D53: =-D43 -> 0 | G53: The consolidated bridge credits 100% of Waymo cash: Alphabet's share is already in the attributable value and the outside share belongs to Waymo's other holders.
A54: Less: financing, settlement and NCI claims | B54: =-Valuation!$B$50 -> -141236.33 | C54: =-Valuation!$B$50 -> -141236.33 | D54: =-Valuation!$B$50 -> -141236.33 | G54: Same claims as the DCF, NCI included in full: the Waymo share of the 7,100 NCI is not disclosed, so this may overstate claims by up to 7,100.
A55: SOTP common equity value | B55: =SUM(B51:B54) -> 2712558.7 | C55: =SUM(C51:C54) -> 3003752.3 | D55: =SUM(D51:D54) -> 3453765.5
A56: vs market capitalisation | B56: =B55/Valuation!$B$7-1 -> -0.30731392 | C56: =C55/Valuation!$B$7-1 -> -0.23295396 | D56: =D55/Valuation!$B$7-1 -> -0.11803742
A57: DCF common equity value | B57: =Valuation!$B$48+Valuation!$B$49-Valuation!$B$50 -> 2333298.4 | C57: =Valuation!$B$48+Valuation!$B$49-Valuation!$B$50 -> 2333298.4 | D57: =Valuation!$B$48+Valuation!$B$49-Valuation!$B$50 -> 2333298.4 | G57: Base DCF bridge.
A58: SOTP vs DCF | B58: =B55/B57-1 -> 0.16254254 | C58: =C55/C57-1 -> 0.28734168 | D58: =D55/D57-1 -> 0.48020735
A60: Cloud EV/EBIT needed to reach market capitalisation (Services at peer multiple) | B60: =((Valuation!$B$7-(B49+B50+B52+B53+B54))/(1-ABS('Historical base'!$F$23)/($D$29+B37))-$D$29*B35)/B37 -> 77.256438 | C60: =((Valuation!$B$7-(C49+C50+C52+C53+C54))/(1-ABS('Historical base'!$F$23)/($D$29+C37))-$D$29*C35)/C37 -> 65.699557 | D60: =((Valuation!$B$7-(D49+D50+D52+D53+D54))/(1-ABS('Historical base'!$F$23)/($D$29+D37))-$D$29*D35)/D37 -> 42.068136 | G60: Solves for the Cloud multiple with the shared-cost blend moving consistently. Which segment absorbs the premium depends on which one is held at its peer benchmark.
A61: Services EV/EBIT needed to reach market capitalisation (Cloud at peer multiple) | B61: =((Valuation!$B$7-(B49+B50+B52+B53+B54))/(1-ABS('Historical base'!$F$23)/($D$29+B37))-B37*B36)/$D$29 -> 24.083048 | C61: =((Valuation!$B$7-(C49+C50+C52+C53+C54))/(1-ABS('Historical base'!$F$23)/($D$29+C37))-C37*C36)/$D$29 -> 23.527442 | D61: =((Valuation!$B$7-(D49+D50+D52+D53+D54))/(1-ABS('Historical base'!$F$23)/($D$29+D37))-D37*D36)/$D$29 -> 21.780573 | G61: Alternative allocation of the market premium with Cloud held at its peer benchmark; compare with current row 35, not a fixed historical multiple.
A62: Peer multiples measure relative pricing rather than intrinsic value. The SOTP tests the DCF against current market benchmarks; segment attribution of any premium depends on which benchmark is held fixed.
A63: Primary sources: Meta September 2026 10-Q and FY2025 10-K; Microsoft FY2026 annual report; Oracle August 2026 10-Q and FY2026 10-K; Amazon Q2 2026 release. Dated market quotes and calculation inputs below.
A64: Microsoft finance leases 66,594 verified in the FY2026 annual report lease note: https://www.sec.gov/Archives/edgar/data/789019/000119312526427876/d62902dars.pdf
A67: October update: normalisation and source reconciliation
A68: Meta Q3 2026 10-Q | B68: https://www.sec.gov/Archives/edgar/data/1326801/000162828026066773/meta-20260930.htm
A69: Oracle Q1 FY2027 10-Q | B69: https://www.sec.gov/Archives/edgar/data/1341439/000119312526389274/orcl-20260831.htm
A70: Meta non-recurring settlement EBIT charge | B70: 9890 | C70: Q3 included in Family of Apps costs; remove once from recurring earnings.
A71: Meta normalised TTM group EBIT | B71: =C17+B70 -> 89270
A72: Meta normalised TTM Family of Apps EBIT | B72: =D30+B70 -> 108067
A73: Meta non-current debt | B73: 80922
A74: Meta current debt | B74: 2750
A75: Meta finance-lease claim proxy | B75: 11704 | C75: Finance-lease ROU assets used as liability proxy where separate liability total is unavailable; not a disclosed lease liability.
A76: Meta non-contingent settlement claim proxy | B76: 12775 | C76: 12,700 non-contingent payments +75 legal fees. Undiscounted nominal proxy; 5,300 conditional payments excluded. Higher than present value, conservatively raises EV.
A77: Meta prior nine-month revenue, 2024 | B77: 116116
A78: Meta prior TTM revenue | B78: =164501+141073-B77 -> 189458
A79: Meta prior-period source | B79: https://investor.atmeta.com/investor-news/press-release-details/2025/Meta-Reports-Third-Quarter-2025-Results/default.aspx
A80: Meta normalised group EV/EBIT | B80: =C14/B71 -> 18.377975
A81: Meta settlement normalisation | B81: GAAP peer multiple is shown in row 21; normalised Services benchmark is row 35. Settlement claim and cost add-back are paired; they do not change Alphabet's own forecast.

Sheet Simulation inputs
A1: Alphabet | Monte Carlo inputs, evidence and correlations
A2: Each driver draws one triangular scenario position z ∈ [−1, +1], mode 0, mapped to its full Bear/Base/Bull path. The bounded shape favours the central judgement without assuming historically estimated volatility. Financial inputs need not themselves be triangular. Scenario anchors have no assigned probabilities; results are conditional on the model, ranges and copula. Details and robustness below.
A4: Driver (path H2 2026 → 2031 unless stated) | B4: Bear | C4: Base | D4: Bull | E4: Evidence anchoring the range | F4: Basis
A5: Search growth | B5: 10% → 3% | C5: 17.9% → 8% | D5: 22% → 12% | E5: FY2025 +13.4%; H1 2026 +17.9%; Bear converges to nominal-GDP growth | F5: Evidence-anchored
A6: YouTube advertising growth | B6: 7% → 3% | C6: 11.8% → 8% | D6: 16% → 12% | E6: FY2025 +11.7%; H1 2026 +11.8% | F6: Evidence-anchored
A7: Network growth | B7: -8% → -5% | C7: -2.3% → -2% | D7: 0% → 2% | E7: FY2025 -1.9%; H1 2026 -2.3% | F7: Evidence-anchored
A8: Subscriptions, platforms and devices growth | B8: 8% → 4% | C8: 17.2% → 9% | D8: 20% → 13% | E8: FY2025 +19.1%; H1 2026 +17.2% | F8: Evidence-anchored
A9: Cloud demand growth | B9: 45% → 6% | C9: 73% → 12% | D9: 85% → 18% | E9: H1 2026 +73%; USD 513.9bn backlog; AWS +27.5%, Microsoft Intelligent Cloud +29.7%, OCI +77% (TTM) | F9: Evidence-anchored; 2030-31 tail is judgement
A10: Cloud operating margin | B10: 30% → 28% | C10: 34.4% → 38% | D10: 36% → 42% | E10: FY2025 23.7%, H1 2026 34.4%; AWS 36.8%, Microsoft Intelligent Cloud 41.3% | F10: Evidence-anchored (own history and peers)
A11: CapEx / planned revenue (2027 → 2031) | B11: 38% → 27% | C11: 35% → 22% | D11: 36% → 23% | E11: TTM 29.7%; peers' cash CapEx 35-83% of revenue. Both scenario rows are larger builds, so the distribution is skewed above Base | F11: Judgement anchored to peers
A12: Commissioning rate | B12: 0.4 | C12: 0.6 | D12: 0.8 | E12: Proxies: 2024 60.4%, 2025 65.9%, H1 2026 61.2% | F12: Wider than history: judgement
A13: New hardware life | B13: 4 years | C13: 5 years | D13: 6 years | E13: Alphabet depreciates servers over six years; accelerators may become obsolete sooner | F13: Policy-anchored judgement
A14: TAC partner pricing (change in TAC rate) | B14: +0.25 → +0.5pp | C14: 0 | D14: -0.25 → -0.5pp | E14: Search-distribution terms under antitrust remedies (U.S. Department of Justice, 2025) | F14: Judgement
A15: AI serving unit-cost improvement (annual) | B15: 0.08 | C15: 0.15 | D15: 0.25 | E15: Management reports falling Gemini serving costs; no cost per query disclosed | F15: Judgement
A16: AI workload growth per revenue dollar (annual) | B16: 0.2 | C16: 0.12 | D16: 0.15 | E16: Adoption of AI search features; not disclosed. Both alternatives exceed Base | F16: Judgement
A17: Shared research: elasticity (H2 2026 growth) | B17: 1.10 (20%) | C17: 0.80 (10%) | D17: 0.65 (5%) | E17: Alphabet-level costs rose 75% in H1 2026 (USD 11.2bn vs 6.4bn) | F17: Evidence-anchored
A18: Other Bets: revenue growth / cost growth | B18: 0% / 25% → 10% | C18: 10% / 15% → 5% | D18: 25% → 20% / 10% → 0% | E18: FY2025 revenue -6.7%, losses +69% | F18: Judgement
A19: Customer-funding stress on a 20% exposure: deferral / new-business cut | B19: 25% / 35% | C19: 5% / 10% | D19: 0% / 0% | E19: USD 20bn conditional commitment to a private company; Anthropic capacity from 2027 | F19: Judgement
A20: Terminal return ceiling (also capped at each scenario's starting return) | B20: ="WACC "&TEXT(Valuation!B29,"0.00%") -> WACC 9.38% | C20: 0.12 | D20: 0.16 | E20: The ceiling also cannot exceed the scenario's initial incremental return: Base starts at 20.1%, full Bear at 3.6%. Thus Bear terminal returns remain well below WACC. | F20: Theory-anchored judgement
A21: Terminal growth | B21: 0.02 | C21: 0.03 | D21: 0.035 | E21: ="Below the "&TEXT('Discount rate'!B8,"0.00%")&" Treasury yield" -> Below the 5.00% Treasury yield | F21: Theory-anchored
A23: Latent Gaussian correlations (copula) | B23: ρ | E23: Rationale | F23: Basis
A24: Search - YouTube | B24: 0.5 | E24: Common advertising cycle | F24: Judgement
A25: Search - Subscriptions | B25: 0.4 | E25: Shared consumer engagement | F25: Judgement
A26: YouTube - Subscriptions | B26: 0.4 | E26: YouTube Premium and TV sit in subscriptions | F26: Judgement
A27: Search - Network | B27: 0.3 | E27: Same advertiser budgets | F27: Judgement
A28: Cloud demand - Cloud margin | B28: 0.4 | E28: Operating leverage on fixed capacity | F28: Judgement
A29: Cloud demand - CapEx intensity | B29: 0.4 | E29: Capacity is built to demand | F29: Judgement
A30: Cloud demand - Commissioning | B30: 0.3 | E30: Strong demand pulls capacity into service | F30: Judgement
A31: Cloud demand - Customer-funding stress | B31: 0.3 | E31: AI customers' financing moves with AI demand | F31: Judgement
A32: Cloud margin - Terminal return | B32: 0.3 | E32: Durable pricing power | F32: Judgement
A33: Search - Terminal return | B33: 0.3 | E33: Persistence of the core moat | F33: Judgement
A35: Robustness (10,000 trials, operating EV, USD tn) | B35: P10 | C35: P50 | D35: P90 | E35: Trials at or above market-implied EV (3.75tn) | F35: Maximum trial
A36: As specified | B36: 1.6507302 | C36: 2.0406441 | D36: 2.4459123 | E36: 0 | F36: 3.2424546
A37: No correlations | B37: 1.711717 | C37: 2.0351452 | D37: 2.3687984 | E37: 0 | F37: 3.1092404
A38: Correlations x1.3 | B38: 1.6331133 | C38: 2.0404971 | D38: 2.4675712 | E38: 0 | F38: 3.246818
A39: WACC also uncertain, ±1pp triangular | B39: 1.6173908 | C39: 2.0348122 | D39: 2.5114942 | E39: 0 | F39: 3.5417599
A40: WACC also uncertain, ±2pp triangular | B40: 1.541015 | C40: 2.032213 | D40: 2.6840021 | E40: 14 | F40: 4.2472644
A41: 10,000 valid trials per run, seed 7. Fourteen ±2pp WACC trials exceed market EV (0.14% conditional frequency); none for ±1pp, uniform, independent or stronger-correlation runs. Reproduce with robustness.py.
A42: Sources: Historical base and Relative valuation tabs; Alphabet Inc. (2026a, 2026c); peer filings listed in Relative valuation. Python files: alphabet_model.py and monte_carlo.py.
A43: Uniform scenario positions | B43: 1.4343563 | C43: 1.9749863 | D43: 2.5632592 | E43: 0 | F43: 3.602499
A45: Deterministic scenario (USD bn) | B45: Operating EV | C45: Initial return | D45: Terminal return
A46: Bear | B46: 259.89784 | C46: 0.03584961 | D46: 0.03584961
A47: Base | B47: =Valuation!B48/1000 -> 2167.2683 | C47: 0.2009948 | D47: 0.12
A48: Bull | B48: 4024.8882 | C48: 0.25245469 | D48: 0.16
A49: 25 October 2026 valuation; 23 October market closes. WACC 9.3831%. Bear/Base/Bull tested against the live worksheet and matched Python. Full scenarios also change inventory; they are not Monte Carlo percentiles.
A51: Distribution choice and probability interpretation
A52: Triangular positions give greater weight near Base. Uniform positions test equal density across z, using the same seed, latent draws and copula. Normal inputs would require supported dispersion and allow unbounded tails; truncated normal requires dispersion plus bounds. Capping normal draws is not the same as truncating them.
A53: No 25/50/25 or other Bear/Base/Bull probabilities are imposed. Each driver's z has half its mass on either side of zero; this is not the probability of a whole scenario. Frequency = qualifying valid trials / all valid trials. P10/P50/P90 are output percentiles, not scenario labels or calibrated real-world probabilities.
A54: One position per driver applies throughout its forecast path, not new annual draws. Asymmetric paths are mapped piecewise: e.g., terminal growth 2%/3%/3.5% has 50% of positions on each side of Base, unlike a standard triangular distribution in growth units. CapEx and AI workload rise on both sides of Base; the numeric inputs are not symmetric. Copula coefficients are latent-normal correlations, not exact Pearson correlations of financial inputs.
A55: Shape test reproduced with robustness.py: uniform positions change the marginal shape only, using the same seed and latent copula draws. Outputs refreshed for the 25 October 2026 valuation.

Sheet Financial assets
A1: Alphabet | non-operating assets and valuation-date cash bridge
A2: USD millions. Disclosed carrying values are separated from tax-basis estimates and valuation adjustments. Blank tax bases remain unresolved.
A3: Selected operating case | B3: =Assumptions!B3 -> Base
A4: Valuation date | B4: =Assumptions!B4 -> 46320
A6: Investment / category | B6: Value / marked estimate | C6: Tax basis input | D6: Tax rate | E6: Value haircut | F6: Adjusted value | G6: Tax deduction | H6: Net credit | I6: Basis / limitation
A7: Marketable debt | B7: 99500 | C7: =B7 -> 99500 | D7: =Assumptions!$B$5 -> 0.21 | E7: 0 | F7: =B7*(1-E7) -> 99500 | G7: =IF(ISNUMBER(C7),MAX(F7-C7,0)*D7,"") -> 0 | H7: =IF(ISNUMBER(G7),F7-G7,"") -> 99500 | I7: Fair value from maturity/recurring-value tables. Tax basis is not the USD 116,454m from the differently scoped AOCI table.
A8: SpaceX — current | B8: =80000*$B$69 -> 69057.708 | C8: 0 | D8: =Assumptions!$B$5 -> 0.21 | E8: 0 | F8: =B8*(1-E8) -> 69057.708 | G8: =IF(ISNUMBER(C8),MAX(F8-C8,0)*D8,"") -> 14502.119 | H8: =IF(ISNUMBER(G8),F8-G8,"") -> 54555.589 | I8: Short-term sale restrictions; tax basis not separately disclosed. Fair-value mark is not the amount of taxable gain.
A9: Other current marketable equities | B9: 7063 | C9: =B9 -> 7063 | D9: =Assumptions!$B$5 -> 0.21 | E9: 0 | F9: =B9*(1-E9) -> 7063 | G9: =IF(ISNUMBER(C9),MAX(F9-C9,0)*D9,"") -> 0 | H9: =IF(ISNUMBER(G9),F9-G9,"") -> 7063 | I9: Residual of USD 87,063m current equities less USD 80,000m SpaceX. Portfolio aggregate, not individual holdings.
A10: SpaceX — non-current | B10: =14126*$B$69 -> 12193.865 | C10: 0 | D10: =Assumptions!$B$5 -> 0.21 | E10: 0 | F10: =B10*(1-E10) -> 12193.865 | G10: =IF(ISNUMBER(C10),MAX(F10-C10,0)*D10,"") -> 2560.7116 | H10: =IF(ISNUMBER(G10),F10-G10,"") -> 9633.1532 | I10: Reported non-current marketable equities include USD 14.1bn SpaceX restricted through Q3 2027. Other non-current assets, not non-marketable securities.
A11: Private equities — measurement alternative | B11: 124259 | C11: 47642 | D11: =Assumptions!$B$5 -> 0.21 | E11: =Assumptions!B202 -> 0.05 | F11: =B11*(1-E11) -> 118046.05 | G11: =IF(ISNUMBER(C11),MAX(F11-C11,0)*D11,"") -> 14784.851 | H11: =IF(ISNUMBER(G11),F11-G11,"") -> 103261.2 | I11: Initial accounting cost used only as a provisional tax-basis proxy. Subject to entity, jurisdiction and disposal structure.
A12: Equity-method investments and other | B12: 7202 | C12: =B12 -> 7202 | D12: =Assumptions!$B$5 -> 0.21 | E12: 0 | F12: =B12*(1-E12) -> 7202 | G12: =IF(ISNUMBER(C12),MAX(F12-C12,0)*D12,"") -> 0 | H12: =IF(ISNUMBER(G12),F12-G12,"") -> 7202 | I12: Separate portfolio category; carrying value and tax basis require review.
A14: Total investment credit | B14: =SUM(B7:B12) -> 319275.57 | F14: =SUM(F7:F12) -> 313062.62 | G14: =IF(COUNT(G7:G12)=6,SUM(G7:G12),"") -> 31847.681 | H14: =IF(COUNT(H7:H12)=6,SUM(H7:H12),"") -> 281214.94 | I14: Tax is assessed on adjusted disposal proceeds less tax basis; no automatic tax benefit for losses.
A16: Tax-basis sensitivity | B16: Net credit | C16: Interpretation
A17: All investments: no additional gains tax | B17: =SUM(F7:F12) -> 313062.62 | C17: Upper credit under the selected valuation haircuts; not a tax conclusion.
A18: All investments: zero tax basis | B18: =SUMPRODUCT(F7:F12,1-D7:D12) -> 247319.47 | C18: Lower credit under a 21% gain-tax stress; not a forecast and not a floor against investment losses.
A20: AOCI scope reconciliation | B20: Amount | C20: Interpretation
A21: Adjusted cost excluding time deposits | B21: =120243-3789 -> 116454 | C21: Different scope from current marketable debt: includes eligible cash equivalents; fair-value-option holdings differ.
A22: Fair value excluding time deposits | B22: =120098-3789 -> 116309 | C22: Compare only with row 21; not with current marketable debt of 99,500.
A23: Matched-scope accounting loss | B23: =B22-B21 -> -145 | C23: Does not establish tax basis or taxable gains for the separately classified current portfolio.
A26: June-to-25 October cash bridge | B26: Amount | C26: Basis / assumption
A27: June cash and cash equivalents | B27: ='Balance sheet'!I8 -> 55911 | C27: Reported balance; includes debt instruments classified as cash equivalents.
A28: Known July Android settlement | B28: =-'Sources and basis'!C87 -> -5200 | C28: Cash payment reduces both cash and accrued legal claims.
A29: Modelled elapsed H2 FCFF | B29: =Valuation!B37-Valuation!B38 -> -17815.262 | C29: Full H2 model FCFF less the remaining 25 October–December stub; estimated accrual of operating cash flows, not reported October cash.
A30: Required operating cash / TTM revenue | B30: 0.02 | C30: Provisional 2% liquidity reserve; analyst assumption to sensitivity-test, not company guidance.
A31: Required operating cash | B31: =B30*'Historical base'!F16 -> 8917.32 | C31: Reserve calculated on TTM sales; excluded from credited excess cash.
A32: Known-event excess cash subtotal | B32: =MAX(B27+B28-B31,0) -> 41793.68 | C32: June cash adjusted only for the known July settlement and operating reserve; incomplete-date sensitivity.
A33: Valuation-date excess cash | B33: =MAX(B27+B28+B29+B70-B71-B72+B73-B31,0) -> 26051.53 | C33: June cash + known settlement + modelled elapsed FCFF + Waymo loan − preferred dividend − estimated common dividend. Unknown financing/repurchases remain a proxy; not a reported October balance.
A35: June accrued legal claims | B35: ='Sources and basis'!C85 -> 17356 | C35: Carrying-value proxy; settlement timing, appeals and tax effects remain judgemental.
A36: July claim extinguished | B36: ='Sources and basis'!C87 -> 5200 | C36: Same payment as row 28, with opposite bridge sign.
A37: Unpaid legal claim proxy | B37: =B35-B36 -> 12156 | C37: Feeds financing/minority/settlement claims; excluded from recurring NOWC.
A39: Known-event asset-credit sensitivity | B39: Amount | C39: Basis
A40: No gains tax | B40: =B32+B17 -> 354856.3 | C40: Known-event cash plus investment credit; excludes modelled elapsed cash and October financing.
A41: Zero tax basis stress | B41: =B32+B18 -> 289113.15 | C41: Same investment haircuts; zero tax basis stress, not a full October bridge.
A44: Additional non-operating assets | B44: Value input | C44: Basis
A45: Capped-call hedge value | C45: Premium paid is not current fair value. Separate claim offset only when valued; no automatic credit.
A46: GFiber disposal interest / other assets | C46: Only add if corresponding operations are removed from the DCF; otherwise a second credit would duplicate value.
A49: Source | B49: https://www.sec.gov/Archives/edgar/data/1652044/000165204426000071/goog-20260630.htm
A50: Valuation haircuts currently default to zero as a neutral starting point, not a conclusion that restrictions are costless. Tax-basis stresses keep unresolved information visible.
A51: Deferred tax is not also deducted as a blanket financing claim. Investment-level adjustments must still be reconciled with relevant tax liabilities and settlement timing.
A54: Conditional customer / investee financing
A55: Disclosed contingent funding through 2030 | B55: ='Sources and basis'!B102 -> 20000 | C55: The filing does not name the private counterparty. Do not assert an Anthropic allocation.
A56: Scenario probability of funding | B56: =Assumptions!B229 -> 0.5 | C56: Milestone-dependent draw stress, not a company probability.
A57: Scenario cash funding exposure | B57: =B55*B56 -> 10000 | C57: Gross funding obtains investment rights. Net valuation impact awaits reconciliation with existing derivatives and acquired interests.
A58: Annual funding | B58: 2027 | C58: 2028 | D58: 2029 | E58: 2030
A59: Illustrative cash outlay | B59: =$B$57/4 -> 2500 | C59: =$B$57/4 -> 2500 | D59: =$B$57/4 -> 2500 | E59: =$B$57/4 -> 2500 | F59: Even timing assumption, not a contractual maturity schedule.
A61: Portfolio haircut and Cloud funding pressures use the same scenario selector. They affect distinct assets/cash flows; neither proves circular revenue or fraud.
A62: No blanket subtraction of funding is added to operating FCFF. The bridge uses proxy tax bases and book-value NCI; contingent funding rights receive no separate credit (disclosed approximations).
A65: 25 October refresh: market marks and cash movements
A66: SpaceX June 30 close (USD) | B66: 170.86 | C66: https://finance.yahoo.com/quote/SPCX/history/
A67: SpaceX October 23 close (USD) | B67: 147.49 | C67: https://www.google.com/finance/quote/SPCX:NASDAQ
A68: Holding assumption | B68: Unchanged share quantities | C68: June current/non-current classification retained; restricted shares still carry sale restrictions. Market mark assumes no intervening trades.
A69: SpaceX mark / June mark | B69: =B67/B66 -> 0.86322135 | C69: Applied to June disclosed current and non-current holdings; tax bases unchanged.
A70: Waymo October term loan proceeds | B70: 5000 | C70: Closed 8 October; add cash and debt equally. https://blog.waymo.com/blog/2026/10/waymo-closes-5-billion-debt-financing/
A71: August preferred dividend | B71: ='Discount rate'!B33/20*12.15 -> 233.8875 | C71: 385m depositary shares /20 × USD12.15 preferred-share first dividend, paid August 15; Q2 Note 11.
A72: September common dividend estimate | B72: 2693 | C72: USD0.22/share declared for September 14. June quarterly cash amount used as proxy because later actual total is not yet reported; Q2 Note 11/equity statement.
A73: Other post-June financing / repurchases | B73: 0 | C73: Unobserved net movements held at zero, not asserted to be absent. Refresh with Q3 filing; settlement, dividends and Waymo financing treated separately.

Sheet Historical base
A1: Alphabet | historical baseline
A2: USD millions. Financial statements retain their reported basis; derived periods are calculated here.
A3: Selected case | B3: =Assumptions!B3 -> Base
A6: Operating history | B6: FY2024 | C6: FY2025 | D6: H1 2025 | E6: H1 2026 | F6: TTM Jun26
A8: Search & other | B8: ='Revenue breakdown'!C8 -> 198084 | C8: ='Revenue breakdown'!G8 -> 224532 | D8: =SUM('Revenue breakdown'!D8:E8) -> 104892 | E8: =SUM('Revenue breakdown'!H8:I8) -> 123670 | F8: =C8-D8+E8 -> 243310
A9: YouTube advertising | B9: ='Revenue breakdown'!C9 -> 36147 | C9: ='Revenue breakdown'!G9 -> 40367 | D9: =SUM('Revenue breakdown'!D9:E9) -> 18723 | E9: =SUM('Revenue breakdown'!H9:I9) -> 20938 | F9: =C9-D9+E9 -> 42582
A10: Google Network | B10: ='Revenue breakdown'!C10 -> 30359 | C10: ='Revenue breakdown'!G10 -> 29792 | D10: =SUM('Revenue breakdown'!D10:E10) -> 14610 | E10: =SUM('Revenue breakdown'!H10:I10) -> 14274 | F10: =C10-D10+E10 -> 29456
A11: Subscriptions / platforms / devices | B11: ='Revenue breakdown'!C12 -> 40340 | C11: ='Revenue breakdown'!G12 -> 48030 | D11: =SUM('Revenue breakdown'!D12:E12) -> 21582 | E11: =SUM('Revenue breakdown'!H12:I12) -> 25295 | F11: =C11-D11+E11 -> 51743
A12: Google Services | B12: ='Revenue breakdown'!C13 -> 304930 | C12: ='Revenue breakdown'!G13 -> 342721 | D12: =SUM('Revenue breakdown'!D13:E13) -> 159807 | E12: =SUM('Revenue breakdown'!H13:I13) -> 184177 | F12: =C12-D12+E12 -> 367091
A13: Google Cloud | B13: ='Revenue breakdown'!C16 -> 43229 | C13: ='Revenue breakdown'!G16 -> 58705 | D13: =SUM('Revenue breakdown'!D16:E16) -> 25884 | E13: =SUM('Revenue breakdown'!H16:I16) -> 44796 | F13: =C13-D13+E13 -> 77617
A14: Other Bets | B14: ='Revenue breakdown'!C17 -> 1648 | C14: ='Revenue breakdown'!G17 -> 1537 | D14: =SUM('Revenue breakdown'!D17:E17) -> 823 | E14: =SUM('Revenue breakdown'!H17:I17) -> 793 | F14: =C14-D14+E14 -> 1507
A15: Hedging gains / losses | B15: ='Revenue breakdown'!C18 -> 211 | C15: ='Revenue breakdown'!G18 -> -127 | D15: =SUM('Revenue breakdown'!D18:E18) -> 148 | E15: =SUM('Revenue breakdown'!H18:I18) -> -74 | F15: =C15-D15+E15 -> -349
A16: Consolidated revenue | B16: ='Income statement'!C8 -> 350018 | C16: ='Income statement'!G8 -> 402836 | D16: =SUM('Income statement'!D8:E8) -> 186662 | E16: =SUM('Income statement'!H8:I8) -> 229692 | F16: =C16-D16+E16 -> 445866
A17: Revenue segment reconciliation | B17: =SUM(B12:B15)-B16 -> 0 | C17: =SUM(C12:C15)-C16 -> 0 | D17: =SUM(D12:D15)-D16 -> 0 | E17: =SUM(E12:E15)-E16 -> 0 | F17: =SUM(F12:F15)-F16 -> 0
A19: Operating profitability
A20: Services operating profit | B20: ='Segment breakdown'!C15 -> 121263 | C20: ='Segment breakdown'!G15 -> 139404 | D20: =SUM('Segment breakdown'!D15:E15) -> 65745 | E20: =SUM('Segment breakdown'!H15:I15) -> 80133 | F20: =C20-D20+E20 -> 153792
A21: Cloud operating profit | B21: ='Segment breakdown'!C16 -> 6112 | C21: ='Segment breakdown'!G16 -> 13910 | D21: =SUM('Segment breakdown'!D16:E16) -> 5003 | E21: =SUM('Segment breakdown'!H16:I16) -> 15412 | F21: =C21-D21+E21 -> 24319
A22: Other Bets operating profit / loss | B22: ='Segment breakdown'!C17 -> -4444 | C22: ='Segment breakdown'!G17 -> -7515 | D22: =SUM('Segment breakdown'!D17:E17) -> -2472 | E22: =SUM('Segment breakdown'!H17:I17) -> -3899 | F22: =C22-D22+E22 -> -8942
A23: Alphabet-level operating loss | B23: ='Segment breakdown'!C18 -> -10541 | C23: ='Segment breakdown'!G18 -> -16760 | D23: =SUM('Segment breakdown'!D18:E18) -> -6399 | E23: =SUM('Segment breakdown'!H18:I18) -> -11180 | F23: =C23-D23+E23 -> -21541
A24: Consolidated EBIT | B24: ='Income statement'!C16 -> 112390 | C24: ='Income statement'!G16 -> 129039 | D24: =SUM('Income statement'!D16:E16) -> 61877 | E24: =SUM('Income statement'!H16:I16) -> 80466 | F24: =C24-D24+E24 -> 147628
A25: EBIT segment reconciliation | B25: =SUM(B20:B23)-B24 -> 0 | C25: =SUM(C20:C23)-C24 -> 0 | D25: =SUM(D20:D23)-D24 -> 0 | E25: =SUM(E20:E23)-E24 -> 0 | F25: =SUM(F20:F23)-F24 -> 0
A26: Services operating margin | B26: =B20/B12 -> 0.39767488 | C26: =C20/C12 -> 0.40675652 | D26: =D20/D12 -> 0.4114025 | E26: =E20/E12 -> 0.4350869 | F26: =F20/F12 -> 0.41894789
A27: Cloud operating margin | B27: =B21/B13 -> 0.14138657 | C27: =C21/C13 -> 0.23694745 | D27: =D21/D13 -> 0.19328543 | E27: =E21/E13 -> 0.34404858 | F27: =F21/F13 -> 0.31332054
A28: Consolidated margin | B28: =B24/B16 -> 0.32109777 | C28: =C24/C16 -> 0.32032639 | D28: =D24/D16 -> 0.33149222 | E28: =E24/E16 -> 0.3503213 | F28: =F24/F16 -> 0.33110396
A29: Cloud revenue share | B29: =B13/B16 -> 0.12350508 | C29: =C13/C16 -> 0.14572928 | D29: =D13/D16 -> 0.13866775 | E29: =E13/E16 -> 0.19502638 | F29: =F13/F16 -> 0.17408145
A30: NOPAT (21% benchmark) | B30: =B24*(1-Assumptions!$B$5) -> 88788.1 | C30: =C24*(1-Assumptions!$B$5) -> 101940.81 | D30: =D24*(1-Assumptions!$B$5) -> 48882.83 | E30: =E24*(1-Assumptions!$B$5) -> 63568.14 | F30: =F24*(1-Assumptions!$B$5) -> 116626.12
A33: Reported cash generation
A34: Operating cash flow | B34: =1*SUM('Cash flow'!C22) -> 125299 | C34: =1*SUM('Cash flow'!G22) -> 164713 | D34: =1*SUM('Cash flow'!E22) -> 63897 | E34: =1*SUM('Cash flow'!I22) -> 84859 | F34: =C34-D34+E34 -> 185675
A35: Cash CapEx | B35: =-1*SUM('Cash flow'!C25) -> 52535 | C35: =-1*SUM('Cash flow'!G25) -> 91447 | D35: =-1*SUM('Cash flow'!E25) -> 39643 | E35: =-1*SUM('Cash flow'!I25) -> 80598 | F35: =C35-D35+E35 -> 132402
A36: Reported FCF | B36: =B34-B35 -> 72764 | C36: =C34-C35 -> 73266 | D36: =D34-D35 -> 24254 | E36: =E34-E35 -> 4261 | F36: =F34-F35 -> 53273
A37: SBC | B37: =1*SUM('Cash flow'!C10) -> 22785 | C37: =1*SUM('Cash flow'!G10) -> 24953 | D37: =1*SUM('Cash flow'!E10) -> 11514 | E37: =1*SUM('Cash flow'!I10) -> 14708 | F37: =C37-D37+E37 -> 28147
A38: FCF less SBC | B38: =B36-B37 -> 49979 | C38: =C36-C37 -> 48313 | D38: =D36-D37 -> 12740 | E38: =E36-E37 -> -10447 | F38: =F36-F37 -> 25126
A39: PP&E depreciation | B39: =1*SUM('Cash flow'!C9) -> 15311 | C39: =1*SUM('Cash flow'!G9) -> 21136 | D39: =1*SUM('Cash flow'!E9) -> 9485 | E39: =1*SUM('Cash flow'!I9) -> 13586 | F39: =C39-D39+E39 -> 25237
A40: Cash CapEx / revenue | B40: =B35/B16 -> 0.15009228 | C40: =C35/C16 -> 0.22700801 | D40: =D35/D16 -> 0.21237852 | E40: =E35/E16 -> 0.35089598 | F40: =F35/F16 -> 0.29695469
A41: Net income | B41: =1*SUM('Cash flow'!C8) -> 100118 | C41: =1*SUM('Cash flow'!G8) -> 132170 | D41: =1*SUM('Cash flow'!E8) -> 62736 | E41: =1*SUM('Cash flow'!I8) -> 174771 | F41: =C41-D41+E41 -> 244205
A42: Deferred tax adjustment | B42: =1*SUM('Cash flow'!C11) -> -5257 | C42: =1*SUM('Cash flow'!G11) -> 8348 | D42: =1*SUM('Cash flow'!E11) -> -1596 | E42: =1*SUM('Cash flow'!I11) -> 27538 | F42: =C42-D42+E42 -> 37482
A43: Investment gain / loss reversal | B43: =1*SUM('Cash flow'!C12) -> -2671 | C43: =1*SUM('Cash flow'!G12) -> -24620 | D43: =1*SUM('Cash flow'!E12) -> -11411 | E43: =1*SUM('Cash flow'!I12) -> -135803 | F43: =C43-D43+E43 -> -149012
A44: Other non-cash adjustment (unclassified) | B44: =1*SUM('Cash flow'!C13) -> 3419 | C44: =1*SUM('Cash flow'!G13) -> 2108 | D44: =1*SUM('Cash flow'!E13) -> 1041 | E44: =1*SUM('Cash flow'!I13) -> 3161 | F44: =C44-D44+E44 -> 4228
A46: Receivable cash movement | B46: =1*SUM('Cash flow'!C14) -> -5891 | C46: =1*SUM('Cash flow'!G14) -> -8779 | D46: =1*SUM('Cash flow'!E14) -> -1201 | E46: =1*SUM('Cash flow'!I14) -> -6904 | F46: =C46-D46+E46 -> -14482
A47: Inventory cash movement | B47: =1*SUM('Cash flow'!C15) -> 0 | C47: =1*SUM('Cash flow'!G15) -> 0 | D47: =1*SUM('Cash flow'!E15) -> 0 | E47: =1*SUM('Cash flow'!I15) -> -7739 | F47: =C47-D47+E47 -> -7739
A48: Other asset cash movement | B48: =1*SUM('Cash flow'!C17) -> -1397 | C48: =1*SUM('Cash flow'!G17) -> -4542 | D48: =1*SUM('Cash flow'!E17) -> -2767 | E48: =1*SUM('Cash flow'!I17) -> -9950 | F48: =C48-D48+E48 -> -11725
A49: Payable cash movement | B49: =1*SUM('Cash flow'!C18) -> 359 | C49: =1*SUM('Cash flow'!G18) -> 907 | D49: =1*SUM('Cash flow'!E18) -> -327 | E49: =1*SUM('Cash flow'!I18) -> 2090 | F49: =C49-D49+E49 -> 3324
A50: Accrued liability cash movement | B50: =1*SUM('Cash flow'!C19) -> -1161 | C50: =1*SUM('Cash flow'!G19) -> 12939 | D50: =1*SUM('Cash flow'!E19) -> -1560 | E50: =1*SUM('Cash flow'!I19) -> 308 | F50: =C50-D50+E50 -> 14807
A51: Revenue-share cash movement | B51: =1*SUM('Cash flow'!C20) -> 1059 | C51: =1*SUM('Cash flow'!G20) -> 899 | D51: =1*SUM('Cash flow'!E20) -> -219 | E51: =1*SUM('Cash flow'!I20) -> 0 | F51: =C51-D51+E51 -> 1118
A52: Deferred-revenue cash movement | B52: =1*SUM('Cash flow'!C21) -> 1043 | C52: =1*SUM('Cash flow'!G21) -> 2420 | D52: =1*SUM('Cash flow'!E21) -> 636 | E52: =1*SUM('Cash flow'!I21) -> 789 | F52: =C52-D52+E52 -> 2573
A53: Cash movement proxy, excluding tax | B53: =SUM(B46:B52) -> -5988 | C53: =SUM(C46:C52) -> 3844 | D53: =SUM(D46:D52) -> -5438 | E53: =SUM(E46:E52) -> -21406 | F53: =SUM(F46:F52) -> -12124
A54: Income-tax cash movement | B54: =1*SUM('Cash flow'!C16) -> -2418 | C54: =1*SUM('Cash flow'!G16) -> -3226 | D54: =1*SUM('Cash flow'!E16) -> -2434 | E54: =1*SUM('Cash flow'!I16) -> 8304 | F54: =C54-D54+E54 -> 7512
A55: Reconstructed operating cash flow | B55: =SUM(B41:B44)+B39+B37+B53+B54 -> 125299 | C55: =SUM(C41:C44)+C39+C37+C53+C54 -> 164713 | D55: =SUM(D41:D44)+D39+D37+D53+D54 -> 63897 | E55: =SUM(E41:E44)+E39+E37+E53+E54 -> 84859 | F55: =SUM(F41:F44)+F39+F37+F53+F54 -> 185675
A56: Reported OCF reconciliation | B56: =B55-B34 -> 0 | C56: =C55-C34 -> 0 | D56: =D55-D34 -> 0 | E56: =E55-E34 -> 0 | F56: =F55-F34 -> 0
A58: FCFF proxy before classification review | B58: =B30+B39+B44+B53-B35 -> 48995.1 | C58: =C30+C39+C44+C53-C35 -> 37581.81 | D58: =D30+D39+D44+D53-D35 -> 14327.83 | E58: =E30+E39+E44+E53-E35 -> -21688.86 | F58: =F30+F39+F44+F53-F35 -> 1565.12
A59: Bridge from reported FCF to proxy | B59: =B36+B30-B41-B37-B42-B43-B54 -> 48995.1 | C59: =C36+C30-C41-C37-C42-C43-C54 -> 37581.81 | D59: =D36+D30-D41-D37-D42-D43-D54 -> 14327.83 | E59: =E36+E30-E41-E37-E42-E43-E54 -> -21688.86 | F59: =F36+F30-F41-F37-F42-F43-F54 -> 1565.12
A60: FCFF proxy bridge difference | B60: =B58-B59 -> 0 | C60: =C58-C59 -> 0 | D60: =D58-D59 -> 0 | E60: =E58-E59 -> 0 | F60: =F58-F59 -> 0
A62: FCFF proxy is not a final adjusted FCFF: Other and other asset/liability movements require operating/non-operating classification.
A63: SBC remains an expense. Do not add it back to forecast NOPAT. No balance-sheet capital change is substituted for cash CapEx.
A66: Capital employed | B66: Dec 2024 | C66: Jun 2025 | D66: Dec 2025 | E66: Jun 2026
A67: Non-cash current assets | B67: ='Balance sheet'!C14-'Balance sheet'!C10 -> 68054 | C67: ='Balance sheet'!E14-'Balance sheet'!E10 -> 71068 | D67: ='Balance sheet'!G14-'Balance sheet'!G10 -> 79195 | E67: ='Balance sheet'!I14-'Balance sheet'!I10 -> 101050
A68: Current liabilities | B68: ='Balance sheet'!C32 -> 89122 | C68: ='Balance sheet'!E32 -> 87310 | D68: ='Balance sheet'!G32 -> 102745 | E68: ='Balance sheet'!I32 -> 126111
A69: Financing/tax/lease/CapEx exclusions | B69: =SUM('Sources and basis'!B36:B42) -> 23518 | C69: =SUM('Sources and basis'!C36:C42) -> 21623 | D69: =SUM('Sources and basis'!D36:D42) -> 22209 | E69: =SUM('Sources and basis'!E36:E42) -> 41062
A70: Adjusted operating current liabilities | B70: =B68-B69 -> 65604 | C70: =C68-C69 -> 65687 | D70: =D68-D69 -> 80536 | E70: =E68-E69 -> 85049
A71: Operating working-capital proxy | B71: =B67-B70 -> 2450 | C71: =C67-C70 -> 5381 | D71: =D67-D70 -> -1341 | E71: =E67-E70 -> 16001
A72: Net PP&E | B72: ='Balance sheet'!C19 -> 171036 | C72: ='Balance sheet'!E19 -> 203231 | D72: ='Balance sheet'!G19 -> 246597 | E72: ='Balance sheet'!I19 -> 321212
A73: Tangible operating capital | B73: =B71+B72 -> 173486 | C73: =C71+C72 -> 208612 | D73: =D71+D72 -> 245256 | E73: =E71+E72 -> 337213
A74: Assets not in service | B74: ='Sources and basis'!B43 -> 50597 | C74: ='Sources and basis'!C43 -> 61700 | D74: ='Sources and basis'!D43 -> 78592 | E74: ='Sources and basis'!E43 -> 122814
A75: Net PP&E in service | B75: =B72-B74 -> 120439 | C75: =C72-C74 -> 141531 | D75: =D72-D74 -> 168005 | E75: =E72-E74 -> 198398
A76: Not-in-service share | B76: =B74/B72 -> 0.29582661 | C76: =C74/C72 -> 0.30359542 | D76: =D74/D72 -> 0.31870623 | E76: =E74/E72 -> 0.38234562
A79: Return on tangible capital | B79: FY2025 | C79: TTM Jun26 | D79: FY2025, forecast basis | E79: TTM Jun26, forecast basis | F79: Legal accrual and held-for-sale inputs | G79: USD m
A80: NOPAT | B80: =C30 -> 101940.81 | C80: =F30 -> 116626.12 | D80: =B80 -> 101940.81 | E80: =C80 -> 116626.12 | F80: Accrued fines and settlements, Dec 2024 (FY2025 10-K recast) | G80: 9830
A81: Opening capital | B81: =B73 -> 173486 | C81: =C73 -> 208612 | D81: =B81+G80+B118 -> 190316.36 | E81: =C81+G81+C118 -> 224538.98 | F81: EC fines plus privacy settlement, Jun 2025 (Q2 2025 10-Q; lower bound) | G81: 8499
A82: Closing capital | B82: =D73 -> 245256 | C82: =E73 -> 337213 | D82: =B82+G82+D118 -> 268906.72 | E82: =C82+G83-G84+E118 -> 356386.32 | F82: Accrued fines and settlements, Dec 2025 | G82: ='Working capital'!B25 -> 15594
A83: Average capital | B83: =AVERAGE(B81:B82) -> 209371 | C83: =AVERAGE(C81:C82) -> 272912.5 | D83: =AVERAGE(D81:D82) -> 229611.54 | E83: =AVERAGE(E81:E82) -> 290462.65 | F83: Accrued fines and settlements, Jun 2026 | G83: ='Working capital'!C25 -> 17356
A84: After-tax tangible return | B84: =B80/B83 -> 0.48689078 | C84: =C80/C83 -> 0.42733887 | D84: =D80/D83 -> 0.44397076 | E84: =E80/E83 -> 0.40151847 | F84: GFiber held-for-sale PP&E, Jun 2026 | G84: ='Working capital'!C11 -> 7100
A86: Published proxy remains in B:C. Forecast-basis D:E excludes legal accruals and held-for-sale PP&E and includes the required cash reserve; changes in balance-sheet capital are not cash reinvestment.
A89: Report reconciliation | B89: FY2025 difference | C89: TTM difference
A90: Revenue | B90: =C16-'Sources and basis'!B75 -> 0 | C90: =F16-'Sources and basis'!C75 -> 0
A91: Operating profit | B91: =C24-'Sources and basis'!B76 -> 0 | C91: =F24-'Sources and basis'!C76 -> 0
A92: NOPAT | B92: =C30-'Sources and basis'!B77 -> 0 | C92: =F30-'Sources and basis'!C77 -> 0
A93: Average capital | B93: =B83-'Sources and basis'!B78 -> 0 | C93: =C83-'Sources and basis'!C78 -> 0
A94: Reported FCF | B94: =C36-'Sources and basis'!B79 -> 0 | C94: =F36-'Sources and basis'!C79 -> 0
A95: FCF less SBC | B95: =C38-'Sources and basis'!B80 -> 0 | C95: =F38-'Sources and basis'!C80 -> 0
A98: Five-year trajectory | B98: FY2021 | C98: FY2022 | D98: FY2023 | E98: FY2024 | F98: FY2025 | G98: Four-year CAGR
A99: Revenue | B99: ='Sources and basis'!B61 -> 257637 | C99: ='Sources and basis'!C61 -> 282836 | D99: ='Sources and basis'!D61 -> 307394 | E99: ='Sources and basis'!E61 -> 350018 | F99: ='Sources and basis'!F61 -> 402836 | G99: =(F99/B99)^(1/4)-1 -> 0.11822709
A100: Operating income | B100: ='Sources and basis'!B62 -> 78714 | C100: ='Sources and basis'!C62 -> 74842 | D100: ='Sources and basis'!D62 -> 84293 | E100: ='Sources and basis'!E62 -> 112390 | F100: ='Sources and basis'!F62 -> 129039 | G100: =(F100/B100)^(1/4)-1 -> 0.13153307
A101: Services revenue | B101: ='Sources and basis'!B63 -> 237529 | C101: ='Sources and basis'!C63 -> 253528 | D101: ='Sources and basis'!D63 -> 272543 | E101: ='Sources and basis'!E63 -> 304930 | F101: ='Sources and basis'!F63 -> 342721 | G101: =(F101/B101)^(1/4)-1 -> 0.095988555
A102: Services EBIT | B102: ='Sources and basis'!B64 -> 88132 | C102: ='Sources and basis'!C64 -> 82699 | D102: ='Sources and basis'!D64 -> 95858 | E102: ='Sources and basis'!E64 -> 121263 | F102: ='Sources and basis'!F64 -> 139404 | G102: =(F102/B102)^(1/4)-1 -> 0.12146417
A103: Cloud revenue | B103: ='Sources and basis'!B65 -> 19206 | C103: ='Sources and basis'!C65 -> 26280 | D103: ='Sources and basis'!D65 -> 33088 | E103: ='Sources and basis'!E65 -> 43229 | F103: ='Sources and basis'!F65 -> 58705 | G103: =(F103/B103)^(1/4)-1 -> 0.32223772
A104: Cloud EBIT | B104: ='Sources and basis'!B66 -> -2282 | C104: ='Sources and basis'!C66 -> -1922 | D104: ='Sources and basis'!D66 -> 1716 | E104: ='Sources and basis'!E66 -> 6112 | F104: ='Sources and basis'!F66 -> 13910
A105: Net PP&E | B105: ='Sources and basis'!B67 -> 97599 | C105: ='Sources and basis'!C67 -> 112668 | D105: ='Sources and basis'!D67 -> 134345 | E105: ='Sources and basis'!E67 -> 171036 | F105: ='Sources and basis'!F67 -> 246597 | G105: =(F105/B105)^(1/4)-1 -> 0.26076924
A106: Operating cash flow | B106: ='Sources and basis'!B68 -> 91652 | C106: ='Sources and basis'!C68 -> 91495 | D106: ='Sources and basis'!D68 -> 101746 | E106: ='Sources and basis'!E68 -> 125299 | F106: ='Sources and basis'!F68 -> 164713 | G106: =(F106/B106)^(1/4)-1 -> 0.15783449
A107: Cash CapEx | B107: ='Sources and basis'!B69 -> 24640 | C107: ='Sources and basis'!C69 -> 31485 | D107: ='Sources and basis'!D69 -> 32251 | E107: ='Sources and basis'!E69 -> 52535 | F107: ='Sources and basis'!F69 -> 91447 | G107: =(F107/B107)^(1/4)-1 -> 0.38797675
A108: SBC | B108: ='Sources and basis'!B70 -> 15376 | C108: ='Sources and basis'!C70 -> 19362 | D108: ='Sources and basis'!D70 -> 22460 | E108: ='Sources and basis'!E70 -> 22785 | F108: ='Sources and basis'!F70 -> 24953 | G108: =(F108/B108)^(1/4)-1 -> 0.12867745
A109: PP&E depreciation | B109: ='Sources and basis'!B71 -> 10273 | C109: ='Sources and basis'!C71 -> 13475 | D109: ='Sources and basis'!D71 -> 11946 | E109: ='Sources and basis'!E71 -> 15311 | F109: ='Sources and basis'!F71 -> 21136 | G109: =(F109/B109)^(1/4)-1 -> 0.19765402
A112: Reported FCF | B112: =B106-B107 -> 67012 | C112: =C106-C107 -> 60010 | D112: =D106-D107 -> 69495 | E112: =E106-E107 -> 72764 | F112: =F106-F107 -> 73266 | G112: =(F112/B112)^(1/4)-1 -> 0.022556881
A113: FCF less SBC | B113: =B112-B108 -> 51636 | C113: =C112-C108 -> 40648 | D113: =D112-D108 -> 47035 | E113: =E112-E108 -> 49979 | F113: =F112-F108 -> 48313 | G113: =(F113/B113)^(1/4)-1 -> -0.016492098
A116: Required operating cash (USD m) | B116: Dec 2024 | C116: Jun 2025 | D116: Dec 2025 | E116: Jun 2026
A117: Annual / TTM revenue | B117: =B16 -> 350018 | C117: =B16+D16-B120 -> 371399 | D117: =C16 -> 402836 | E117: =F16 -> 445866
A118: Required cash at bridge reserve ratio | B118: =B117*'Financial assets'!$B$30 -> 7000.36 | C118: =C117*'Financial assets'!$B$30 -> 7427.98 | D118: =D117*'Financial assets'!$B$30 -> 8056.72 | E118: =E117*'Financial assets'!$B$30 -> 8917.32
A120: H1 2024 revenue (source input) | B120: 165281
A124: Historical FCFF classification (USD m) | B124: FY2025 | C124: TTM Jun26
A125: NOPAT at common 21% tax benchmark | B125: =C30 -> 101940.81 | C125: =F30 -> 116626.12
A126: PP&E depreciation | B126: =C39 -> 21136 | C126: =F39 -> 25237
...

Sheet Income statement
A1: Income statement
A2: USD millions except earnings per share. Q4 filing columns contain full-year 10-K totals.
A4: Reported line item | B4: Q3:24 | C4: Q4:24 | D4: Q1:25 | E4: Q2:25 | F4: Q3:25 | G4: Q4:25 | H4: Q1:26 | I4: Q2:26
A5: Reporting basis | B5: 3 months | C5: full year | D5: 3 months | E5: 3 months | F5: 3 months | G5: full year | H5: 3 months | I5: 3 months
A7: Revenue
A8: Revenues | B8: 88268 | C8: 350018 | D8: 90234 | E8: 96428 | F8: 102346 | G8: 402836 | H8: 109896 | I8: 119796
A10: Operating expenses and profit
A11: Cost of revenues | B11: 36474 | C11: 146306 | D11: 36361 | E11: 39039 | F11: 41369 | G11: 162535 | H11: 41271 | I11: 45943
A12: Research and development | B12: 12447 | C12: 49326 | D12: 13556 | E12: 13808 | F12: 15151 | G12: 61087 | H12: 17032 | I12: 18219
A13: Sales and marketing | B13: 7227 | C13: 27808 | D13: 6172 | E13: 7101 | F13: 7205 | G13: 28693 | H13: 7606 | I13: 8403
A14: General and administrative | B14: 3599 | C14: 14188 | D14: 3539 | E14: 5209 | F14: 7393 | G14: 21482 | H14: 4291 | I14: 6461
A15: Total costs and expenses | B15: 59747 | C15: 237628 | D15: 59628 | E15: 65157 | F15: 71118 | G15: 273797 | H15: 70200 | I15: 79026
A16: Income from operations | B16: 28521 | C16: 112390 | D16: 30606 | E16: 31271 | F16: 31228 | G16: 129039 | H16: 39696 | I16: 40770
A18: Other income and tax
A19: Other income (expense), net | B19: 3185 | C19: 7425 | D19: 11183 | E19: 2662 | F19: 12759 | G19: 29787 | H19: 37716 | I19: 97983
A20: Income before income taxes | B20: 31706 | C20: 119815 | D20: 41789 | E20: 33933 | F20: 43987 | G20: 158826 | H20: 77412 | I20: 138753
A21: Provision for income taxes | B21: 5405 | C21: 19697 | D21: 7249 | E21: 5737 | F21: 9008 | G21: 26656 | H21: 14834 | I21: 26560
A22: Net income | B22: 26301 | C22: 100118 | D22: 34540 | E22: 28196 | F22: 34979 | G22: 132170 | H22: 62578 | I22: 112193
A24: Common shareholder results
A25: Preferred stock dividends | I25: 86
A26: Net income available to common stockholders | I26: 112107
A27: Basic EPS | B27: 2.14 | C27: 8.13 | D27: 2.84 | E27: 2.33 | F27: 2.89 | G27: 10.91 | H27: 5.17 | I27: 9.23
A28: Diluted EPS | B28: 2.12 | C28: 8.04 | D28: 2.81 | E28: 2.31 | F28: 2.87 | G28: 10.81 | H28: 5.11 | I28: 9.11

Sheet Balance sheet
A1: Balance sheet
A2: USD millions. Each column is a point-in-time balance at the filing date.
A4: Reported line item | B4: Q3:24 | C4: Q4:24 | D4: Q1:25 | E4: Q2:25 | F4: Q3:25 | G4: Q4:25 | H4: Q1:26 | I4: Q2:26
A5: Reporting basis | B5: 2024-09-30 | C5: 2024-12-31 | D5: 2025-03-31 | E5: 2025-06-30 | F5: 2025-09-30 | G5: 2025-12-31 | H5: 2026-03-31 | I5: 2026-06-30
A7: Current assets
A8: Cash and cash equivalents | B8: 19959 | C8: 23466 | D8: 23264 | E8: 21036 | F8: 23090 | G8: 30708 | H8: 38063 | I8: 55911
A9: Marketable securities | B9: 73271 | C9: 72191 | D9: 72064 | E9: 74112 | F9: 75406 | G9: 96135 | H9: 88777 | I9: 186563
A10: Total cash, cash equivalents, and marketable securities | B10: 93230 | C10: 95657 | D10: 95328 | E10: 95148 | F10: 98496 | G10: 126843 | H10: 126840 | I10: 242474
A11: Accounts receivable, net | B11: 49104 | C11: 52340 | D11: 51000 | E11: 55048 | F11: 57148 | G11: 62886 | H11: 62999 | I11: 69175
A12: Inventory | I12: 9991
A13: Other current assets | B13: 15207 | C13: 15714 | D13: 15724 | E13: 16020 | F13: 18303 | G13: 16309 | H13: 23914 | I13: 21884
A14: Total current assets | B14: 157541 | C14: 163711 | D14: 162052 | E14: 166216 | F14: 173947 | G14: 206038 | H14: 213753 | I14: 343524
A16: Non-current assets
A17: Non-marketable securities | B17: 36177 | C17: 37982 | D17: 51029 | E17: 52574 | F17: 63800 | G17: 68687 | H17: 106946 | I17: 131461
A18: Deferred income taxes (asset) | B18: 15915 | C18: 17180 | D18: 18386 | E18: 19289 | F18: 10331 | G18: 9113 | H18: 1995 | I18: 1448
A19: Property and equipment, net | B19: 161270 | C19: 171036 | D19: 185062 | E19: 203231 | F19: 223787 | G19: 246597 | H19: 281020 | I19: 321212
A20: Operating lease assets | B20: 13561 | C20: 13588 | D20: 13722 | E20: 14255 | F20: 14524 | G20: 15221 | H20: 15509 | I20: 17694
A21: Goodwill | B21: 31935 | C21: 31885 | D21: 32173 | E21: 32335 | F21: 33269 | G21: 33380 | H21: 57774 | I21: 57828
A22: Intangible assets, net | H22: 9444 | I22: 9105
A23: Other non-current assets | B23: 13867 | C23: 14874 | D23: 12950 | E23: 14153 | F23: 16811 | G23: 16245 | H23: 17478 | I23: 39711
A24: Total assets | B24: 430266 | C24: 450256 | D24: 475374 | E24: 502053 | F24: 536469 | G24: 595281 | H24: 703919 | I24: 921983
A26: Current liabilities
A27: Accounts payable | B27: 7049 | C27: 7987 | D27: 8497 | E27: 8347 | F27: 10546 | G27: 12200 | H27: 16852 | I27: 20258
A28: Accrued compensation and benefits | B28: 12908 | C28: 15069 | D28: 9984 | E28: 12168 | F28: 13944 | G28: 17546 | H28: 13947 | I28: 15086
A29: Accrued expenses and other current liabilities | B29: 46585 | C29: 51228 | D29: 58300 | E29: 52039 | F29: 59437 | G29: 55557 | H29: 63019 | I29: 73014
A30: Accrued revenue share | B30: 9365 | C30: 9802 | D30: 9965 | E30: 9787 | F30: 10081 | G30: 10864 | H30: 10208 | I30: 10599
A31: Deferred revenue | B31: 4896 | C31: 5036 | D31: 4908 | E31: 4969 | F31: 5542 | G31: 6578 | H31: 7162 | I31: 7154
A32: Total current liabilities | B32: 80803 | C32: 89122 | D32: 91654 | E32: 87310 | F32: 99550 | G32: 102745 | H32: 111188 | I32: 126111
A34: Non-current liabilities
A35: Long-term debt | B35: 12297 | C35: 10883 | D35: 10886 | E35: 23607 | F35: 21607 | G35: 46547 | H35: 77501 | I35: 98165
A36: Deferred revenue, non-current | B36: 1015
A37: Income taxes payable, non-current | B37: 8219 | C37: 8782 | D37: 9773 | E37: 10027 | F37: 10072 | G37: 9531 | H37: 12457 | I37: 11306
A38: Deferred income taxes (liability) | B38: 706 | I38: 22819
A39: Operating lease liabilities | B39: 11654 | C39: 11691 | D39: 11678 | E39: 11952 | F39: 12106 | G39: 12744 | H39: 12983 | I39: 14591
A40: Other long-term liabilities | B40: 1453 | C40: 4694 | D40: 6116 | E40: 6241 | F40: 6267 | G40: 8449 | H40: 11044 | I40: 8511
A41: Total liabilities | B41: 116147 | C41: 125172 | D41: 130107 | E41: 139137 | F41: 149602 | G41: 180016 | H41: 225173 | I41: 281503
A43: Equity
A44: Preferred stock and additional paid-in capital | B44: 0 | C44: 0 | D44: 0 | E44: 0 | F44: 0 | G44: 0 | H44: 0 | I44: 18023
A45: Class A/B/C stock and additional paid-in capital | B45: 82030 | C45: 84800 | D45: 86725 | E45: 89283 | F45: 91695 | G45: 93126 | H45: 96902 | I45: 131371
A46: Accumulated other comprehensive income (loss) | B46: -3228 | C46: -4800 | D46: -4086 | E46: -2127 | F46: -2054 | G46: -1916 | H46: -2180 | I46: -2285
A47: Retained earnings | B47: 235317 | C47: 245084 | D47: 262628 | E47: 275760 | F47: 297226 | G47: 324055 | H47: 384024 | I47: 493371
A48: Total stockholders' equity | B48: 314119 | C48: 325084 | D48: 345267 | E48: 362916 | F48: 386867 | G48: 415265 | H48: 478746 | I48: 640480
A49: Total liabilities and stockholders' equity | B49: 430266 | C49: 450256 | D49: 475374 | E49: 502053 | F49: 536469 | G49: 595281 | H49: 703919 | I49: 921983

Sheet Cash flow
A1: Cash flow and FCF inputs
A2: Reported cash flows, USD millions. Q2/Q3 columns are year-to-date; Q4 filing columns are full year. No FCF is calculated.
A4: Reported line item | B4: Q3:24 | C4: Q4:24 | D4: Q1:25 | E4: Q2:25 | F4: Q3:25 | G4: Q4:25 | H4: Q1:26 | I4: Q2:26
A5: Reporting basis | B5: 9 months | C5: full year | D5: 3 months | E5: 6 months | F5: 9 months | G5: full year | H5: 3 months | I5: 6 months
A7: Operating activities
A8: Net income | B8: 73582 | C8: 100118 | D8: 34540 | E8: 62736 | F8: 97715 | G8: 132170 | H8: 62578 | I8: 174771
A9: Depreciation of property and equipment | B9: 11106 | C9: 15311 | D9: 4487 | E9: 9485 | F9: 15096 | G9: 21136 | H9: 6482 | I9: 13586
A10: Stock-based compensation expense | B10: 16975 | C10: 22785 | D10: 5516 | E10: 11514 | F10: 17882 | G10: 24953 | H10: 6751 | I10: 14708
A11: Deferred income taxes | B11: -3809 | C11: -5257 | D11: -1152 | E11: -1596 | F11: 7130 | G11: 8348 | H11: 6920 | I11: 27538
A12: Loss (gain) on debt and equity securities, net | B12: -2738 | C12: -2671 | D12: -9960 | E12: -11411 | F12: -22266 | G12: -24620 | H12: -36804 | I12: -135803
A13: Other | B13: 2592 | C13: 3419 | D13: 481 | E13: 1041 | F13: 843 | G13: 2108 | H13: 1265 | I13: 3161
A14: Accounts receivable, net | B14: -1321 | C14: -5891 | D14: 1638 | E14: -1201 | F14: -3582 | G14: -8779 | H14: -363 | I14: -6904
A15: Inventory | I15: -7739
A16: Income taxes, net | B16: -2797 | C16: -2418 | D16: 7197 | E16: -2434 | F16: -3292 | G16: -3226 | H16: 8101 | I16: 8304
A17: Other assets | B17: -2334 | C17: -1397 | D17: -1288 | E17: -2767 | F17: -4060 | G17: -4542 | H17: -3403 | I17: -9950
A18: Accounts payable | B18: -42 | C18: 359 | D18: -880 | E18: -327 | F18: -771 | G18: 907 | H18: -240 | I18: 2090
A19: Accrued expenses and other liabilities | B19: -6366 | C19: -1161 | D19: -5045 | E19: -1560 | F19: 6199 | G19: 12939 | H19: -6002 | I19: 308
A20: Accrued revenue share | B20: 478 | C20: 1059 | D20: 116 | E20: -219 | F20: 100 | G20: 899
A21: Deferred revenue | B21: 860 | C21: 1043 | D21: 500 | E21: 636 | F21: 1317 | G21: 2420 | H21: 505 | I21: 789
A22: Net cash from operating activities | B22: 86186 | C22: 125299 | D22: 36150 | E22: 63897 | F22: 112311 | G22: 164713 | H22: 45790 | I22: 84859
A24: Investing activities
A25: Purchases of property and equipment | B25: -38259 | C25: -52535 | D25: -17197 | E25: -39643 | F25: -63596 | G25: -91447 | H25: -35674 | I25: -80598
A26: Purchases of marketable securities | B26: -65034 | C26: -86679 | D26: -18453 | E26: -39870 | F26: -60834 | G26: -103773 | H26: -31041 | I26: -76480
A27: Maturities and sales of marketable securities | B27: 81779 | C27: 103428 | D27: 20345 | E27: 40930 | F27: 61301 | G27: 83240 | H27: 38001 | I27: 66696
A28: Purchases of non-marketable securities | B28: -3234 | C28: -5034 | D28: -958 | E28: -2312 | F28: -3312 | G28: -5716 | H28: -906 | I28: -22051
A29: Maturities and sales of non-marketable securities | B29: 732 | C29: 882 | D29: 259 | E29: 873 | F29: 1196 | G29: 1367 | H29: 848 | I29: 1667
A30: Acquisitions, net of cash acquired, and purchases of intangible assets | B30: -2840 | C30: -2931 | D30: -340 | E30: -353 | F30: -1425 | G30: -1592 | H30: -33621 | I30: -33697
A31: Other investing activities | B31: -2500 | C31: -2667 | D31: 150 | E31: -363 | F31: -1845 | G31: -2370 | H31: -996 | I31: -1359
A32: Net cash from investing activities | B32: -29356 | C32: -45536 | D32: -16194 | E32: -40738 | F32: -68515 | G32: -120291 | H32: -63389 | I32: -145822
A34: Financing activities
A35: Net payments related to stock-based award activities | B35: -9141 | C35: -12190 | D35: -3110 | E35: -5731 | F35: -9001 | G35: -14167 | H35: -5483 | I35: -12056
A36: Repurchases of stock | B36: -46671 | C36: -62222 | D36: -15068 | E36: -28706 | F36: -40210 | G36: -45709 | H36: 0 | I36: 0
A37: Dividend payments | B37: -4921 | C37: -7363 | D37: -2434 | E37: -4977 | F37: -7513 | G37: -10049 | H37: -2542 | I37: -5231
A38: Proceeds from issuance of common stock, net of costs | I38: 30499
A39: Proceeds from issuance of mandatory convertible preferred stock, net of costs | I39: 19063
A40: Proceeds from issuance of debt, net of costs | B40: 8694 | C40: 13589 | D40: 4532 | E40: 31378 | F40: 38002 | G40: 64564 | H40: 31379 | I40: 56226
A41: Repayments of debt | B41: -8951 | C41: -12701 | D41: -4521 | E41: -18397 | F41: -26094 | G41: -32427 | H41: -1477 | I41: -5253
A42: Proceeds from sale of interest in consolidated entities, net | B42: 293 | C42: 1154 | D42: 400 | E42: 400 | F42: 400 | G42: 400 | H42: 3200 | I42: 3758
A43: Other financing activities | I43: -686
A44: Net cash from financing activities | B44: -60697 | C44: -79733 | D44: -20201 | E44: -26033 | F44: -44416 | G44: -37388 | H44: 25077 | I44: 86320
A46: Cash reconciliation and supplemental
A47: Effect of exchange rate changes on cash and cash equivalents | B47: -222 | C47: -612 | D47: 43 | E47: 444 | F47: 244 | G47: 208 | H47: -123 | I47: -154
A48: Net increase (decrease) in cash and cash equivalents | B48: -4089 | C48: -582 | D48: -202 | E48: -2430 | F48: -376 | G48: 7242 | H48: 7355 | I48: 25203
A49: Cash and cash equivalents at beginning of period | B49: 24048 | C49: 24048 | D49: 23466 | E49: 23466 | F49: 23466 | G49: 23466 | H49: 30708 | I49: 30708
A50: Cash and cash equivalents at end of period | B50: 19959 | C50: 23466 | D50: 23264 | E50: 21036 | F50: 23090 | G50: 30708 | H50: 38063 | I50: 55911
A51: Property and equipment included in accrued liabilities and accounts payable | G51: 15090 | H51: 24131 | I51: 29113

Sheet Revenue breakdown
A1: Revenue breakdown
A2: USD millions. Product lines are reported for three months except full-year 10-K columns.
A4: Reported line item | B4: Q3:24 | C4: Q4:24 | D4: Q1:25 | E4: Q2:25 | F4: Q3:25 | G4: Q4:25 | H4: Q1:26 | I4: Q2:26
A5: Reporting basis | B5: 3 months | C5: full year | D5: 3 months | E5: 3 months | F5: 3 months | G5: full year | H5: 3 months | I5: 3 months
A7: Google Services
A8: Google Search & other | B8: 49385 | C8: 198084 | D8: 50702 | E8: 54190 | F8: 56567 | G8: 224532 | H8: 60399 | I8: 63271
A9: YouTube ads | B9: 8921 | C9: 36147 | D9: 8927 | E9: 9796 | F9: 10261 | G9: 40367 | H9: 9883 | I9: 11055
A10: Google Network | B10: 7548 | C10: 30359 | D10: 7256 | E10: 7354 | F10: 7354 | G10: 29792 | H10: 6971 | I10: 7303
A11: Google advertising | B11: 65854 | C11: 264590 | D11: 66885 | E11: 71340 | F11: 74182 | G11: 294691 | H11: 77253 | I11: 81629
A12: Google subscriptions, platforms, and devices | B12: 10656 | C12: 40340 | D12: 10379 | E12: 11203 | F12: 12870 | G12: 48030 | H12: 12384 | I12: 12911
A13: Google Services total | B13: 76510 | C13: 304930 | D13: 77264 | E13: 82543 | F13: 87052 | G13: 342721 | H13: 89637 | I13: 94540
A15: Other segments and total
A16: Google Cloud | B16: 11353 | C16: 43229 | D16: 12260 | E16: 13624 | F16: 15157 | G16: 58705 | H16: 20028 | I16: 24768
A17: Other Bets | B17: 388 | C17: 1648 | D17: 450 | E17: 373 | F17: 344 | G17: 1537 | H17: 411 | I17: 382
A18: Hedging gains (losses) | B18: 17 | C18: 211 | D18: 260 | E18: -112 | F18: -207 | G18: -127 | H18: -180 | I18: 106
A19: Total revenues | B19: 88268 | C19: 350018 | D19: 90234 | E19: 96428 | F19: 102346 | G19: 402836 | H19: 109896 | I19: 119796

Sheet Segment breakdown
A1: Segment breakdown
A2: USD millions. Segment results include allocated costs; Q4 filing columns contain full-year totals.
A4: Reported line item | B4: Q3:24 | C4: Q4:24 | D4: Q1:25 | E4: Q2:25 | F4: Q3:25 | G4: Q4:25 | H4: Q1:26 | I4: Q2:26
A5: Reporting basis | B5: 3 months | C5: full year | D5: 3 months | E5: 3 months | F5: 3 months | G5: full year | H5: 3 months | I5: 3 months
A7: Segment revenue
A8: Google Services | B8: 76510 | C8: 304930 | D8: 77264 | E8: 82543 | F8: 87052 | G8: 342721 | H8: 89637 | I8: 94540
A9: Google Cloud | B9: 11353 | C9: 43229 | D9: 12260 | E9: 13624 | F9: 15157 | G9: 58705 | H9: 20028 | I9: 24768
A10: Other Bets | B10: 388 | C10: 1648 | D10: 450 | E10: 373 | F10: 344 | G10: 1537 | H10: 411 | I10: 382
A11: Hedging gains (losses) | B11: 17 | C11: 211 | D11: 260 | E11: -112 | F11: -207 | G11: -127 | H11: -180 | I11: 106
A12: Total revenues | B12: 88268 | C12: 350018 | D12: 90234 | E12: 96428 | F12: 102346 | G12: 402836 | H12: 109896 | I12: 119796
A14: Segment operating income
A15: Google Services | B15: 30856 | C15: 121263 | D15: 32682 | E15: 33063 | F15: 33527 | G15: 139404 | H15: 40589 | I15: 39544
A16: Google Cloud | B16: 1947 | C16: 6112 | D16: 2177 | E16: 2826 | F16: 3594 | G16: 13910 | H16: 6598 | I16: 8814
A17: Other Bets | B17: -1116 | C17: -4444 | D17: -1226 | E17: -1246 | F17: -1426 | G17: -7515 | H17: -2100 | I17: -1799
A18: Alphabet-level activities | B18: -3166 | C18: -10541 | D18: -3027 | E18: -3372 | F18: -4467 | G18: -16760 | H18: -5391 | I18: -5789
A19: Total income from operations | B19: 28521 | C19: 112390 | D19: 30606 | E19: 31271 | F19: 31228 | G19: 129039 | H19: 39696 | I19: 40770
A21: Google Services costs
A22: Employee compensation expenses | C22: 44560 | D22: 11337 | E22: 11306 | F22: 11070 | G22: 45124 | H22: 12206 | I22: 12275
A23: Other costs and expenses | C23: 139107 | D23: 33245 | E23: 38174 | F23: 42455 | G23: 158193 | H23: 36842 | I23: 42721
A24: Total Google Services costs and expenses | C24: 183667 | D24: 44582 | E24: 49480 | F24: 53525 | G24: 203317 | H24: 49048 | I24: 54996
A26: Google Cloud costs
A27: Employee compensation expenses | C27: 20519 | D27: 5412 | E27: 5517 | F27: 5586 | G27: 22078 | H27: 6443 | I27: 6933
A28: Other costs and expenses | C28: 16598 | D28: 4671 | E28: 5281 | F28: 5977 | G28: 22717 | H28: 6987 | I28: 9021
A29: Total Google Cloud costs and expenses | C29: 37117 | D29: 10083 | E29: 10798 | F29: 11563 | G29: 44795 | H29: 13430 | I29: 15954

Sheet Sources and basis
A1: Sources and reporting basis
A2: Eight filings through June 2026. Blanks mean the line was not reported in that period; zero means a reported zero.
A4: Filing period | B4: Form | C4: Period end | D4: Income / revenue / segment | E4: Cash flow | F4: SEC filing URL
A5: Q3:24 | B5: 10-Q | C5: 2024-09-30 | D5: 3 months | E5: 9 months | F5: https://www.sec.gov/Archives/edgar/data/1652044/000165204424000118/goog-20240930.htm
A6: Q4:24 | B6: 10-K | C6: 2024-12-31 | D6: full year | E6: full year | F6: https://www.sec.gov/Archives/edgar/data/1652044/000165204425000014/goog-20241231.htm
A7: Q1:25 | B7: 10-Q | C7: 2025-03-31 | D7: 3 months | E7: 3 months | F7: https://www.sec.gov/Archives/edgar/data/1652044/000165204425000043/goog-20250331.htm
A8: Q2:25 | B8: 10-Q | C8: 2025-06-30 | D8: 3 months | E8: 6 months | F8: https://www.sec.gov/Archives/edgar/data/1652044/000165204425000062/goog-20250630.htm
A9: Q3:25 | B9: 10-Q | C9: 2025-09-30 | D9: 3 months | E9: 9 months | F9: https://www.sec.gov/Archives/edgar/data/1652044/000165204425000091/goog-20250930.htm
A10: Q4:25 | B10: 10-K | C10: 2025-12-31 | D10: full year | E10: full year | F10: https://www.sec.gov/Archives/edgar/data/1652044/000165204426000018/goog-20251231.htm
A11: Q1:26 | B11: 10-Q | C11: 2026-03-31 | D11: 3 months | E11: 3 months | F11: https://www.sec.gov/Archives/edgar/data/1652044/000165204426000048/goog-20260331.htm
